import java.util.Vector;

public final class ae implements Runnable {
  ag a;
  
  Vector a;
  
  Vector b;
  
  boolean a;
  
  public int a;
  
  public static int b;
  
  private int c;
  
  public boolean b;
  
  public Vector c = true;
  
  public ae() {
    this.c = new Vector();
    v.a(this);
  }
  
  private synchronized void b() {
    // Byte code:
    //   0: aload_0
    //   1: invokespecial c : ()V
    //   4: aload_0
    //   5: getfield a : Lag;
    //   8: invokeinterface a : ()[B
    //   13: astore_1
    //   14: new java/io/ByteArrayInputStream
    //   17: dup
    //   18: aload_1
    //   19: invokespecial <init> : ([B)V
    //   22: astore_1
    //   23: new java/io/DataInputStream
    //   26: dup
    //   27: aload_1
    //   28: invokespecial <init> : (Ljava/io/InputStream;)V
    //   31: astore_2
    //   32: aload_2
    //   33: invokevirtual readInt : ()I
    //   36: istore_3
    //   37: iconst_0
    //   38: istore #5
    //   40: iload #5
    //   42: iload_3
    //   43: if_icmpge -> 105
    //   46: iconst_4
    //   47: anewarray java/lang/Object
    //   50: dup
    //   51: astore #4
    //   53: iconst_0
    //   54: aload_2
    //   55: invokevirtual readUTF : ()Ljava/lang/String;
    //   58: aastore
    //   59: aload #4
    //   61: iconst_1
    //   62: aload_2
    //   63: invokevirtual readUTF : ()Ljava/lang/String;
    //   66: aastore
    //   67: aload #4
    //   69: iconst_2
    //   70: aload_2
    //   71: invokevirtual readUTF : ()Ljava/lang/String;
    //   74: aastore
    //   75: aload #4
    //   77: iconst_3
    //   78: new java/lang/Long
    //   81: dup
    //   82: aload_2
    //   83: invokevirtual readLong : ()J
    //   86: invokespecial <init> : (J)V
    //   89: aastore
    //   90: aload_0
    //   91: getfield a : Ljava/util/Vector;
    //   94: aload #4
    //   96: invokevirtual addElement : (Ljava/lang/Object;)V
    //   99: iinc #5, 1
    //   102: goto -> 40
    //   105: aload_2
    //   106: invokevirtual close : ()V
    //   109: aload_1
    //   110: invokevirtual close : ()V
    //   113: return
    //   114: pop
    //   115: return
    // Exception table:
    //   from	to	target	type
    //   0	32	114	java/lang/Throwable
    //   32	113	114	java/lang/Throwable
  }
  
  public final synchronized boolean a() {
    // Byte code:
    //   0: aload_0
    //   1: invokespecial c : ()V
    //   4: new java/io/ByteArrayOutputStream
    //   7: dup
    //   8: invokespecial <init> : ()V
    //   11: astore_1
    //   12: new java/io/DataOutputStream
    //   15: dup
    //   16: aload_1
    //   17: invokespecial <init> : (Ljava/io/OutputStream;)V
    //   20: astore_2
    //   21: aload_0
    //   22: getfield a : Ljava/util/Vector;
    //   25: invokevirtual size : ()I
    //   28: istore_3
    //   29: aload_2
    //   30: iload_3
    //   31: invokevirtual writeInt : (I)V
    //   34: iconst_0
    //   35: istore #5
    //   37: iload #5
    //   39: iload_3
    //   40: if_icmpge -> 119
    //   43: aload_0
    //   44: getfield a : Ljava/util/Vector;
    //   47: iload #5
    //   49: invokevirtual elementAt : (I)Ljava/lang/Object;
    //   52: checkcast [Ljava/lang/Object;
    //   55: astore #4
    //   57: aload_2
    //   58: aload #4
    //   60: iconst_0
    //   61: aaload
    //   62: checkcast java/lang/String
    //   65: invokestatic i : (Ljava/lang/String;)Ljava/lang/String;
    //   68: invokevirtual writeUTF : (Ljava/lang/String;)V
    //   71: aload_2
    //   72: aload #4
    //   74: iconst_1
    //   75: aaload
    //   76: checkcast java/lang/String
    //   79: invokestatic i : (Ljava/lang/String;)Ljava/lang/String;
    //   82: invokevirtual writeUTF : (Ljava/lang/String;)V
    //   85: aload_2
    //   86: aload #4
    //   88: iconst_2
    //   89: aaload
    //   90: checkcast java/lang/String
    //   93: invokestatic i : (Ljava/lang/String;)Ljava/lang/String;
    //   96: invokevirtual writeUTF : (Ljava/lang/String;)V
    //   99: aload_2
    //   100: aload #4
    //   102: iconst_3
    //   103: aaload
    //   104: checkcast java/lang/Long
    //   107: invokevirtual longValue : ()J
    //   110: invokevirtual writeLong : (J)V
    //   113: iinc #5, 1
    //   116: goto -> 37
    //   119: aload_0
    //   120: getfield a : Lag;
    //   123: aload_1
    //   124: invokevirtual toByteArray : ()[B
    //   127: invokeinterface a : ([B)Z
    //   132: pop
    //   133: aload_2
    //   134: invokevirtual close : ()V
    //   137: aload_1
    //   138: invokevirtual close : ()V
    //   141: aload_0
    //   142: iconst_0
    //   143: putfield a : Z
    //   146: iconst_1
    //   147: ireturn
    //   148: pop
    //   149: iconst_0
    //   150: ireturn
    // Exception table:
    //   from	to	target	type
    //   0	147	148	java/lang/Throwable
  }
  
  public final boolean a(a parama) {
    // Byte code:
    //   0: aload_1
    //   1: iconst_0
    //   2: invokevirtual a : (Z)Ljava/lang/String;
    //   5: astore_2
    //   6: aload_1
    //   7: invokevirtual a : ()Ljava/lang/String;
    //   10: astore_3
    //   11: aload_0
    //   12: aload_2
    //   13: aload_3
    //   14: invokespecial a : (Ljava/lang/String;Ljava/lang/String;)Ljava/lang/String;
    //   17: astore_2
    //   18: bipush #9
    //   20: anewarray java/lang/Object
    //   23: dup
    //   24: astore_3
    //   25: iconst_0
    //   26: aload_2
    //   27: aastore
    //   28: aload_3
    //   29: iconst_1
    //   30: aload_1
    //   31: getfield a : [Ljava/lang/Object;
    //   34: aastore
    //   35: aload_3
    //   36: iconst_2
    //   37: aload_1
    //   38: getfield a : [Lah;
    //   41: aastore
    //   42: aload_3
    //   43: iconst_3
    //   44: iconst_5
    //   45: newarray int
    //   47: dup
    //   48: iconst_0
    //   49: aload_1
    //   50: getfield a : Lv;
    //   53: getfield as : I
    //   56: iastore
    //   57: dup
    //   58: iconst_1
    //   59: aload_1
    //   60: getfield a : Lv;
    //   63: getfield ar : I
    //   66: iastore
    //   67: dup
    //   68: iconst_2
    //   69: aload_1
    //   70: getfield a : Lv;
    //   73: getfield ac : I
    //   76: iastore
    //   77: dup
    //   78: iconst_3
    //   79: aload_1
    //   80: getfield m : I
    //   83: iastore
    //   84: dup
    //   85: iconst_4
    //   86: aload_1
    //   87: getfield a : Lv;
    //   90: getfield az : I
    //   93: iastore
    //   94: aastore
    //   95: aload_3
    //   96: iconst_4
    //   97: aload_1
    //   98: getfield a : [Z
    //   101: aastore
    //   102: aload_3
    //   103: iconst_5
    //   104: aload_1
    //   105: getfield b : [Z
    //   108: aastore
    //   109: aload_3
    //   110: bipush #6
    //   112: aload_1
    //   113: getfield e : [I
    //   116: aastore
    //   117: aload_3
    //   118: bipush #7
    //   120: aload_1
    //   121: getfield f : [I
    //   124: aastore
    //   125: aload_3
    //   126: bipush #8
    //   128: iconst_1
    //   129: newarray boolean
    //   131: dup
    //   132: iconst_0
    //   133: aload_1
    //   134: getfield J : Z
    //   137: bastore
    //   138: aastore
    //   139: iconst_m1
    //   140: istore_1
    //   141: iconst_0
    //   142: istore #4
    //   144: iload #4
    //   146: aload_0
    //   147: getfield b : Ljava/util/Vector;
    //   150: invokevirtual size : ()I
    //   153: if_icmpge -> 198
    //   156: aload_0
    //   157: getfield b : Ljava/util/Vector;
    //   160: iload #4
    //   162: invokevirtual elementAt : (I)Ljava/lang/Object;
    //   165: checkcast [Ljava/lang/Object;
    //   168: iconst_0
    //   169: aaload
    //   170: aload_2
    //   171: invokevirtual equals : (Ljava/lang/Object;)Z
    //   174: ifeq -> 192
    //   177: iload #4
    //   179: istore_1
    //   180: aload_0
    //   181: getfield b : Ljava/util/Vector;
    //   184: aload_3
    //   185: iload_1
    //   186: invokevirtual setElementAt : (Ljava/lang/Object;I)V
    //   189: goto -> 198
    //   192: iinc #4, 1
    //   195: goto -> 144
    //   198: aload_0
    //   199: getfield b : Ljava/util/Vector;
    //   202: invokevirtual size : ()I
    //   205: getstatic v.m : I
    //   208: if_icmplt -> 229
    //   211: aload_0
    //   212: getfield b : Ljava/util/Vector;
    //   215: aload_0
    //   216: getfield b : Ljava/util/Vector;
    //   219: invokevirtual firstElement : ()Ljava/lang/Object;
    //   222: invokevirtual removeElement : (Ljava/lang/Object;)Z
    //   225: pop
    //   226: goto -> 198
    //   229: iload_1
    //   230: iconst_m1
    //   231: if_icmpne -> 242
    //   234: aload_0
    //   235: getfield b : Ljava/util/Vector;
    //   238: aload_3
    //   239: invokevirtual addElement : (Ljava/lang/Object;)V
    //   242: iconst_1
    //   243: ireturn
    //   244: pop
    //   245: iconst_0
    //   246: ireturn
    // Exception table:
    //   from	to	target	type
    //   0	243	244	java/lang/Exception
  }
  
  public final boolean b(a parama) {
    // Byte code:
    //   0: aload_1
    //   1: iconst_0
    //   2: invokevirtual a : (Z)Ljava/lang/String;
    //   5: astore_2
    //   6: aload_1
    //   7: invokevirtual a : ()Ljava/lang/String;
    //   10: astore_3
    //   11: aload_0
    //   12: aload_2
    //   13: aload_3
    //   14: invokespecial a : (Ljava/lang/String;Ljava/lang/String;)Ljava/lang/String;
    //   17: dup
    //   18: astore #4
    //   20: ifnull -> 34
    //   23: aload_0
    //   24: aload_1
    //   25: aload #4
    //   27: invokespecial a : (La;Ljava/lang/String;)Z
    //   30: istore_2
    //   31: goto -> 232
    //   34: aload_0
    //   35: astore #4
    //   37: new java/lang/StringBuffer
    //   40: dup
    //   41: invokespecial <init> : ()V
    //   44: astore #5
    //   46: iconst_0
    //   47: istore #6
    //   49: new java/lang/StringBuffer
    //   52: dup
    //   53: invokespecial <init> : ()V
    //   56: astore #7
    //   58: aload #7
    //   60: iconst_0
    //   61: invokevirtual setLength : (I)V
    //   64: aload #7
    //   66: ldc '000'
    //   68: invokevirtual append : (Ljava/lang/String;)Ljava/lang/StringBuffer;
    //   71: iload #6
    //   73: invokestatic toHexString : (I)Ljava/lang/String;
    //   76: invokevirtual toLowerCase : ()Ljava/lang/String;
    //   79: invokevirtual append : (Ljava/lang/String;)Ljava/lang/StringBuffer;
    //   82: pop
    //   83: aload #7
    //   85: iconst_0
    //   86: aload #7
    //   88: invokevirtual length : ()I
    //   91: iconst_4
    //   92: isub
    //   93: invokevirtual delete : (II)Ljava/lang/StringBuffer;
    //   96: astore #7
    //   98: aload #5
    //   100: iconst_0
    //   101: invokevirtual setLength : (I)V
    //   104: aload #5
    //   106: ldc 'opr'
    //   108: invokevirtual append : (Ljava/lang/String;)Ljava/lang/StringBuffer;
    //   111: aload #7
    //   113: invokevirtual append : (Ljava/lang/Object;)Ljava/lang/StringBuffer;
    //   116: ldc '.omc'
    //   118: invokevirtual append : (Ljava/lang/String;)Ljava/lang/StringBuffer;
    //   121: pop
    //   122: aload #4
    //   124: aload #5
    //   126: invokevirtual toString : ()Ljava/lang/String;
    //   129: invokevirtual a : (Ljava/lang/String;)[Ljava/lang/Object;
    //   132: ifnull -> 139
    //   135: iconst_1
    //   136: goto -> 140
    //   139: iconst_0
    //   140: ifeq -> 153
    //   143: iinc #6, 1
    //   146: iload #6
    //   148: ldc 65535
    //   150: if_icmplt -> 58
    //   153: aload #5
    //   155: invokevirtual toString : ()Ljava/lang/String;
    //   158: astore #4
    //   160: aload_0
    //   161: aload_1
    //   162: aload #4
    //   164: invokespecial a : (La;Ljava/lang/String;)Z
    //   167: pop
    //   168: aload_0
    //   169: aload #4
    //   171: aload_2
    //   172: aload_3
    //   173: astore #6
    //   175: astore_1
    //   176: astore #5
    //   178: astore #4
    //   180: iconst_4
    //   181: anewarray java/lang/Object
    //   184: dup
    //   185: astore #7
    //   187: iconst_0
    //   188: aload #5
    //   190: aastore
    //   191: aload #7
    //   193: iconst_1
    //   194: aload_1
    //   195: aastore
    //   196: aload #7
    //   198: iconst_2
    //   199: aload #6
    //   201: aastore
    //   202: aload #7
    //   204: iconst_3
    //   205: new java/lang/Long
    //   208: dup
    //   209: invokestatic currentTimeMillis : ()J
    //   212: invokespecial <init> : (J)V
    //   215: aastore
    //   216: aload #4
    //   218: getfield a : Ljava/util/Vector;
    //   221: aload #7
    //   223: invokevirtual addElement : (Ljava/lang/Object;)V
    //   226: aload #4
    //   228: invokevirtual a : ()Z
    //   231: istore_2
    //   232: aload_0
    //   233: dup
    //   234: astore #4
    //   236: getfield a : Lag;
    //   239: getstatic v.S : Ljava/lang/String;
    //   242: invokeinterface a : (Ljava/lang/String;)V
    //   247: aload #4
    //   249: getfield a : Lag;
    //   252: iconst_1
    //   253: invokeinterface a : (Z)J
    //   258: bipush #10
    //   260: lshr
    //   261: getstatic v.bx : I
    //   264: i2l
    //   265: lcmp
    //   266: ifle -> 276
    //   269: aload_0
    //   270: invokespecial b : ()Z
    //   273: ifne -> 232
    //   276: iload_2
    //   277: ireturn
    //   278: pop
    //   279: iconst_0
    //   280: ireturn
    // Exception table:
    //   from	to	target	type
    //   0	277	278	java/lang/Exception
  }
  
  public final e a(String paramString1, String paramString2) {
    try {
      Object[] arrayOfObject = a(paramString1, paramString2);
      return a(arrayOfObject);
    } catch (Exception exception) {
      return null;
    } 
  }
  
  public final boolean a(String paramString1, String paramString2, boolean paramBoolean) {
    // Byte code:
    //   0: iconst_0
    //   1: istore_3
    //   2: aload_0
    //   3: aload_1
    //   4: aload_2
    //   5: invokespecial a : (Ljava/lang/String;Ljava/lang/String;)[Ljava/lang/Object;
    //   8: dup
    //   9: astore_1
    //   10: ifnull -> 96
    //   13: aload_0
    //   14: getfield a : Ljava/util/Vector;
    //   17: aload_1
    //   18: invokevirtual removeElement : (Ljava/lang/Object;)Z
    //   21: ifeq -> 42
    //   24: aload_0
    //   25: aload_1
    //   26: iconst_0
    //   27: aaload
    //   28: checkcast java/lang/String
    //   31: invokevirtual a : (Ljava/lang/String;)Z
    //   34: ifeq -> 42
    //   37: aload_0
    //   38: invokevirtual a : ()Z
    //   41: istore_3
    //   42: iconst_0
    //   43: istore_2
    //   44: iload_2
    //   45: aload_0
    //   46: getfield b : Ljava/util/Vector;
    //   49: invokevirtual size : ()I
    //   52: if_icmpge -> 96
    //   55: aload_0
    //   56: getfield b : Ljava/util/Vector;
    //   59: iload_2
    //   60: invokevirtual elementAt : (I)Ljava/lang/Object;
    //   63: checkcast [Ljava/lang/Object;
    //   66: iconst_0
    //   67: aaload
    //   68: checkcast java/lang/String
    //   71: aload_1
    //   72: iconst_0
    //   73: aaload
    //   74: invokevirtual equals : (Ljava/lang/Object;)Z
    //   77: ifeq -> 90
    //   80: aload_0
    //   81: getfield b : Ljava/util/Vector;
    //   84: iload_2
    //   85: invokevirtual removeElementAt : (I)V
    //   88: iconst_1
    //   89: istore_3
    //   90: iinc #2, 1
    //   93: goto -> 44
    //   96: iload_3
    //   97: ireturn
  }
  
  private synchronized boolean a(a parama, String paramString) {
    // Byte code:
    //   0: aload_0
    //   1: getfield a : Lag;
    //   4: new java/lang/StringBuffer
    //   7: dup
    //   8: getstatic v.S : Ljava/lang/String;
    //   11: invokespecial <init> : (Ljava/lang/String;)V
    //   14: aload_2
    //   15: invokevirtual append : (Ljava/lang/String;)Ljava/lang/StringBuffer;
    //   18: invokevirtual toString : ()Ljava/lang/String;
    //   21: invokeinterface a : (Ljava/lang/String;)V
    //   26: aload_1
    //   27: invokevirtual c : ()Z
    //   30: ifne -> 45
    //   33: aload_0
    //   34: getfield a : Lag;
    //   37: invokeinterface b : ()Z
    //   42: ifne -> 245
    //   45: new java/io/ByteArrayOutputStream
    //   48: dup
    //   49: invokespecial <init> : ()V
    //   52: astore_3
    //   53: new java/io/DataOutputStream
    //   56: dup
    //   57: aload_3
    //   58: invokespecial <init> : (Ljava/io/OutputStream;)V
    //   61: astore #4
    //   63: aload_1
    //   64: getfield d : Ljava/lang/String;
    //   67: ifnull -> 80
    //   70: aload_1
    //   71: getfield d : Ljava/lang/String;
    //   74: invokevirtual length : ()I
    //   77: ifne -> 93
    //   80: aload_1
    //   81: aload_1
    //   82: getfield a : [Ljava/lang/Object;
    //   85: iconst_1
    //   86: aaload
    //   87: checkcast java/lang/String
    //   90: putfield d : Ljava/lang/String;
    //   93: aload_1
    //   94: getfield d : Ljava/lang/String;
    //   97: invokevirtual toCharArray : ()[C
    //   100: dup
    //   101: astore #5
    //   103: iconst_0
    //   104: aload #5
    //   106: arraylength
    //   107: aconst_null
    //   108: iconst_0
    //   109: iconst_1
    //   110: invokestatic a : ([CII[BIZ)I
    //   113: dup
    //   114: istore #6
    //   116: newarray byte
    //   118: astore #7
    //   120: aload #5
    //   122: iconst_0
    //   123: aload #5
    //   125: arraylength
    //   126: aload #7
    //   128: iconst_0
    //   129: iconst_0
    //   130: invokestatic a : ([CII[BIZ)I
    //   133: pop
    //   134: aload #4
    //   136: iload #6
    //   138: invokevirtual writeShort : (I)V
    //   141: aload #4
    //   143: aload #7
    //   145: invokevirtual write : ([B)V
    //   148: aload #4
    //   150: aload_1
    //   151: getfield c : Ljava/lang/String;
    //   154: ifnonnull -> 162
    //   157: ldc 'null'
    //   159: goto -> 166
    //   162: aload_1
    //   163: getfield c : Ljava/lang/String;
    //   166: invokevirtual writeUTF : (Ljava/lang/String;)V
    //   169: aload #4
    //   171: aload_1
    //   172: getfield a : Ljava/lang/String;
    //   175: ifnonnull -> 183
    //   178: ldc 'null'
    //   180: goto -> 187
    //   183: aload_1
    //   184: getfield a : Ljava/lang/String;
    //   187: invokevirtual writeUTF : (Ljava/lang/String;)V
    //   190: aload #4
    //   192: aload_1
    //   193: getfield b : Lh;
    //   196: invokevirtual size : ()I
    //   199: invokevirtual writeInt : (I)V
    //   202: aload #4
    //   204: aload_1
    //   205: getfield b : Lh;
    //   208: invokevirtual toByteArray : ()[B
    //   211: iconst_0
    //   212: aload_1
    //   213: getfield b : Lh;
    //   216: invokevirtual size : ()I
    //   219: invokevirtual write : ([BII)V
    //   222: aload_0
    //   223: getfield a : Lag;
    //   226: aload_3
    //   227: invokevirtual toByteArray : ()[B
    //   230: invokeinterface a : ([B)Z
    //   235: pop
    //   236: aload #4
    //   238: invokevirtual close : ()V
    //   241: aload_3
    //   242: invokevirtual close : ()V
    //   245: bipush #9
    //   247: anewarray java/lang/Object
    //   250: dup
    //   251: astore_3
    //   252: iconst_0
    //   253: aload_2
    //   254: aastore
    //   255: aload_3
    //   256: iconst_1
    //   257: aload_1
    //   258: getfield a : [Ljava/lang/Object;
    //   261: aastore
    //   262: aload_3
    //   263: iconst_2
    //   264: aload_1
    //   265: getfield a : [Lah;
    //   268: aastore
    //   269: aload_3
    //   270: iconst_3
    //   271: iconst_5
    //   272: newarray int
    //   274: dup
    //   275: iconst_0
    //   276: aload_1
    //   277: getfield a : Lv;
    //   280: getfield as : I
    //   283: iastore
    //   284: dup
    //   285: iconst_1
    //   286: aload_1
    //   287: getfield a : Lv;
    //   290: getfield ar : I
    //   293: iastore
    //   294: dup
    //   295: iconst_2
    //   296: aload_1
    //   297: getfield a : Lv;
    //   300: getfield ac : I
    //   303: iastore
    //   304: dup
    //   305: iconst_3
    //   306: aload_1
    //   307: getfield m : I
    //   310: iastore
    //   311: dup
    //   312: iconst_4
    //   313: aload_1
    //   314: getfield a : Lv;
    //   317: getfield az : I
    //   320: iastore
    //   321: aastore
    //   322: aload_3
    //   323: iconst_4
    //   324: aload_1
    //   325: getfield a : [Z
    //   328: aastore
    //   329: aload_3
    //   330: iconst_5
    //   331: aload_1
    //   332: getfield b : [Z
    //   335: aastore
    //   336: aload_3
    //   337: bipush #6
    //   339: aload_1
    //   340: getfield e : [I
    //   343: aastore
    //   344: aload_3
    //   345: bipush #7
    //   347: aload_1
    //   348: getfield f : [I
    //   351: aastore
    //   352: aload_3
    //   353: bipush #8
    //   355: iconst_1
    //   356: newarray boolean
    //   358: dup
    //   359: iconst_0
    //   360: aload_1
    //   361: getfield J : Z
    //   364: bastore
    //   365: aastore
    //   366: iconst_0
    //   367: istore #5
    //   369: iload #5
    //   371: aload_0
    //   372: getfield b : Ljava/util/Vector;
    //   375: invokevirtual size : ()I
    //   378: if_icmpge -> 420
    //   381: aload_0
    //   382: getfield b : Ljava/util/Vector;
    //   385: iload #5
    //   387: invokevirtual elementAt : (I)Ljava/lang/Object;
    //   390: checkcast [Ljava/lang/Object;
    //   393: iconst_0
    //   394: aaload
    //   395: aload_2
    //   396: invokevirtual equals : (Ljava/lang/Object;)Z
    //   399: ifeq -> 414
    //   402: aload_0
    //   403: getfield b : Ljava/util/Vector;
    //   406: iload #5
    //   408: invokevirtual removeElementAt : (I)V
    //   411: goto -> 420
    //   414: iinc #5, 1
    //   417: goto -> 369
    //   420: aload_0
    //   421: getfield b : Ljava/util/Vector;
    //   424: invokevirtual size : ()I
    //   427: getstatic v.m : I
    //   430: if_icmplt -> 451
    //   433: aload_0
    //   434: getfield b : Ljava/util/Vector;
    //   437: aload_0
    //   438: getfield b : Ljava/util/Vector;
    //   441: invokevirtual firstElement : ()Ljava/lang/Object;
    //   444: invokevirtual removeElement : (Ljava/lang/Object;)Z
    //   447: pop
    //   448: goto -> 420
    //   451: aload_0
    //   452: getfield b : Ljava/util/Vector;
    //   455: aload_3
    //   456: invokevirtual addElement : (Ljava/lang/Object;)V
    //   459: iconst_1
    //   460: ireturn
  }
  
  private synchronized e a(Object[] paramArrayOfObject) {
    // Byte code:
    //   0: aload_1
    //   1: ifnonnull -> 6
    //   4: aconst_null
    //   5: areturn
    //   6: aload_1
    //   7: iconst_0
    //   8: aaload
    //   9: checkcast java/lang/String
    //   12: astore_2
    //   13: aload_0
    //   14: getfield a : Lag;
    //   17: new java/lang/StringBuffer
    //   20: dup
    //   21: getstatic v.S : Ljava/lang/String;
    //   24: invokespecial <init> : (Ljava/lang/String;)V
    //   27: aload_2
    //   28: invokevirtual append : (Ljava/lang/String;)Ljava/lang/StringBuffer;
    //   31: invokevirtual toString : ()Ljava/lang/String;
    //   34: invokeinterface a : (Ljava/lang/String;)V
    //   39: new java/io/DataInputStream
    //   42: dup
    //   43: aload_0
    //   44: getfield a : Lag;
    //   47: invokeinterface a : ()Ljava/io/InputStream;
    //   52: invokespecial <init> : (Ljava/io/InputStream;)V
    //   55: astore_3
    //   56: new e
    //   59: dup
    //   60: iconst_0
    //   61: invokespecial <init> : (B)V
    //   64: dup
    //   65: astore #4
    //   67: aload_2
    //   68: putfield d : Ljava/lang/String;
    //   71: aload_3
    //   72: invokevirtual readShort : ()S
    //   75: dup
    //   76: istore #5
    //   78: newarray byte
    //   80: astore #6
    //   82: aload_3
    //   83: aload #6
    //   85: invokevirtual read : ([B)I
    //   88: pop
    //   89: iload #5
    //   91: newarray char
    //   93: astore #7
    //   95: aload #6
    //   97: iconst_0
    //   98: aload #6
    //   100: arraylength
    //   101: aload #7
    //   103: invokestatic a : ([BII[C)I
    //   106: istore #5
    //   108: aload #4
    //   110: new java/lang/String
    //   113: dup
    //   114: aload #7
    //   116: iconst_0
    //   117: iload #5
    //   119: invokespecial <init> : ([CII)V
    //   122: putfield a : Ljava/lang/String;
    //   125: aload #4
    //   127: aload_3
    //   128: invokevirtual readUTF : ()Ljava/lang/String;
    //   131: putfield b : Ljava/lang/String;
    //   134: ldc 'null'
    //   136: aload #4
    //   138: getfield b : Ljava/lang/String;
    //   141: invokevirtual equals : (Ljava/lang/Object;)Z
    //   144: ifeq -> 153
    //   147: aload #4
    //   149: aconst_null
    //   150: putfield b : Ljava/lang/String;
    //   153: aload #4
    //   155: aload_3
    //   156: invokevirtual readUTF : ()Ljava/lang/String;
    //   159: putfield c : Ljava/lang/String;
    //   162: ldc 'null'
    //   164: aload #4
    //   166: getfield c : Ljava/lang/String;
    //   169: invokevirtual equals : (Ljava/lang/Object;)Z
    //   172: ifeq -> 181
    //   175: aload #4
    //   177: aconst_null
    //   178: putfield c : Ljava/lang/String;
    //   181: aload_3
    //   182: invokevirtual readInt : ()I
    //   185: newarray byte
    //   187: astore #5
    //   189: aload_3
    //   190: aload #5
    //   192: invokevirtual read : ([B)I
    //   195: pop
    //   196: aload #4
    //   198: getfield a : Lh;
    //   201: aload #5
    //   203: invokevirtual a : ([B)V
    //   206: aload_3
    //   207: invokevirtual close : ()V
    //   210: aload_0
    //   211: getfield a : Lag;
    //   214: invokeinterface b : ()V
    //   219: iconst_m1
    //   220: istore #5
    //   222: aload_0
    //   223: getfield b : Ljava/util/Vector;
    //   226: invokevirtual size : ()I
    //   229: istore #6
    //   231: iconst_0
    //   232: istore #7
    //   234: iload #7
    //   236: iload #6
    //   238: if_icmpge -> 411
    //   241: aload_0
    //   242: getfield b : Ljava/util/Vector;
    //   245: iload #7
    //   247: invokevirtual elementAt : (I)Ljava/lang/Object;
    //   250: checkcast [Ljava/lang/Object;
    //   253: dup
    //   254: astore_3
    //   255: iconst_0
    //   256: aaload
    //   257: aload_2
    //   258: invokevirtual equals : (Ljava/lang/Object;)Z
    //   261: ifeq -> 405
    //   264: iload #7
    //   266: istore #5
    //   268: aload #4
    //   270: aload_3
    //   271: iconst_1
    //   272: aaload
    //   273: checkcast [Ljava/lang/Object;
    //   276: putfield a : [Ljava/lang/Object;
    //   279: aload #4
    //   281: aload_3
    //   282: iconst_2
    //   283: aaload
    //   284: checkcast [Lah;
    //   287: putfield a : [Lah;
    //   290: aload #4
    //   292: aload_3
    //   293: iconst_3
    //   294: aaload
    //   295: checkcast [I
    //   298: iconst_0
    //   299: iaload
    //   300: putfield a : I
    //   303: aload #4
    //   305: aload_3
    //   306: iconst_3
    //   307: aaload
    //   308: checkcast [I
    //   311: iconst_2
    //   312: iaload
    //   313: putfield c : I
    //   316: aload #4
    //   318: aload_3
    //   319: iconst_3
    //   320: aaload
    //   321: checkcast [I
    //   324: iconst_3
    //   325: iaload
    //   326: putfield d : I
    //   329: aload #4
    //   331: aload_3
    //   332: iconst_3
    //   333: aaload
    //   334: checkcast [I
    //   337: iconst_4
    //   338: iaload
    //   339: putfield b : I
    //   342: aload #4
    //   344: aload_3
    //   345: iconst_4
    //   346: aaload
    //   347: checkcast [Z
    //   350: putfield a : [Z
    //   353: aload #4
    //   355: aload_3
    //   356: iconst_5
    //   357: aaload
    //   358: checkcast [Z
    //   361: putfield b : [Z
    //   364: aload #4
    //   366: aload_3
    //   367: bipush #6
    //   369: aaload
    //   370: checkcast [I
    //   373: putfield a : [I
    //   376: aload #4
    //   378: aload_3
    //   379: bipush #7
    //   381: aaload
    //   382: checkcast [I
    //   385: putfield b : [I
    //   388: aload #4
    //   390: aload_3
    //   391: bipush #8
    //   393: aaload
    //   394: checkcast [Z
    //   397: iconst_0
    //   398: baload
    //   399: putfield a : Z
    //   402: goto -> 411
    //   405: iinc #7, 1
    //   408: goto -> 234
    //   411: iload #5
    //   413: iconst_m1
    //   414: if_icmpne -> 459
    //   417: aload #4
    //   419: bipush #14
    //   421: anewarray java/lang/Object
    //   424: putfield a : [Ljava/lang/Object;
    //   427: aload #4
    //   429: getfield a : [Ljava/lang/Object;
    //   432: iconst_0
    //   433: aload_1
    //   434: iconst_1
    //   435: aaload
    //   436: aastore
    //   437: aload #4
    //   439: getfield a : [Ljava/lang/Object;
    //   442: iconst_1
    //   443: aload #4
    //   445: getfield a : Ljava/lang/String;
    //   448: aastore
    //   449: aload #4
    //   451: getfield a : [Ljava/lang/Object;
    //   454: iconst_4
    //   455: aload_1
    //   456: iconst_2
    //   457: aaload
    //   458: aastore
    //   459: aload #4
    //   461: areturn
  }
  
  public final Object[] a(String paramString) {
    // Byte code:
    //   0: aload_0
    //   1: getfield a : Ljava/util/Vector;
    //   4: ifnull -> 76
    //   7: aload_0
    //   8: getfield a : Ljava/util/Vector;
    //   11: invokevirtual isEmpty : ()Z
    //   14: ifne -> 76
    //   17: aload_0
    //   18: getfield a : Ljava/util/Vector;
    //   21: invokevirtual size : ()I
    //   24: istore #4
    //   26: iconst_0
    //   27: istore #5
    //   29: iload #5
    //   31: iload #4
    //   33: if_icmpge -> 76
    //   36: aload_0
    //   37: getfield a : Ljava/util/Vector;
    //   40: iload #5
    //   42: invokevirtual elementAt : (I)Ljava/lang/Object;
    //   45: checkcast [Ljava/lang/Object;
    //   48: dup
    //   49: astore_2
    //   50: iconst_0
    //   51: aaload
    //   52: checkcast java/lang/String
    //   55: dup
    //   56: astore_3
    //   57: ifnull -> 70
    //   60: aload_3
    //   61: aload_1
    //   62: invokevirtual equals : (Ljava/lang/Object;)Z
    //   65: ifeq -> 70
    //   68: aload_2
    //   69: areturn
    //   70: iinc #5, 1
    //   73: goto -> 29
    //   76: aconst_null
    //   77: areturn
  }
  
  private Object[] a(String paramString1, String paramString2) {
    // Byte code:
    //   0: aload_1
    //   1: ifnonnull -> 7
    //   4: ldc ''
    //   6: astore_1
    //   7: aload_2
    //   8: ifnonnull -> 14
    //   11: ldc ''
    //   13: astore_2
    //   14: aload_1
    //   15: bipush #35
    //   17: invokevirtual indexOf : (I)I
    //   20: dup
    //   21: istore_3
    //   22: iconst_m1
    //   23: if_icmpeq -> 33
    //   26: aload_1
    //   27: iconst_0
    //   28: iload_3
    //   29: invokevirtual substring : (II)Ljava/lang/String;
    //   32: astore_1
    //   33: aload_2
    //   34: bipush #35
    //   36: invokevirtual indexOf : (I)I
    //   39: dup
    //   40: istore_3
    //   41: iconst_m1
    //   42: if_icmpeq -> 52
    //   45: aload_2
    //   46: iconst_0
    //   47: iload_3
    //   48: invokevirtual substring : (II)Ljava/lang/String;
    //   51: astore_2
    //   52: getstatic v.S : Z
    //   55: ifeq -> 70
    //   58: aload_1
    //   59: iconst_1
    //   60: invokestatic a : (Ljava/lang/String;Z)Ljava/lang/String;
    //   63: astore_1
    //   64: aload_2
    //   65: iconst_1
    //   66: invokestatic a : (Ljava/lang/String;Z)Ljava/lang/String;
    //   69: astore_2
    //   70: aconst_null
    //   71: astore_3
    //   72: aload_0
    //   73: getfield a : Ljava/util/Vector;
    //   76: invokevirtual size : ()I
    //   79: istore #4
    //   81: iconst_0
    //   82: istore #5
    //   84: iload #5
    //   86: iload #4
    //   88: if_icmpge -> 246
    //   91: aload_0
    //   92: getfield a : Ljava/util/Vector;
    //   95: iload #5
    //   97: invokevirtual elementAt : (I)Ljava/lang/Object;
    //   100: checkcast [Ljava/lang/Object;
    //   103: dup
    //   104: astore #6
    //   106: iconst_1
    //   107: aaload
    //   108: checkcast java/lang/String
    //   111: astore #7
    //   113: aload #6
    //   115: iconst_2
    //   116: aaload
    //   117: checkcast java/lang/String
    //   120: astore #8
    //   122: getstatic v.S : Z
    //   125: ifeq -> 144
    //   128: aload #7
    //   130: iconst_1
    //   131: invokestatic a : (Ljava/lang/String;Z)Ljava/lang/String;
    //   134: astore #7
    //   136: aload #8
    //   138: iconst_1
    //   139: invokestatic a : (Ljava/lang/String;Z)Ljava/lang/String;
    //   142: astore #8
    //   144: aload #7
    //   146: aload_1
    //   147: invokevirtual equals : (Ljava/lang/Object;)Z
    //   150: ifeq -> 186
    //   153: aload #6
    //   155: iconst_3
    //   156: new java/lang/Long
    //   159: dup
    //   160: invokestatic currentTimeMillis : ()J
    //   163: invokespecial <init> : (J)V
    //   166: aastore
    //   167: aload_0
    //   168: getfield a : Ljava/util/Vector;
    //   171: aload #6
    //   173: iload #5
    //   175: invokevirtual setElementAt : (Ljava/lang/Object;I)V
    //   178: aload_0
    //   179: iconst_1
    //   180: putfield a : Z
    //   183: aload #6
    //   185: areturn
    //   186: aload #8
    //   188: aload_2
    //   189: invokevirtual equals : (Ljava/lang/Object;)Z
    //   192: ifeq -> 240
    //   195: aload_3
    //   196: ifnonnull -> 240
    //   199: aload #7
    //   201: invokevirtual length : ()I
    //   204: ifne -> 240
    //   207: aload #6
    //   209: iconst_3
    //   210: new java/lang/Long
    //   213: dup
    //   214: invokestatic currentTimeMillis : ()J
    //   217: invokespecial <init> : (J)V
    //   220: aastore
    //   221: aload_0
    //   222: getfield a : Ljava/util/Vector;
    //   225: aload #6
    //   227: iload #5
    //   229: invokevirtual setElementAt : (Ljava/lang/Object;I)V
    //   232: aload_0
    //   233: iconst_1
    //   234: putfield a : Z
    //   237: aload #6
    //   239: astore_3
    //   240: iinc #5, 1
    //   243: goto -> 84
    //   246: aload_3
    //   247: areturn
  }
  
  private String a(String paramString1, String paramString2) {
    Object[] arrayOfObject;
    return ((arrayOfObject = a(paramString1, paramString2)) != null) ? (String)this[0] : null;
  }
  
  private synchronized boolean b() {
    // Byte code:
    //   0: aload_0
    //   1: getfield a : Ljava/util/Vector;
    //   4: invokevirtual size : ()I
    //   7: istore_1
    //   8: invokestatic currentTimeMillis : ()J
    //   11: lstore_2
    //   12: aconst_null
    //   13: astore #4
    //   15: iconst_0
    //   16: istore #6
    //   18: iload #6
    //   20: iload_1
    //   21: if_icmpge -> 74
    //   24: aload_0
    //   25: getfield a : Ljava/util/Vector;
    //   28: iload #6
    //   30: invokevirtual elementAt : (I)Ljava/lang/Object;
    //   33: checkcast [Ljava/lang/Object;
    //   36: dup
    //   37: astore #5
    //   39: ifnull -> 68
    //   42: aload #5
    //   44: iconst_3
    //   45: aaload
    //   46: checkcast java/lang/Long
    //   49: invokevirtual longValue : ()J
    //   52: lstore #7
    //   54: lload_2
    //   55: lload #7
    //   57: lcmp
    //   58: ifle -> 68
    //   61: lload #7
    //   63: lstore_2
    //   64: aload #5
    //   66: astore #4
    //   68: iinc #6, 1
    //   71: goto -> 18
    //   74: aload #4
    //   76: ifnull -> 103
    //   79: aload_0
    //   80: aload #4
    //   82: iconst_1
    //   83: aaload
    //   84: checkcast java/lang/String
    //   87: aload #4
    //   89: iconst_2
    //   90: aaload
    //   91: checkcast java/lang/String
    //   94: iconst_1
    //   95: invokevirtual a : (Ljava/lang/String;Ljava/lang/String;Z)Z
    //   98: ifeq -> 103
    //   101: iconst_1
    //   102: ireturn
    //   103: iconst_0
    //   104: ireturn
  }
  
  public final synchronized boolean a(String paramString) {
    // Byte code:
    //   0: aload_0
    //   1: getfield a : Lag;
    //   4: new java/lang/StringBuffer
    //   7: dup
    //   8: getstatic v.S : Ljava/lang/String;
    //   11: invokespecial <init> : (Ljava/lang/String;)V
    //   14: aload_1
    //   15: invokevirtual append : (Ljava/lang/String;)Ljava/lang/StringBuffer;
    //   18: invokevirtual toString : ()Ljava/lang/String;
    //   21: invokeinterface a : (Ljava/lang/String;)Z
    //   26: ireturn
  }
  
  public final synchronized void a(boolean paramBoolean) {
    // Byte code:
    //   0: iload_1
    //   1: ifeq -> 71
    //   4: aload_0
    //   5: getfield a : Ljava/util/Vector;
    //   8: invokevirtual size : ()I
    //   11: istore_1
    //   12: iinc #1, -1
    //   15: iload_1
    //   16: iflt -> 43
    //   19: aload_0
    //   20: aload_0
    //   21: getfield a : Ljava/util/Vector;
    //   24: iload_1
    //   25: invokevirtual elementAt : (I)Ljava/lang/Object;
    //   28: checkcast [Ljava/lang/Object;
    //   31: iconst_0
    //   32: aaload
    //   33: checkcast java/lang/String
    //   36: invokevirtual a : (Ljava/lang/String;)Z
    //   39: pop
    //   40: goto -> 12
    //   43: aload_0
    //   44: getfield a : Lag;
    //   47: new java/lang/StringBuffer
    //   50: dup
    //   51: getstatic v.S : Ljava/lang/String;
    //   54: invokespecial <init> : (Ljava/lang/String;)V
    //   57: ldc 'dcache4.url'
    //   59: invokevirtual append : (Ljava/lang/String;)Ljava/lang/StringBuffer;
    //   62: invokevirtual toString : ()Ljava/lang/String;
    //   65: invokeinterface a : (Ljava/lang/String;)Z
    //   70: pop
    //   71: aload_0
    //   72: getfield a : Ljava/util/Vector;
    //   75: invokevirtual removeAllElements : ()V
    //   78: aload_0
    //   79: getfield b : Ljava/util/Vector;
    //   82: invokevirtual removeAllElements : ()V
    //   85: aload_0
    //   86: invokespecial c : ()V
    //   89: aload_0
    //   90: getfield a : Lag;
    //   93: invokeinterface b : ()Z
    //   98: ifne -> 111
    //   101: aload_0
    //   102: getfield a : Lag;
    //   105: invokeinterface a : ()Z
    //   110: pop
    //   111: aload_0
    //   112: invokespecial b : ()V
    //   115: return
  }
  
  public final void run() {
    // Byte code:
    //   0: aload_0
    //   1: getfield c : I
    //   4: lookupswitch default -> 113, 1 -> 24
    //   24: aload_0
    //   25: aload_0
    //   26: getfield a : Lag;
    //   29: invokestatic a : (Lag;)Lag;
    //   32: putfield a : Lag;
    //   35: aload_0
    //   36: getfield a : Lag;
    //   39: ifnonnull -> 59
    //   42: iconst_0
    //   43: putstatic v.U : Z
    //   46: aconst_null
    //   47: invokestatic d : (Ljava/io/DataOutputStream;)Ljava/io/DataOutputStream;
    //   50: pop
    //   51: new java/lang/Error
    //   54: dup
    //   55: invokespecial <init> : ()V
    //   58: athrow
    //   59: aload_0
    //   60: invokespecial c : ()V
    //   63: aload_0
    //   64: getfield a : Lag;
    //   67: invokeinterface b : ()Z
    //   72: ifne -> 85
    //   75: aload_0
    //   76: getfield a : Lag;
    //   79: invokeinterface a : ()Z
    //   84: pop
    //   85: aload_0
    //   86: new java/util/Vector
    //   89: dup
    //   90: iconst_0
    //   91: invokespecial <init> : (I)V
    //   94: putfield a : Ljava/util/Vector;
    //   97: aload_0
    //   98: new java/util/Vector
    //   101: dup
    //   102: iconst_0
    //   103: invokespecial <init> : (I)V
    //   106: putfield b : Ljava/util/Vector;
    //   109: aload_0
    //   110: invokespecial b : ()V
    //   113: goto -> 117
    //   116: pop
    //   117: aload_0
    //   118: iconst_0
    //   119: putfield c : I
    //   122: getstatic ae.b : I
    //   125: tableswitch default -> 189, 1 -> 152, 2 -> 167, 3 -> 179
    //   152: getstatic af.b : Laf;
    //   155: getfield a : Lfavax/microedition/lcdui/Display;
    //   158: getstatic af.b : Laf;
    //   161: invokevirtual callSerially : (Ljava/lang/Runnable;)V
    //   164: goto -> 189
    //   167: getstatic af.b : Laf;
    //   170: getstatic v.u : Ljava/lang/String;
    //   173: invokevirtual b : (Ljava/lang/String;)V
    //   176: goto -> 189
    //   179: getstatic af.b : Laf;
    //   182: getfield a : Lv;
    //   185: iconst_0
    //   186: invokevirtual d : (Z)V
    //   189: iconst_0
    //   190: putstatic ae.b : I
    //   193: return
    // Exception table:
    //   from	to	target	type
    //   0	113	116	java/lang/Throwable
  }
  
  private void c() {
    // Byte code:
    //   0: aload_0
    //   1: getfield a : Lag;
    //   4: new java/lang/StringBuffer
    //   7: dup
    //   8: getstatic v.S : Ljava/lang/String;
    //   11: invokespecial <init> : (Ljava/lang/String;)V
    //   14: ldc 'dcache4.url'
    //   16: invokevirtual append : (Ljava/lang/String;)Ljava/lang/StringBuffer;
    //   19: invokevirtual toString : ()Ljava/lang/String;
    //   22: invokeinterface a : (Ljava/lang/String;)V
    //   27: return
  }
  
  public final void a(String paramString) {
    if (this.c.contains(paramString)) {
      this.c.removeElement(paramString);
    } else {
      this.c.addElement(paramString);
    } 
    this.b = !this.c.isEmpty();
  }
  
  public final void a() {
    StringBuffer stringBuffer = new StringBuffer(0);
    for (byte b = 0; b < this.a.size(); b++) {
      stringBuffer.setLength(0);
      a(stringBuffer.append(b + 1).append('.').append((String)((Object[])this.a.elementAt(b))[0]).toString());
    } 
  }
}


/* Location:              D:\Desktop\kemulator\LocID_BitByByte.jar!\ae.class
 * Java compiler version: 2 (46.0)
 * JD-Core Version:       1.1.3
 */