import java.io.ByteArrayOutputStream;
import java.io.DataOutputStream;
import java.io.InputStream;
import java.util.Enumeration;
import java.util.Vector;
import javax.microedition.lcdui.Command;
import javax.microedition.lcdui.CommandListener;
import javax.microedition.lcdui.Displayable;

public final class ai implements Runnable, CommandListener {
  private int b;
  
  private r a;
  
  private static String c;
  
  public static String a;
  
  private String d;
  
  private static int c;
  
  private static Command a;
  
  private static Command b;
  
  private static Command c;
  
  private static Command d;
  
  public String b = true;
  
  public static boolean a;
  
  public static Vector a;
  
  public String[] a;
  
  public int a;
  
  private String e;
  
  private String f;
  
  public static Thread a;
  
  private static int d = false;
  
  public static byte[] a;
  
  private static int e = true;
  
  private String g;
  
  private boolean d;
  
  private boolean e;
  
  private boolean f;
  
  private boolean g;
  
  public static x a;
  
  public static boolean b;
  
  public static aa a;
  
  private StringBuffer a;
  
  public static boolean c;
  
  private boolean h;
  
  private boolean i;
  
  private boolean j;
  
  private int f;
  
  private String h;
  
  private static boolean k;
  
  private static int g;
  
  private int h;
  
  private boolean l;
  
  private static String i = "*";
  
  public ai() {
    this.b = "";
    this.e = "";
    this.f = "";
    this.a = new StringBuffer(0);
    v.a[((v)((af)af.b).a).c] = v.a(v.a[((v)((af)af.b).a).c]);
    a = (StringBuffer)new Vector(0);
    c = false;
    a = null;
    a = (StringBuffer)new Command(v.d(0), ((af)af.b).n, 1);
    b = new Command(v.d(4), 2, 2);
    c = new Command(v.d(11), 4, 1);
    d = new Command(v.d(12), 2, 0);
    this.a = false;
    a = (StringBuffer)new aa((v)((af)af.b).a);
  }
  
  public final void a(int paramInt) {
    ((v)((af)af.b).a).bf = this.b = paramInt;
  }
  
  private void b(int paramInt) {
    if (a == null || !d) {
      if (paramInt != 47)
        af.b.a(true, (v)((af)af.b).a); 
      d = paramInt;
      (a = (StringBuffer)v.a(this)).setPriority(1);
      return;
    } 
    af.b.a(1500, v.a(v.d(536), String.valueOf(d), ":", String.valueOf(paramInt)), v.d(332));
  }
  
  public final void run() {
    // Byte code:
    //   0: iconst_1
    //   1: putstatic ai.c : Z
    //   4: getstatic af.b : Laf;
    //   7: getfield a : Lv;
    //   10: astore_1
    //   11: iconst_0
    //   12: putstatic ai.b : Z
    //   15: iconst_1
    //   16: istore_2
    //   17: iconst_m1
    //   18: istore_3
    //   19: iconst_m1
    //   20: istore #4
    //   22: getstatic v.a : [Lag;
    //   25: ifnonnull -> 35
    //   28: iconst_2
    //   29: anewarray ag
    //   32: putstatic v.a : [Lag;
    //   35: getstatic v.a : [Lag;
    //   38: aload_1
    //   39: getfield c : B
    //   42: getstatic v.a : [Lag;
    //   45: aload_1
    //   46: getfield c : B
    //   49: aaload
    //   50: invokestatic a : (Lag;)Lag;
    //   53: aastore
    //   54: aload_0
    //   55: getfield h : Z
    //   58: ifeq -> 221
    //   61: aload_0
    //   62: iconst_0
    //   63: putfield h : Z
    //   66: aconst_null
    //   67: putstatic ai.a : Ljava/lang/Thread;
    //   70: aload_0
    //   71: getstatic v.a : [Lag;
    //   74: getstatic af.b : Laf;
    //   77: getfield a : Lv;
    //   80: getfield c : B
    //   83: aaload
    //   84: invokeinterface b : ()Z
    //   89: putfield i : Z
    //   92: aload_0
    //   93: dup
    //   94: astore #5
    //   96: getfield i : Z
    //   99: ifeq -> 201
    //   102: aload #5
    //   104: getstatic v.a : [Lag;
    //   107: getstatic af.b : Laf;
    //   110: getfield a : Lv;
    //   113: getfield c : B
    //   116: aaload
    //   117: invokeinterface a : ()Ljava/lang/String;
    //   122: putfield e : Ljava/lang/String;
    //   125: new javax/microedition/lcdui/Alert
    //   128: dup
    //   129: sipush #276
    //   132: invokestatic d : (I)Ljava/lang/String;
    //   135: sipush #277
    //   138: invokestatic d : (I)Ljava/lang/String;
    //   141: ldc ' '
    //   143: aload #5
    //   145: getfield d : Ljava/lang/String;
    //   148: invokestatic a : (Ljava/lang/String;Ljava/lang/String;Ljava/lang/String;)Ljava/lang/String;
    //   151: aconst_null
    //   152: getstatic javax/microedition/lcdui/AlertType.CONFIRMATION : Ljavax/microedition/lcdui/AlertType;
    //   155: invokespecial <init> : (Ljava/lang/String;Ljava/lang/String;Ljavax/microedition/lcdui/Image;Ljavax/microedition/lcdui/AlertType;)V
    //   158: dup
    //   159: astore #6
    //   161: bipush #-2
    //   163: invokevirtual setTimeout : (I)V
    //   166: aload #6
    //   168: getstatic ai.c : Ljavax/microedition/lcdui/Command;
    //   171: invokevirtual addCommand : (Ljavax/microedition/lcdui/Command;)V
    //   174: aload #6
    //   176: getstatic ai.d : Ljavax/microedition/lcdui/Command;
    //   179: invokevirtual addCommand : (Ljavax/microedition/lcdui/Command;)V
    //   182: aload #6
    //   184: aload #5
    //   186: invokevirtual setCommandListener : (Ljavax/microedition/lcdui/CommandListener;)V
    //   189: getstatic af.b : Laf;
    //   192: aload #6
    //   194: aconst_null
    //   195: invokevirtual a : (Ljavax/microedition/lcdui/Alert;Ljavax/microedition/lcdui/Displayable;)V
    //   198: goto -> 212
    //   201: aload #5
    //   203: getstatic ai.c : Ljavax/microedition/lcdui/Command;
    //   206: getstatic af.b : Laf;
    //   209: invokevirtual commandAction : (Ljavax/microedition/lcdui/Command;Ljavax/microedition/lcdui/Displayable;)V
    //   212: iconst_0
    //   213: putstatic ai.c : Z
    //   216: aconst_null
    //   217: putstatic ai.a : Ljava/lang/Thread;
    //   220: return
    //   221: getstatic ai.d : I
    //   224: tableswitch default -> 5422, 4 -> 805, 5 -> 805, 6 -> 1976, 7 -> 632, 8 -> 1087, 9 -> 2256, 10 -> 738, 11 -> 5422, 12 -> 5422, 13 -> 5422, 14 -> 5422, 15 -> 5422, 16 -> 5422, 17 -> 5422, 18 -> 5422, 19 -> 5422, 20 -> 416, 21 -> 423, 22 -> 2130, 23 -> 2204, 24 -> 5422, 25 -> 5422, 26 -> 2628, 27 -> 5422, 28 -> 5422, 29 -> 3046, 30 -> 3233, 31 -> 3125, 32 -> 3380, 33 -> 3430, 34 -> 3779, 35 -> 473, 36 -> 4169, 37 -> 4251, 38 -> 4295, 39 -> 4333, 40 -> 2673, 41 -> 5422, 42 -> 4382, 43 -> 4398, 44 -> 4398, 45 -> 4658, 46 -> 4904, 47 -> 5216
    //   416: aload_0
    //   417: invokevirtual b : ()V
    //   420: goto -> 5422
    //   423: aload_0
    //   424: dup
    //   425: astore #5
    //   427: monitorenter
    //   428: aload_0
    //   429: getstatic v.a : [Lag;
    //   432: aload_1
    //   433: getfield c : B
    //   436: aaload
    //   437: invokeinterface b : ()[Ljava/lang/String;
    //   442: dup_x1
    //   443: putfield a : [Ljava/lang/String;
    //   446: ifnull -> 459
    //   449: aload_0
    //   450: iconst_1
    //   451: putfield j : Z
    //   454: aload_0
    //   455: iconst_0
    //   456: putfield a : I
    //   459: aload #5
    //   461: monitorexit
    //   462: goto -> 5422
    //   465: astore #6
    //   467: aload #5
    //   469: monitorexit
    //   470: aload #6
    //   472: athrow
    //   473: getstatic ai.a : Z
    //   476: ifne -> 493
    //   479: getstatic ai.a : Ljava/util/Vector;
    //   482: aload_0
    //   483: getfield b : Ljava/lang/String;
    //   486: invokevirtual addElement : (Ljava/lang/Object;)V
    //   489: iconst_1
    //   490: putstatic ai.a : Z
    //   493: iconst_0
    //   494: getstatic ai.a : Ljava/util/Vector;
    //   497: invokevirtual size : ()I
    //   500: if_icmpge -> 625
    //   503: aload_0
    //   504: getfield a : Ljava/lang/StringBuffer;
    //   507: iconst_0
    //   508: invokevirtual setLength : (I)V
    //   511: getstatic v.a : [Lag;
    //   514: aload_1
    //   515: getfield c : B
    //   518: aaload
    //   519: aload_0
    //   520: getfield a : Ljava/lang/StringBuffer;
    //   523: aload_0
    //   524: invokevirtual a : ()Ljava/lang/String;
    //   527: invokevirtual append : (Ljava/lang/String;)Ljava/lang/StringBuffer;
    //   530: getstatic ai.a : Ljava/util/Vector;
    //   533: iconst_0
    //   534: invokevirtual elementAt : (I)Ljava/lang/Object;
    //   537: invokevirtual append : (Ljava/lang/Object;)Ljava/lang/StringBuffer;
    //   540: invokevirtual toString : ()Ljava/lang/String;
    //   543: invokeinterface a : (Ljava/lang/String;)V
    //   548: getstatic v.a : [Lag;
    //   551: aload_1
    //   552: getfield c : B
    //   555: aaload
    //   556: aload_0
    //   557: getfield e : Z
    //   560: invokeinterface a : (Z)V
    //   565: getstatic v.a : [Lag;
    //   568: aload_1
    //   569: getfield c : B
    //   572: aaload
    //   573: aload_0
    //   574: getfield f : Z
    //   577: ifne -> 584
    //   580: iconst_1
    //   581: goto -> 585
    //   584: iconst_0
    //   585: invokeinterface c : (Z)V
    //   590: getstatic v.a : [Lag;
    //   593: aload_1
    //   594: getfield c : B
    //   597: aaload
    //   598: aload_0
    //   599: getfield g : Z
    //   602: ifne -> 609
    //   605: iconst_1
    //   606: goto -> 610
    //   609: iconst_0
    //   610: invokeinterface b : (Z)V
    //   615: getstatic ai.a : Ljava/util/Vector;
    //   618: iconst_0
    //   619: invokevirtual removeElementAt : (I)V
    //   622: goto -> 493
    //   625: aload_0
    //   626: invokevirtual b : ()V
    //   629: goto -> 5422
    //   632: iconst_0
    //   633: putstatic ai.c : I
    //   636: getstatic v.a : [Lag;
    //   639: aload_1
    //   640: getfield c : B
    //   643: aaload
    //   644: aload_0
    //   645: invokevirtual a : ()Ljava/lang/String;
    //   648: aload_0
    //   649: getfield g : Ljava/lang/String;
    //   652: invokestatic a : (Ljava/lang/String;Ljava/lang/String;)Ljava/lang/String;
    //   655: invokeinterface a : (Ljava/lang/String;)V
    //   660: getstatic v.a : [Lag;
    //   663: aload_1
    //   664: getfield c : B
    //   667: aaload
    //   668: invokeinterface b : ()Z
    //   673: ifne -> 695
    //   676: getstatic v.a : [Lag;
    //   679: aload_1
    //   680: getfield c : B
    //   683: aaload
    //   684: invokeinterface f : ()Z
    //   689: ifeq -> 727
    //   692: goto -> 712
    //   695: getstatic ai.c : I
    //   698: iconst_4
    //   699: if_icmpeq -> 712
    //   702: getstatic ai.c : I
    //   705: iconst_5
    //   706: if_icmpeq -> 712
    //   709: invokestatic s : ()V
    //   712: aload_0
    //   713: aload_0
    //   714: invokevirtual a : ()Ljava/lang/String;
    //   717: aload_0
    //   718: getfield g : Ljava/lang/String;
    //   721: invokestatic a : (Ljava/lang/String;Ljava/lang/String;)Ljava/lang/String;
    //   724: invokevirtual b : (Ljava/lang/String;)V
    //   727: aload_0
    //   728: invokevirtual b : ()V
    //   731: iconst_1
    //   732: putstatic v.i : Z
    //   735: goto -> 5422
    //   738: iconst_0
    //   739: putstatic ai.c : I
    //   742: getstatic v.a : [Lag;
    //   745: aload_1
    //   746: getfield c : B
    //   749: aaload
    //   750: aload_0
    //   751: invokevirtual a : ()Ljava/lang/String;
    //   754: aload_0
    //   755: getfield g : Ljava/lang/String;
    //   758: invokestatic a : (Ljava/lang/String;Ljava/lang/String;)Ljava/lang/String;
    //   761: invokeinterface a : (Ljava/lang/String;)V
    //   766: getstatic v.a : [Lag;
    //   769: aload_1
    //   770: getfield c : B
    //   773: aaload
    //   774: invokeinterface b : ()Z
    //   779: ifne -> 5422
    //   782: getstatic v.a : [Lag;
    //   785: aload_1
    //   786: getfield c : B
    //   789: aaload
    //   790: invokeinterface a : ()Z
    //   795: ifeq -> 5422
    //   798: aload_0
    //   799: invokevirtual b : ()V
    //   802: goto -> 5422
    //   805: aconst_null
    //   806: astore #5
    //   808: iconst_0
    //   809: istore #6
    //   811: getstatic ai.a : Z
    //   814: ifne -> 830
    //   817: getstatic ai.a : Ljava/util/Vector;
    //   820: getstatic ai.c : Ljava/lang/String;
    //   823: invokevirtual addElement : (Ljava/lang/Object;)V
    //   826: iconst_1
    //   827: putstatic ai.a : Z
    //   830: getstatic ai.k : Z
    //   833: ifeq -> 862
    //   836: getstatic ai.c : Ljava/lang/String;
    //   839: invokestatic e : (Ljava/lang/String;)Z
    //   842: ifne -> 856
    //   845: aload_0
    //   846: aload_0
    //   847: getfield d : Ljava/lang/String;
    //   850: invokestatic g : (Ljava/lang/String;)Ljava/lang/String;
    //   853: putfield d : Ljava/lang/String;
    //   856: aload_0
    //   857: getfield d : Ljava/lang/String;
    //   860: astore #5
    //   862: iconst_0
    //   863: istore #7
    //   865: iload #7
    //   867: getstatic ai.a : Ljava/util/Vector;
    //   870: invokevirtual size : ()I
    //   873: if_icmpge -> 1021
    //   876: getstatic ai.b : Z
    //   879: ifne -> 1021
    //   882: getstatic ai.a : Ljava/lang/String;
    //   885: aload_0
    //   886: invokevirtual a : ()Ljava/lang/String;
    //   889: invokevirtual equals : (Ljava/lang/Object;)Z
    //   892: ifeq -> 914
    //   895: getstatic ai.a : Ljava/lang/String;
    //   898: aload_0
    //   899: invokevirtual a : ()Ljava/lang/String;
    //   902: invokevirtual equals : (Ljava/lang/Object;)Z
    //   905: ifeq -> 1009
    //   908: getstatic ai.k : Z
    //   911: ifeq -> 1009
    //   914: iconst_1
    //   915: getstatic v.a : [Lag;
    //   918: aload_1
    //   919: getfield c : B
    //   922: aaload
    //   923: getstatic ai.a : Ljava/lang/String;
    //   926: getstatic ai.a : Ljava/util/Vector;
    //   929: iload #7
    //   931: invokevirtual elementAt : (I)Ljava/lang/Object;
    //   934: checkcast java/lang/String
    //   937: invokestatic a : (Ljava/lang/String;Ljava/lang/String;)Ljava/lang/String;
    //   940: aload #5
    //   942: ifnonnull -> 966
    //   945: aload_0
    //   946: invokevirtual a : ()Ljava/lang/String;
    //   949: getstatic ai.a : Ljava/util/Vector;
    //   952: iload #7
    //   954: invokevirtual elementAt : (I)Ljava/lang/Object;
    //   957: checkcast java/lang/String
    //   960: invokestatic a : (Ljava/lang/String;Ljava/lang/String;)Ljava/lang/String;
    //   963: goto -> 975
    //   966: aload_0
    //   967: invokevirtual a : ()Ljava/lang/String;
    //   970: aload #5
    //   972: invokestatic a : (Ljava/lang/String;Ljava/lang/String;)Ljava/lang/String;
    //   975: getstatic ai.d : I
    //   978: iconst_4
    //   979: if_icmpne -> 986
    //   982: iconst_1
    //   983: goto -> 987
    //   986: iconst_0
    //   987: invokeinterface a : (Ljava/lang/String;Ljava/lang/String;Z)I
    //   992: dup
    //   993: istore #6
    //   995: if_icmpne -> 1009
    //   998: getstatic ai.a : Ljava/util/Vector;
    //   1001: iload #7
    //   1003: invokevirtual removeElementAt : (I)V
    //   1006: iinc #7, -1
    //   1009: iload #6
    //   1011: iconst_3
    //   1012: if_icmpeq -> 1021
    //   1015: iinc #7, 1
    //   1018: goto -> 865
    //   1021: iconst_0
    //   1022: putstatic ai.k : Z
    //   1025: getstatic ai.b : Z
    //   1028: ifeq -> 1037
    //   1031: getstatic ai.a : Ljava/util/Vector;
    //   1034: invokevirtual removeAllElements : ()V
    //   1037: getstatic af.b : Laf;
    //   1040: iconst_0
    //   1041: putfield C : Z
    //   1044: getstatic af.b : Laf;
    //   1047: invokevirtual repaint : ()V
    //   1050: iload #6
    //   1052: ifne -> 1080
    //   1055: getstatic af.b : Laf;
    //   1058: getstatic ai.d : I
    //   1061: iconst_4
    //   1062: if_icmpne -> 1071
    //   1065: sipush #318
    //   1068: goto -> 1074
    //   1071: sipush #317
    //   1074: invokestatic d : (I)Ljava/lang/String;
    //   1077: invokevirtual c : (Ljava/lang/String;)V
    //   1080: aload_0
    //   1081: invokevirtual b : ()V
    //   1084: goto -> 5422
    //   1087: ldc ''
    //   1089: astore #7
    //   1091: ldc ''
    //   1093: astore #5
    //   1095: ldc ''
    //   1097: astore #8
    //   1099: ldc ''
    //   1101: astore #9
    //   1103: iconst_0
    //   1104: istore #10
    //   1106: iconst_0
    //   1107: istore #11
    //   1109: getstatic ai.a : Z
    //   1112: ifne -> 1129
    //   1115: getstatic ai.a : Ljava/util/Vector;
    //   1118: aload_0
    //   1119: getfield b : Ljava/lang/String;
    //   1122: invokevirtual addElement : (Ljava/lang/Object;)V
    //   1125: iconst_1
    //   1126: putstatic ai.a : Z
    //   1129: aload_0
    //   1130: getfield h : Ljava/lang/String;
    //   1133: bipush #42
    //   1135: invokevirtual indexOf : (I)I
    //   1138: iconst_m1
    //   1139: if_icmpne -> 1148
    //   1142: iconst_1
    //   1143: istore #10
    //   1145: goto -> 1323
    //   1148: iconst_1
    //   1149: istore #11
    //   1151: aload_0
    //   1152: getfield h : Ljava/lang/String;
    //   1155: invokestatic j : (Ljava/lang/String;)Ljava/lang/String;
    //   1158: astore #6
    //   1160: aload_0
    //   1161: getfield h : Ljava/lang/String;
    //   1164: invokestatic i : (Ljava/lang/String;)Ljava/lang/String;
    //   1167: astore #12
    //   1169: aload #6
    //   1171: invokevirtual length : ()I
    //   1174: ifle -> 1242
    //   1177: aload #6
    //   1179: bipush #42
    //   1181: invokevirtual indexOf : (I)I
    //   1184: dup
    //   1185: istore #13
    //   1187: iflt -> 1242
    //   1190: iload #13
    //   1192: ifne -> 1213
    //   1195: ldc '*'
    //   1197: astore #7
    //   1199: aload #6
    //   1201: iload #13
    //   1203: iconst_1
    //   1204: iadd
    //   1205: invokevirtual substring : (I)Ljava/lang/String;
    //   1208: astore #5
    //   1210: goto -> 1246
    //   1213: iload #13
    //   1215: aload #6
    //   1217: invokevirtual length : ()I
    //   1220: iconst_1
    //   1221: isub
    //   1222: if_icmpne -> 1246
    //   1225: aload #6
    //   1227: iconst_0
    //   1228: iload #13
    //   1230: invokevirtual substring : (II)Ljava/lang/String;
    //   1233: astore #7
    //   1235: ldc '*'
    //   1237: astore #5
    //   1239: goto -> 1246
    //   1242: aload #6
    //   1244: astore #7
    //   1246: aload #12
    //   1248: invokevirtual length : ()I
    //   1251: ifle -> 1319
    //   1254: aload #12
    //   1256: bipush #42
    //   1258: invokevirtual indexOf : (I)I
    //   1261: dup
    //   1262: istore #13
    //   1264: iflt -> 1319
    //   1267: iload #13
    //   1269: ifne -> 1290
    //   1272: ldc '*'
    //   1274: astore #8
    //   1276: aload #12
    //   1278: iload #13
    //   1280: iconst_1
    //   1281: iadd
    //   1282: invokevirtual substring : (I)Ljava/lang/String;
    //   1285: astore #9
    //   1287: goto -> 1323
    //   1290: iload #13
    //   1292: aload #12
    //   1294: invokevirtual length : ()I
    //   1297: iconst_1
    //   1298: isub
    //   1299: if_icmpne -> 1323
    //   1302: aload #12
    //   1304: iconst_0
    //   1305: iload #13
    //   1307: invokevirtual substring : (II)Ljava/lang/String;
    //   1310: astore #8
    //   1312: ldc '*'
    //   1314: astore #9
    //   1316: goto -> 1323
    //   1319: aload #12
    //   1321: astore #8
    //   1323: getstatic ai.a : Ljava/util/Vector;
    //   1326: invokevirtual size : ()I
    //   1329: iconst_1
    //   1330: if_icmpne -> 1336
    //   1333: iconst_1
    //   1334: istore #10
    //   1336: aload_0
    //   1337: invokevirtual a : ()Ljava/lang/String;
    //   1340: astore #12
    //   1342: iconst_0
    //   1343: istore #13
    //   1345: iload #13
    //   1347: getstatic ai.a : Ljava/util/Vector;
    //   1350: invokevirtual size : ()I
    //   1353: if_icmpge -> 1969
    //   1356: getstatic ai.b : Z
    //   1359: ifne -> 1969
    //   1362: getstatic ai.a : Ljava/util/Vector;
    //   1365: iload #13
    //   1367: invokevirtual elementAt : (I)Ljava/lang/Object;
    //   1370: checkcast java/lang/String
    //   1373: astore #14
    //   1375: aload_0
    //   1376: getfield h : Ljava/lang/String;
    //   1379: astore #15
    //   1381: iload #11
    //   1383: ifeq -> 1585
    //   1386: aload #14
    //   1388: invokestatic h : (Ljava/lang/String;)Ljava/lang/String;
    //   1391: dup
    //   1392: astore #15
    //   1394: invokestatic j : (Ljava/lang/String;)Ljava/lang/String;
    //   1397: astore #16
    //   1399: aload #15
    //   1401: invokestatic i : (Ljava/lang/String;)Ljava/lang/String;
    //   1404: astore #6
    //   1406: aload_0
    //   1407: getfield a : Ljava/lang/StringBuffer;
    //   1410: iconst_0
    //   1411: invokevirtual setLength : (I)V
    //   1414: aload #7
    //   1416: ldc '*'
    //   1418: if_acmpne -> 1434
    //   1421: aload_0
    //   1422: getfield a : Ljava/lang/StringBuffer;
    //   1425: aload #16
    //   1427: invokevirtual append : (Ljava/lang/String;)Ljava/lang/StringBuffer;
    //   1430: pop
    //   1431: goto -> 1452
    //   1434: aload #7
    //   1436: invokevirtual length : ()I
    //   1439: ifle -> 1452
    //   1442: aload_0
    //   1443: getfield a : Ljava/lang/StringBuffer;
    //   1446: aload #7
    //   1448: invokevirtual append : (Ljava/lang/String;)Ljava/lang/StringBuffer;
    //   1451: pop
    //   1452: aload #5
    //   1454: ldc '*'
    //   1456: if_acmpne -> 1472
    //   1459: aload_0
    //   1460: getfield a : Ljava/lang/StringBuffer;
    //   1463: aload #16
    //   1465: invokevirtual append : (Ljava/lang/String;)Ljava/lang/StringBuffer;
    //   1468: pop
    //   1469: goto -> 1490
    //   1472: aload #5
    //   1474: invokevirtual length : ()I
    //   1477: ifle -> 1490
    //   1480: aload_0
    //   1481: getfield a : Ljava/lang/StringBuffer;
    //   1484: aload #5
    //   1486: invokevirtual append : (Ljava/lang/String;)Ljava/lang/StringBuffer;
    //   1489: pop
    //   1490: aload_0
    //   1491: getfield a : Ljava/lang/StringBuffer;
    //   1494: bipush #46
    //   1496: invokevirtual append : (C)Ljava/lang/StringBuffer;
    //   1499: pop
    //   1500: aload #8
    //   1502: ldc '*'
    //   1504: if_acmpne -> 1520
    //   1507: aload_0
    //   1508: getfield a : Ljava/lang/StringBuffer;
    //   1511: aload #6
    //   1513: invokevirtual append : (Ljava/lang/String;)Ljava/lang/StringBuffer;
    //   1516: pop
    //   1517: goto -> 1538
    //   1520: aload #8
    //   1522: invokevirtual length : ()I
    //   1525: ifle -> 1538
    //   1528: aload_0
    //   1529: getfield a : Ljava/lang/StringBuffer;
    //   1532: aload #8
    //   1534: invokevirtual append : (Ljava/lang/String;)Ljava/lang/StringBuffer;
    //   1537: pop
    //   1538: aload #9
    //   1540: ldc '*'
    //   1542: if_acmpne -> 1558
    //   1545: aload_0
    //   1546: getfield a : Ljava/lang/StringBuffer;
    //   1549: aload #6
    //   1551: invokevirtual append : (Ljava/lang/String;)Ljava/lang/StringBuffer;
    //   1554: pop
    //   1555: goto -> 1576
    //   1558: aload #9
    //   1560: invokevirtual length : ()I
    //   1563: ifle -> 1576
    //   1566: aload_0
    //   1567: getfield a : Ljava/lang/StringBuffer;
    //   1570: aload #9
    //   1572: invokevirtual append : (Ljava/lang/String;)Ljava/lang/StringBuffer;
    //   1575: pop
    //   1576: aload_0
    //   1577: getfield a : Ljava/lang/StringBuffer;
    //   1580: invokevirtual toString : ()Ljava/lang/String;
    //   1583: astore #15
    //   1585: aload #14
    //   1587: bipush #47
    //   1589: invokestatic a : (Ljava/lang/String;C)Z
    //   1592: ifeq -> 1619
    //   1595: getstatic v.bd : I
    //   1598: iconst_4
    //   1599: if_icmpne -> 1612
    //   1602: aload #15
    //   1604: invokestatic g : (Ljava/lang/String;)Ljava/lang/String;
    //   1607: astore #15
    //   1609: goto -> 1619
    //   1612: aload #15
    //   1614: invokestatic h : (Ljava/lang/String;)Ljava/lang/String;
    //   1617: astore #15
    //   1619: aload #14
    //   1621: invokestatic h : (Ljava/lang/String;)Ljava/lang/String;
    //   1624: aload #15
    //   1626: invokestatic h : (Ljava/lang/String;)Ljava/lang/String;
    //   1629: invokevirtual equals : (Ljava/lang/Object;)Z
    //   1632: ifeq -> 1653
    //   1635: iload #10
    //   1637: ifeq -> 1963
    //   1640: getstatic ai.a : Ljava/util/Vector;
    //   1643: invokevirtual removeAllElements : ()V
    //   1646: iconst_0
    //   1647: putstatic ai.a : Z
    //   1650: goto -> 1969
    //   1653: getstatic v.bd : I
    //   1656: iconst_1
    //   1657: if_icmpne -> 1674
    //   1660: aload_0
    //   1661: aload #12
    //   1663: aload #15
    //   1665: invokestatic a : (Ljava/lang/String;Ljava/lang/String;)Ljava/lang/String;
    //   1668: putfield d : Ljava/lang/String;
    //   1671: goto -> 1680
    //   1674: aload_0
    //   1675: aload #15
    //   1677: putfield d : Ljava/lang/String;
    //   1680: getstatic v.a : [Lag;
    //   1683: aload_1
    //   1684: getfield c : B
    //   1687: aaload
    //   1688: aload #12
    //   1690: aload #15
    //   1692: invokestatic a : (Ljava/lang/String;Ljava/lang/String;)Ljava/lang/String;
    //   1695: invokeinterface a : (Ljava/lang/String;)V
    //   1700: aload_0
    //   1701: getstatic v.a : [Lag;
    //   1704: aload_1
    //   1705: getfield c : B
    //   1708: aaload
    //   1709: invokeinterface b : ()Z
    //   1714: putfield i : Z
    //   1717: iconst_0
    //   1718: istore #16
    //   1720: aload_0
    //   1721: getfield i : Z
    //   1724: ifeq -> 1831
    //   1727: getstatic v.a : [Lag;
    //   1730: aload_1
    //   1731: getfield c : B
    //   1734: aaload
    //   1735: invokeinterface b : ()J
    //   1740: lstore #17
    //   1742: getstatic v.a : [Lag;
    //   1745: aload_1
    //   1746: getfield c : B
    //   1749: aaload
    //   1750: aload #12
    //   1752: aload #14
    //   1754: invokestatic a : (Ljava/lang/String;Ljava/lang/String;)Ljava/lang/String;
    //   1757: invokeinterface a : (Ljava/lang/String;)V
    //   1762: getstatic v.a : [Lag;
    //   1765: aload_1
    //   1766: getfield c : B
    //   1769: aaload
    //   1770: invokeinterface b : ()J
    //   1775: lstore #19
    //   1777: aload #14
    //   1779: lload #19
    //   1781: aload #15
    //   1783: lload #17
    //   1785: invokestatic a : (Ljava/lang/String;JLjava/lang/String;J)I
    //   1788: dup
    //   1789: istore #6
    //   1791: iconst_1
    //   1792: if_icmpeq -> 1831
    //   1795: iload #6
    //   1797: iconst_2
    //   1798: if_icmpne -> 1819
    //   1801: iload #10
    //   1803: ifeq -> 1963
    //   1806: getstatic ai.a : Ljava/util/Vector;
    //   1809: invokevirtual removeAllElements : ()V
    //   1812: iconst_0
    //   1813: putstatic ai.a : Z
    //   1816: goto -> 1969
    //   1819: iload #6
    //   1821: iconst_3
    //   1822: if_icmpne -> 1828
    //   1825: iconst_1
    //   1826: istore #10
    //   1828: goto -> 1834
    //   1831: iconst_1
    //   1832: istore #16
    //   1834: iload #16
    //   1836: ifeq -> 1945
    //   1839: aload #14
    //   1841: invokestatic f : (Ljava/lang/String;)Ljava/lang/String;
    //   1844: invokestatic h : (Ljava/lang/String;)Ljava/lang/String;
    //   1847: aload #15
    //   1849: invokestatic f : (Ljava/lang/String;)Ljava/lang/String;
    //   1852: invokestatic h : (Ljava/lang/String;)Ljava/lang/String;
    //   1855: invokevirtual equals : (Ljava/lang/Object;)Z
    //   1858: ifne -> 1896
    //   1861: getstatic v.a : [Lag;
    //   1864: aload_1
    //   1865: getfield c : B
    //   1868: aaload
    //   1869: aload #12
    //   1871: aload #15
    //   1873: invokestatic a : (Ljava/lang/String;Ljava/lang/String;)Ljava/lang/String;
    //   1876: invokeinterface a : (Ljava/lang/String;)V
    //   1881: getstatic v.a : [Lag;
    //   1884: aload_1
    //   1885: getfield c : B
    //   1888: aaload
    //   1889: iconst_0
    //   1890: invokeinterface a : (Z)Z
    //   1895: pop
    //   1896: getstatic v.a : [Lag;
    //   1899: aload_1
    //   1900: getfield c : B
    //   1903: aaload
    //   1904: aload #12
    //   1906: aload #14
    //   1908: invokestatic a : (Ljava/lang/String;Ljava/lang/String;)Ljava/lang/String;
    //   1911: invokeinterface a : (Ljava/lang/String;)V
    //   1916: getstatic v.a : [Lag;
    //   1919: aload_1
    //   1920: getfield c : B
    //   1923: aaload
    //   1924: aload_0
    //   1925: getfield d : Ljava/lang/String;
    //   1928: invokeinterface b : (Ljava/lang/String;)Z
    //   1933: pop
    //   1934: getstatic ai.a : Ljava/util/Vector;
    //   1937: iload #13
    //   1939: invokevirtual removeElementAt : (I)V
    //   1942: iinc #13, -1
    //   1945: iload #10
    //   1947: ifeq -> 1963
    //   1950: getstatic ai.a : Ljava/util/Vector;
    //   1953: invokevirtual removeAllElements : ()V
    //   1956: iconst_0
    //   1957: putstatic ai.a : Z
    //   1960: goto -> 1969
    //   1963: iinc #13, 1
    //   1966: goto -> 1345
    //   1969: aload_0
    //   1970: invokevirtual b : ()V
    //   1973: goto -> 5422
    //   1976: getstatic ai.a : Z
    //   1979: ifne -> 1996
    //   1982: getstatic ai.a : Ljava/util/Vector;
    //   1985: aload_0
    //   1986: getfield b : Ljava/lang/String;
    //   1989: invokevirtual addElement : (Ljava/lang/Object;)V
    //   1992: iconst_1
    //   1993: putstatic ai.a : Z
    //   1996: aload_0
    //   1997: getfield a : Ljava/lang/StringBuffer;
    //   2000: iconst_0
    //   2001: invokevirtual setLength : (I)V
    //   2004: iconst_0
    //   2005: istore #13
    //   2007: iload #13
    //   2009: getstatic ai.a : Ljava/util/Vector;
    //   2012: invokevirtual size : ()I
    //   2015: if_icmpge -> 2104
    //   2018: getstatic ai.b : Z
    //   2021: ifne -> 2104
    //   2024: aload_0
    //   2025: getfield a : Ljava/lang/StringBuffer;
    //   2028: iconst_0
    //   2029: invokevirtual setLength : (I)V
    //   2032: getstatic v.a : [Lag;
    //   2035: aload_1
    //   2036: getfield c : B
    //   2039: aaload
    //   2040: aload_0
    //   2041: getfield a : Ljava/lang/StringBuffer;
    //   2044: aload_0
    //   2045: invokevirtual a : ()Ljava/lang/String;
    //   2048: invokevirtual append : (Ljava/lang/String;)Ljava/lang/StringBuffer;
    //   2051: getstatic ai.a : Ljava/util/Vector;
    //   2054: iload #13
    //   2056: invokevirtual elementAt : (I)Ljava/lang/Object;
    //   2059: invokevirtual append : (Ljava/lang/Object;)Ljava/lang/StringBuffer;
    //   2062: invokevirtual toString : ()Ljava/lang/String;
    //   2065: invokeinterface a : (Ljava/lang/String;)V
    //   2070: getstatic v.a : [Lag;
    //   2073: aload_1
    //   2074: getfield c : B
    //   2077: aaload
    //   2078: iconst_1
    //   2079: invokeinterface a : (Z)Z
    //   2084: ifeq -> 2098
    //   2087: getstatic ai.a : Ljava/util/Vector;
    //   2090: iload #13
    //   2092: invokevirtual removeElementAt : (I)V
    //   2095: iinc #13, -1
    //   2098: iinc #13, 1
    //   2101: goto -> 2007
    //   2104: getstatic ai.a : Ljava/util/Vector;
    //   2107: invokevirtual removeAllElements : ()V
    //   2110: getstatic af.b : Laf;
    //   2113: iconst_0
    //   2114: putfield C : Z
    //   2117: getstatic af.b : Laf;
    //   2120: invokevirtual repaint : ()V
    //   2123: aload_0
    //   2124: invokevirtual b : ()V
    //   2127: goto -> 5422
    //   2130: getstatic af.b : Laf;
    //   2133: getfield a : La;
    //   2136: ifnull -> 2197
    //   2139: getstatic af.b : Laf;
    //   2142: getfield a : La;
    //   2145: getfield b : Lh;
    //   2148: ifnull -> 2197
    //   2151: getstatic af.b : Laf;
    //   2154: getfield a : La;
    //   2157: getfield b : Lh;
    //   2160: invokevirtual size : ()I
    //   2163: iconst_m1
    //   2164: if_icmpeq -> 2197
    //   2167: aload_0
    //   2168: invokespecial y : ()V
    //   2171: getstatic v.a : [Lag;
    //   2174: aload_1
    //   2175: getfield c : B
    //   2178: aaload
    //   2179: getstatic af.b : Laf;
    //   2182: getfield a : La;
    //   2185: getfield b : Lh;
    //   2188: invokevirtual toByteArray : ()[B
    //   2191: invokeinterface a : ([B)Z
    //   2196: pop
    //   2197: aload_0
    //   2198: invokevirtual b : ()V
    //   2201: goto -> 5422
    //   2204: getstatic v.a : [Lag;
    //   2207: aload_1
    //   2208: getfield c : B
    //   2211: aaload
    //   2212: aload_0
    //   2213: invokevirtual a : ()Ljava/lang/String;
    //   2216: aload_0
    //   2217: getfield b : Ljava/lang/String;
    //   2220: invokestatic a : (Ljava/lang/String;Ljava/lang/String;)Ljava/lang/String;
    //   2223: invokeinterface a : (Ljava/lang/String;)V
    //   2228: getstatic af.b : Laf;
    //   2231: ldc 'file:///'
    //   2233: aload_0
    //   2234: invokevirtual a : ()Ljava/lang/String;
    //   2237: aload_0
    //   2238: getfield b : Ljava/lang/String;
    //   2241: invokestatic a : (Ljava/lang/String;Ljava/lang/String;Ljava/lang/String;)Ljava/lang/String;
    //   2244: invokevirtual b : (Ljava/lang/String;)V
    //   2247: getstatic af.b : Laf;
    //   2250: invokestatic a : (Ljavax/microedition/lcdui/Displayable;)V
    //   2253: goto -> 5422
    //   2256: aconst_null
    //   2257: putstatic ai.a : [B
    //   2260: aconst_null
    //   2261: astore #13
    //   2263: getstatic v.a : [Lag;
    //   2266: aload_1
    //   2267: getfield c : B
    //   2270: aaload
    //   2271: aload_1
    //   2272: getfield C : Ljava/lang/String;
    //   2275: invokeinterface a : (Ljava/lang/String;)V
    //   2280: aload_1
    //   2281: getstatic v.a : [Lag;
    //   2284: aload_1
    //   2285: getfield c : B
    //   2288: aaload
    //   2289: invokeinterface b : ()J
    //   2294: l2i
    //   2295: dup
    //   2296: putstatic ai.e : I
    //   2299: putfield aR : I
    //   2302: new q
    //   2305: dup
    //   2306: aconst_null
    //   2307: getstatic v.a : [Lag;
    //   2310: aload_1
    //   2311: getfield c : B
    //   2314: aaload
    //   2315: invokeinterface a : ()Ljava/io/InputStream;
    //   2320: iconst_0
    //   2321: iconst_0
    //   2322: invokespecial <init> : (La;Ljava/io/InputStream;ZZ)V
    //   2325: astore #13
    //   2327: aload_1
    //   2328: getfield aP : I
    //   2331: iconst_3
    //   2332: if_icmpne -> 2341
    //   2335: getstatic v.aF : I
    //   2338: goto -> 2344
    //   2341: getstatic v.aE : I
    //   2344: istore #14
    //   2346: aload_1
    //   2347: getfield aP : I
    //   2350: iconst_2
    //   2351: if_icmpne -> 2394
    //   2354: aload_1
    //   2355: aload_0
    //   2356: aload #13
    //   2358: aload_1
    //   2359: getfield aQ : I
    //   2362: iload #14
    //   2364: invokespecial a : (Ljava/io/InputStream;II)Ljava/lang/String;
    //   2367: invokevirtual toCharArray : ()[C
    //   2370: putfield c : [C
    //   2373: aload_1
    //   2374: getfield h : Ljava/util/Vector;
    //   2377: new java/lang/Integer
    //   2380: dup
    //   2381: aload_0
    //   2382: getfield f : I
    //   2385: invokespecial <init> : (I)V
    //   2388: invokevirtual addElement : (Ljava/lang/Object;)V
    //   2391: goto -> 2413
    //   2394: aload_1
    //   2395: aload #13
    //   2397: aload_1
    //   2398: getfield aQ : I
    //   2401: iload #14
    //   2403: aload_1
    //   2404: getfield aP : I
    //   2407: invokestatic a : (Ljava/io/InputStream;III)[C
    //   2410: putfield c : [C
    //   2413: aload_1
    //   2414: iload #14
    //   2416: putfield aS : I
    //   2419: aload #13
    //   2421: invokestatic a : (Ljava/lang/Object;)Ljava/lang/String;
    //   2424: pop
    //   2425: getstatic v.a : [Lag;
    //   2428: aload_1
    //   2429: getfield c : B
    //   2432: aaload
    //   2433: invokeinterface b : ()V
    //   2438: goto -> 2616
    //   2441: astore #14
    //   2443: aload_0
    //   2444: getfield a : Ljava/lang/StringBuffer;
    //   2447: iconst_0
    //   2448: invokevirtual setLength : (I)V
    //   2451: getstatic af.b : Laf;
    //   2454: aload_0
    //   2455: getfield a : Ljava/lang/StringBuffer;
    //   2458: sipush #319
    //   2461: invokestatic d : (I)Ljava/lang/String;
    //   2464: invokevirtual append : (Ljava/lang/String;)Ljava/lang/StringBuffer;
    //   2467: bipush #10
    //   2469: invokevirtual append : (C)Ljava/lang/StringBuffer;
    //   2472: aload #14
    //   2474: invokevirtual append : (Ljava/lang/Object;)Ljava/lang/StringBuffer;
    //   2477: invokevirtual toString : ()Ljava/lang/String;
    //   2480: invokevirtual c : (Ljava/lang/String;)V
    //   2483: aload #13
    //   2485: invokestatic a : (Ljava/lang/Object;)Ljava/lang/String;
    //   2488: pop
    //   2489: getstatic v.a : [Lag;
    //   2492: aload_1
    //   2493: getfield c : B
    //   2496: aaload
    //   2497: invokeinterface b : ()V
    //   2502: goto -> 2616
    //   2505: astore #14
    //   2507: aload_1
    //   2508: aconst_null
    //   2509: putfield c : [C
    //   2512: getstatic v.aE : I
    //   2515: iconst_1
    //   2516: ishr
    //   2517: putstatic v.aE : I
    //   2520: getstatic v.aF : I
    //   2523: iconst_1
    //   2524: ishr
    //   2525: putstatic v.aF : I
    //   2528: invokestatic C : ()V
    //   2531: aload_0
    //   2532: getfield a : Ljava/lang/StringBuffer;
    //   2535: iconst_0
    //   2536: invokevirtual setLength : (I)V
    //   2539: getstatic af.b : Laf;
    //   2542: aload_0
    //   2543: getfield a : Ljava/lang/StringBuffer;
    //   2546: bipush #62
    //   2548: invokestatic d : (I)Ljava/lang/String;
    //   2551: invokevirtual append : (Ljava/lang/String;)Ljava/lang/StringBuffer;
    //   2554: bipush #10
    //   2556: invokevirtual append : (C)Ljava/lang/StringBuffer;
    //   2559: aload #14
    //   2561: invokevirtual append : (Ljava/lang/Object;)Ljava/lang/StringBuffer;
    //   2564: invokevirtual toString : ()Ljava/lang/String;
    //   2567: invokevirtual c : (Ljava/lang/String;)V
    //   2570: aload #13
    //   2572: invokestatic a : (Ljava/lang/Object;)Ljava/lang/String;
    //   2575: pop
    //   2576: getstatic v.a : [Lag;
    //   2579: aload_1
    //   2580: getfield c : B
    //   2583: aaload
    //   2584: invokeinterface b : ()V
    //   2589: goto -> 2616
    //   2592: astore #5
    //   2594: aload #13
    //   2596: invokestatic a : (Ljava/lang/Object;)Ljava/lang/String;
    //   2599: pop
    //   2600: getstatic v.a : [Lag;
    //   2603: aload_1
    //   2604: getfield c : B
    //   2607: aaload
    //   2608: invokeinterface b : ()V
    //   2613: aload #5
    //   2615: athrow
    //   2616: getstatic af.b : Laf;
    //   2619: sipush #29811
    //   2622: invokevirtual b : (I)V
    //   2625: goto -> 5422
    //   2628: getstatic ai.a : [B
    //   2631: ifnull -> 2666
    //   2634: getstatic ai.a : [B
    //   2637: arraylength
    //   2638: ifle -> 2666
    //   2641: aload_0
    //   2642: invokespecial y : ()V
    //   2645: getstatic v.a : [Lag;
    //   2648: aload_1
    //   2649: getfield c : B
    //   2652: aaload
    //   2653: getstatic ai.a : [B
    //   2656: iconst_0
    //   2657: getstatic ai.e : I
    //   2660: invokeinterface a : ([BII)Z
    //   2665: pop
    //   2666: aload_0
    //   2667: invokevirtual b : ()V
    //   2670: goto -> 5422
    //   2673: aload_0
    //   2674: iconst_0
    //   2675: putfield j : Z
    //   2678: getstatic ai.a : [B
    //   2681: ifnull -> 3013
    //   2684: aconst_null
    //   2685: invokestatic a : (Lag;)Lag;
    //   2688: dup
    //   2689: astore #14
    //   2691: aload_1
    //   2692: getfield C : Ljava/lang/String;
    //   2695: invokeinterface a : (Ljava/lang/String;)V
    //   2700: aconst_null
    //   2701: invokestatic a : (Lag;)Lag;
    //   2704: astore #15
    //   2706: new java/lang/StringBuffer
    //   2709: dup
    //   2710: iconst_0
    //   2711: invokespecial <init> : (I)V
    //   2714: astore #16
    //   2716: aload #16
    //   2718: aload_1
    //   2719: getfield C : Ljava/lang/String;
    //   2722: invokestatic g : (Ljava/lang/String;)Ljava/lang/String;
    //   2725: invokevirtual append : (Ljava/lang/String;)Ljava/lang/StringBuffer;
    //   2728: bipush #126
    //   2730: invokevirtual append : (C)Ljava/lang/StringBuffer;
    //   2733: invokestatic currentTimeMillis : ()J
    //   2736: invokevirtual append : (J)Ljava/lang/StringBuffer;
    //   2739: ldc '.tmp'
    //   2741: invokevirtual append : (Ljava/lang/String;)Ljava/lang/StringBuffer;
    //   2744: pop
    //   2745: aload #15
    //   2747: aload #16
    //   2749: invokevirtual toString : ()Ljava/lang/String;
    //   2752: invokeinterface a : (Ljava/lang/String;)V
    //   2757: aload #16
    //   2759: iconst_0
    //   2760: invokevirtual setLength : (I)V
    //   2763: aload #15
    //   2765: invokeinterface b : ()Z
    //   2770: ifne -> 2716
    //   2773: aload #15
    //   2775: invokeinterface a : ()Z
    //   2780: pop
    //   2781: aload #14
    //   2783: invokeinterface a : ()Ljava/io/InputStream;
    //   2788: astore #6
    //   2790: aload #15
    //   2792: lconst_0
    //   2793: invokeinterface a : (J)Ljava/io/OutputStream;
    //   2798: astore #17
    //   2800: aload #6
    //   2802: aload #17
    //   2804: aload_1
    //   2805: getfield aQ : I
    //   2808: aconst_null
    //   2809: invokestatic a : (Ljava/io/InputStream;Ljava/io/OutputStream;ILa;)I
    //   2812: pop
    //   2813: getstatic ai.a : [B
    //   2816: arraylength
    //   2817: ifle -> 2833
    //   2820: aload #17
    //   2822: getstatic ai.a : [B
    //   2825: iconst_0
    //   2826: getstatic ai.a : [B
    //   2829: arraylength
    //   2830: invokevirtual write : ([BII)V
    //   2833: aload_1
    //   2834: getfield aP : I
    //   2837: iconst_2
    //   2838: if_icmpne -> 2848
    //   2841: aload_0
    //   2842: getfield f : I
    //   2845: goto -> 2852
    //   2848: aload_1
    //   2849: getfield aS : I
    //   2852: istore #18
    //   2854: getstatic v.bd : I
    //   2857: iconst_2
    //   2858: if_icmpeq -> 2873
    //   2861: aload #6
    //   2863: iload #18
    //   2865: i2l
    //   2866: invokevirtual skip : (J)J
    //   2869: pop2
    //   2870: goto -> 2894
    //   2873: iload #18
    //   2875: istore #19
    //   2877: iinc #19, -1
    //   2880: iload #19
    //   2882: iflt -> 2894
    //   2885: aload #6
    //   2887: invokevirtual read : ()I
    //   2890: pop
    //   2891: goto -> 2877
    //   2894: aload #6
    //   2896: aload #17
    //   2898: aload_1
    //   2899: getfield aR : I
    //   2902: aload_1
    //   2903: getfield aQ : I
    //   2906: isub
    //   2907: iload #18
    //   2909: isub
    //   2910: aconst_null
    //   2911: invokestatic a : (Ljava/io/InputStream;Ljava/io/OutputStream;ILa;)I
    //   2914: pop
    //   2915: getstatic v.bd : I
    //   2918: iconst_4
    //   2919: if_icmpne -> 2947
    //   2922: aload #15
    //   2924: aload #17
    //   2926: checkcast java/io/ByteArrayOutputStream
    //   2929: invokevirtual toByteArray : ()[B
    //   2932: iconst_0
    //   2933: aload #17
    //   2935: checkcast java/io/ByteArrayOutputStream
    //   2938: invokevirtual size : ()I
    //   2941: invokeinterface a : ([BII)Z
    //   2946: pop
    //   2947: aload #17
    //   2949: invokestatic a : (Ljava/lang/Object;)Ljava/lang/String;
    //   2952: pop
    //   2953: aload #6
    //   2955: invokestatic a : (Ljava/lang/Object;)Ljava/lang/String;
    //   2958: pop
    //   2959: aload #14
    //   2961: iconst_0
    //   2962: invokeinterface a : (Z)Z
    //   2967: pop
    //   2968: getstatic v.bd : I
    //   2971: iconst_1
    //   2972: if_icmpne -> 2986
    //   2975: aload_0
    //   2976: aload_1
    //   2977: getfield C : Ljava/lang/String;
    //   2980: putfield d : Ljava/lang/String;
    //   2983: goto -> 2997
    //   2986: aload_0
    //   2987: aload_1
    //   2988: getfield C : Ljava/lang/String;
    //   2991: invokestatic e : (Ljava/lang/String;)Ljava/lang/String;
    //   2994: putfield d : Ljava/lang/String;
    //   2997: aload #15
    //   2999: aload_0
    //   3000: getfield d : Ljava/lang/String;
    //   3003: invokeinterface b : (Ljava/lang/String;)Z
    //   3008: pop
    //   3009: aconst_null
    //   3010: putstatic ai.a : [B
    //   3013: getstatic v.a : [Lag;
    //   3016: aload_1
    //   3017: getfield c : B
    //   3020: aaload
    //   3021: aload_1
    //   3022: getfield C : Ljava/lang/String;
    //   3025: invokeinterface a : (Ljava/lang/String;)V
    //   3030: aload_1
    //   3031: sipush #29811
    //   3034: invokevirtual d : (I)V
    //   3037: getstatic af.b : Laf;
    //   3040: invokestatic a : (Ljavax/microedition/lcdui/Displayable;)V
    //   3043: goto -> 5422
    //   3046: getstatic v.a : [Lag;
    //   3049: aload_1
    //   3050: getfield c : B
    //   3053: aaload
    //   3054: aload_0
    //   3055: invokevirtual a : ()Ljava/lang/String;
    //   3058: aload_0
    //   3059: getfield b : Ljava/lang/String;
    //   3062: invokestatic a : (Ljava/lang/String;Ljava/lang/String;)Ljava/lang/String;
    //   3065: invokeinterface a : (Ljava/lang/String;)V
    //   3070: new x
    //   3073: dup
    //   3074: iconst_0
    //   3075: invokespecial <init> : (B)V
    //   3078: dup
    //   3079: astore #14
    //   3081: getfield a : Ljavax/microedition/lcdui/Image;
    //   3084: ifnull -> 3102
    //   3087: aload #14
    //   3089: invokestatic a : (Ljavax/microedition/lcdui/Displayable;)V
    //   3092: aload #14
    //   3094: invokevirtual repaint : ()V
    //   3097: iconst_0
    //   3098: istore_2
    //   3099: goto -> 5422
    //   3102: getstatic af.b : Laf;
    //   3105: sipush #1000
    //   3108: sipush #492
    //   3111: invokestatic d : (I)Ljava/lang/String;
    //   3114: bipush #38
    //   3116: invokestatic d : (I)Ljava/lang/String;
    //   3119: invokevirtual a : (ILjava/lang/String;Ljava/lang/String;)V
    //   3122: goto -> 5422
    //   3125: getstatic v.b : [I
    //   3128: arraylength
    //   3129: dup
    //   3130: istore #15
    //   3132: iconst_3
    //   3133: imul
    //   3134: newarray byte
    //   3136: astore #16
    //   3138: iconst_0
    //   3139: istore #6
    //   3141: iload #6
    //   3143: iload #15
    //   3145: if_icmpge -> 3206
    //   3148: aload #16
    //   3150: iload #6
    //   3152: iconst_3
    //   3153: imul
    //   3154: getstatic v.b : [I
    //   3157: iload #6
    //   3159: iaload
    //   3160: bipush #16
    //   3162: ishr
    //   3163: i2b
    //   3164: bastore
    //   3165: aload #16
    //   3167: iload #6
    //   3169: iconst_3
    //   3170: imul
    //   3171: iconst_1
    //   3172: iadd
    //   3173: getstatic v.b : [I
    //   3176: iload #6
    //   3178: iaload
    //   3179: bipush #8
    //   3181: ishr
    //   3182: i2b
    //   3183: bastore
    //   3184: aload #16
    //   3186: iload #6
    //   3188: iconst_3
    //   3189: imul
    //   3190: iconst_2
    //   3191: iadd
    //   3192: getstatic v.b : [I
    //   3195: iload #6
    //   3197: iaload
    //   3198: i2b
    //   3199: bastore
    //   3200: iinc #6, 1
    //   3203: goto -> 3141
    //   3206: aload_0
    //   3207: invokespecial y : ()V
    //   3210: getstatic v.a : [Lag;
    //   3213: aload_1
    //   3214: getfield c : B
    //   3217: aaload
    //   3218: aload #16
    //   3220: invokeinterface a : ([B)Z
    //   3225: pop
    //   3226: aload_0
    //   3227: invokevirtual b : ()V
    //   3230: goto -> 5422
    //   3233: getstatic v.a : [Lag;
    //   3236: aload_1
    //   3237: getfield c : B
    //   3240: aaload
    //   3241: aload_0
    //   3242: invokevirtual a : ()Ljava/lang/String;
    //   3245: aload_0
    //   3246: getfield b : Ljava/lang/String;
    //   3249: invokestatic a : (Ljava/lang/String;Ljava/lang/String;)Ljava/lang/String;
    //   3252: invokeinterface a : (Ljava/lang/String;)V
    //   3257: getstatic v.a : [Lag;
    //   3260: aload_1
    //   3261: getfield c : B
    //   3264: aaload
    //   3265: invokeinterface a : ()[B
    //   3270: dup
    //   3271: astore #16
    //   3273: ifnull -> 3282
    //   3276: aload #16
    //   3278: arraylength
    //   3279: ifne -> 3291
    //   3282: iconst_0
    //   3283: putstatic ai.c : Z
    //   3286: aconst_null
    //   3287: putstatic ai.a : Ljava/lang/Thread;
    //   3290: return
    //   3291: getstatic v.a : [I
    //   3294: arraylength
    //   3295: newarray int
    //   3297: dup
    //   3298: putstatic v.b : [I
    //   3301: aload #16
    //   3303: invokestatic a : ([I[B)V
    //   3306: goto -> 3351
    //   3309: astore #6
    //   3311: aload_0
    //   3312: getfield a : Ljava/lang/StringBuffer;
    //   3315: iconst_0
    //   3316: invokevirtual setLength : (I)V
    //   3319: getstatic af.b : Laf;
    //   3322: aload_0
    //   3323: getfield a : Ljava/lang/StringBuffer;
    //   3326: sipush #610
    //   3329: invokestatic d : (I)Ljava/lang/String;
    //   3332: invokevirtual append : (Ljava/lang/String;)Ljava/lang/StringBuffer;
    //   3335: bipush #10
    //   3337: invokevirtual append : (C)Ljava/lang/StringBuffer;
    //   3340: aload #6
    //   3342: invokevirtual append : (Ljava/lang/Object;)Ljava/lang/StringBuffer;
    //   3345: invokevirtual toString : ()Ljava/lang/String;
    //   3348: invokevirtual c : (Ljava/lang/String;)V
    //   3351: invokestatic J : ()V
    //   3354: aload_1
    //   3355: ifnull -> 3363
    //   3358: aload_1
    //   3359: iconst_0
    //   3360: invokevirtual d : (Z)V
    //   3363: aload_1
    //   3364: iconst_m1
    //   3365: putfield bz : I
    //   3368: getstatic af.b : Laf;
    //   3371: sipush #17235
    //   3374: invokevirtual b : (I)V
    //   3377: goto -> 5422
    //   3380: getstatic ai.a : [B
    //   3383: ifnull -> 3419
    //   3386: getstatic ai.a : [B
    //   3389: arraylength
    //   3390: ifle -> 3419
    //   3393: aload_0
    //   3394: invokespecial y : ()V
    //   3397: getstatic v.a : [Lag;
    //   3400: aload_1
    //   3401: getfield c : B
    //   3404: aaload
    //   3405: getstatic ai.a : [B
    //   3408: iconst_0
    //   3409: getstatic ai.a : [B
    //   3412: arraylength
    //   3413: invokeinterface a : ([BII)Z
    //   3418: pop
    //   3419: aconst_null
    //   3420: putstatic ai.a : [B
    //   3423: aload_0
    //   3424: invokevirtual b : ()V
    //   3427: goto -> 5422
    //   3430: getstatic v.b : Lz;
    //   3433: getfield a : Ljava/util/Vector;
    //   3436: invokevirtual size : ()I
    //   3439: istore #6
    //   3441: new java/io/ByteArrayOutputStream
    //   3444: dup
    //   3445: invokespecial <init> : ()V
    //   3448: astore #17
    //   3450: aload_0
    //   3451: getfield a : Ljava/lang/StringBuffer;
    //   3454: iconst_0
    //   3455: invokevirtual setLength : (I)V
    //   3458: iconst_0
    //   3459: istore #18
    //   3461: iload #18
    //   3463: iload #6
    //   3465: if_icmpge -> 3737
    //   3468: aload_0
    //   3469: getfield a : Ljava/lang/StringBuffer;
    //   3472: iconst_0
    //   3473: invokevirtual setLength : (I)V
    //   3476: aload_0
    //   3477: getfield a : Ljava/lang/StringBuffer;
    //   3480: iload #18
    //   3482: ifne -> 3494
    //   3485: sipush #154
    //   3488: invokestatic d : (I)Ljava/lang/String;
    //   3491: goto -> 3496
    //   3494: ldc ''
    //   3496: invokevirtual append : (Ljava/lang/String;)Ljava/lang/StringBuffer;
    //   3499: bipush #10
    //   3501: invokevirtual append : (C)Ljava/lang/StringBuffer;
    //   3504: ldc '<p_item>'
    //   3506: invokevirtual append : (Ljava/lang/String;)Ljava/lang/StringBuffer;
    //   3509: bipush #10
    //   3511: invokevirtual append : (C)Ljava/lang/StringBuffer;
    //   3514: bipush #9
    //   3516: invokevirtual append : (C)Ljava/lang/StringBuffer;
    //   3519: ldc '<p_record>'
    //   3521: invokevirtual append : (Ljava/lang/String;)Ljava/lang/StringBuffer;
    //   3524: getstatic v.b : Lz;
    //   3527: getfield a : Ljava/util/Vector;
    //   3530: iload #18
    //   3532: invokevirtual elementAt : (I)Ljava/lang/Object;
    //   3535: checkcast [Ljava/lang/Object;
    //   3538: iconst_4
    //   3539: aaload
    //   3540: checkcast java/lang/String
    //   3543: invokevirtual append : (Ljava/lang/String;)Ljava/lang/StringBuffer;
    //   3546: ldc '</p_record>'
    //   3548: invokevirtual append : (Ljava/lang/String;)Ljava/lang/StringBuffer;
    //   3551: bipush #10
    //   3553: invokevirtual append : (C)Ljava/lang/StringBuffer;
    //   3556: bipush #9
    //   3558: invokevirtual append : (C)Ljava/lang/StringBuffer;
    //   3561: ldc '<p_record>'
    //   3563: invokevirtual append : (Ljava/lang/String;)Ljava/lang/StringBuffer;
    //   3566: getstatic v.b : Lz;
    //   3569: getfield a : Ljava/util/Vector;
    //   3572: iload #18
    //   3574: invokevirtual elementAt : (I)Ljava/lang/Object;
    //   3577: checkcast [Ljava/lang/Object;
    //   3580: iconst_1
    //   3581: aaload
    //   3582: checkcast java/lang/String
    //   3585: invokevirtual append : (Ljava/lang/String;)Ljava/lang/StringBuffer;
    //   3588: ldc '</p_record>'
    //   3590: invokevirtual append : (Ljava/lang/String;)Ljava/lang/StringBuffer;
    //   3593: bipush #10
    //   3595: invokevirtual append : (C)Ljava/lang/StringBuffer;
    //   3598: bipush #9
    //   3600: invokevirtual append : (C)Ljava/lang/StringBuffer;
    //   3603: ldc '<p_record>'
    //   3605: invokevirtual append : (Ljava/lang/String;)Ljava/lang/StringBuffer;
    //   3608: getstatic v.b : Lz;
    //   3611: getfield a : Ljava/util/Vector;
    //   3614: iload #18
    //   3616: invokevirtual elementAt : (I)Ljava/lang/Object;
    //   3619: checkcast [Ljava/lang/Object;
    //   3622: iconst_0
    //   3623: aaload
    //   3624: checkcast java/lang/String
    //   3627: invokevirtual append : (Ljava/lang/String;)Ljava/lang/StringBuffer;
    //   3630: ldc '</p_record>'
    //   3632: invokevirtual append : (Ljava/lang/String;)Ljava/lang/StringBuffer;
    //   3635: bipush #10
    //   3637: invokevirtual append : (C)Ljava/lang/StringBuffer;
    //   3640: bipush #9
    //   3642: invokevirtual append : (C)Ljava/lang/StringBuffer;
    //   3645: ldc '<p_record>'
    //   3647: invokevirtual append : (Ljava/lang/String;)Ljava/lang/StringBuffer;
    //   3650: getstatic v.b : Lz;
    //   3653: getfield a : Ljava/util/Vector;
    //   3656: iload #18
    //   3658: invokevirtual elementAt : (I)Ljava/lang/Object;
    //   3661: checkcast [Ljava/lang/Object;
    //   3664: iconst_3
    //   3665: aaload
    //   3666: checkcast java/lang/Byte
    //   3669: invokevirtual append : (Ljava/lang/Object;)Ljava/lang/StringBuffer;
    //   3672: ldc '</p_record>'
    //   3674: invokevirtual append : (Ljava/lang/String;)Ljava/lang/StringBuffer;
    //   3677: bipush #10
    //   3679: invokevirtual append : (C)Ljava/lang/StringBuffer;
    //   3682: ldc '</p_item>'
    //   3684: invokevirtual append : (Ljava/lang/String;)Ljava/lang/StringBuffer;
    //   3687: invokevirtual toString : ()Ljava/lang/String;
    //   3690: invokevirtual toCharArray : ()[C
    //   3693: dup
    //   3694: astore #19
    //   3696: iconst_0
    //   3697: aload #19
    //   3699: arraylength
    //   3700: aconst_null
    //   3701: iconst_0
    //   3702: iconst_1
    //   3703: invokestatic a : ([CII[BIZ)I
    //   3706: newarray byte
    //   3708: astore #20
    //   3710: aload #19
    //   3712: iconst_0
    //   3713: aload #19
    //   3715: arraylength
    //   3716: aload #20
    //   3718: iconst_0
    //   3719: iconst_0
    //   3720: invokestatic a : ([CII[BIZ)I
    //   3723: pop
    //   3724: aload #17
    //   3726: aload #20
    //   3728: invokevirtual write : ([B)V
    //   3731: iinc #18, 1
    //   3734: goto -> 3461
    //   3737: aload_0
    //   3738: invokespecial y : ()V
    //   3741: getstatic v.a : [Lag;
    //   3744: aload_1
    //   3745: getfield c : B
    //   3748: aaload
    //   3749: aload #17
    //   3751: invokevirtual toByteArray : ()[B
    //   3754: iconst_0
    //   3755: aload #17
    //   3757: invokevirtual size : ()I
    //   3760: invokeinterface a : ([BII)Z
    //   3765: pop
    //   3766: aload #17
    //   3768: invokestatic a : (Ljava/lang/Object;)Ljava/lang/String;
    //   3771: pop
    //   3772: aload_0
    //   3773: invokevirtual b : ()V
    //   3776: goto -> 5422
    //   3779: getstatic v.a : [Lag;
    //   3782: aload_1
    //   3783: getfield c : B
    //   3786: aaload
    //   3787: aload_0
    //   3788: invokevirtual a : ()Ljava/lang/String;
    //   3791: aload_0
    //   3792: getfield b : Ljava/lang/String;
    //   3795: invokestatic a : (Ljava/lang/String;Ljava/lang/String;)Ljava/lang/String;
    //   3798: invokeinterface a : (Ljava/lang/String;)V
    //   3803: new java/io/ByteArrayInputStream
    //   3806: dup
    //   3807: getstatic v.a : [Lag;
    //   3810: aload_1
    //   3811: getfield c : B
    //   3814: aaload
    //   3815: invokeinterface a : ()[B
    //   3820: invokespecial <init> : ([B)V
    //   3823: astore #18
    //   3825: ldc ''
    //   3827: astore #19
    //   3829: aload_0
    //   3830: aload #18
    //   3832: iconst_0
    //   3833: aload #18
    //   3835: invokevirtual available : ()I
    //   3838: invokespecial a : (Ljava/io/InputStream;II)Ljava/lang/String;
    //   3841: astore #19
    //   3843: goto -> 3877
    //   3846: pop
    //   3847: getstatic af.b : Laf;
    //   3850: sipush #319
    //   3853: invokestatic d : (I)Ljava/lang/String;
    //   3856: invokevirtual c : (Ljava/lang/String;)V
    //   3859: goto -> 3877
    //   3862: pop
    //   3863: invokestatic C : ()V
    //   3866: getstatic af.b : Laf;
    //   3869: bipush #62
    //   3871: invokestatic d : (I)Ljava/lang/String;
    //   3874: invokevirtual c : (Ljava/lang/String;)V
    //   3877: getstatic v.b : Lz;
    //   3880: new java/util/Vector
    //   3883: dup
    //   3884: iconst_0
    //   3885: invokespecial <init> : (I)V
    //   3888: putfield a : Ljava/util/Vector;
    //   3891: iconst_4
    //   3892: newarray int
    //   3894: dup
    //   3895: iconst_0
    //   3896: iconst_4
    //   3897: iastore
    //   3898: dup
    //   3899: iconst_1
    //   3900: iconst_1
    //   3901: iastore
    //   3902: dup
    //   3903: iconst_2
    //   3904: iconst_0
    //   3905: iastore
    //   3906: dup
    //   3907: iconst_3
    //   3908: iconst_3
    //   3909: iastore
    //   3910: astore #20
    //   3912: ldc '<p_item>'
    //   3914: invokevirtual length : ()I
    //   3917: istore #5
    //   3919: ldc '<p_record>'
    //   3921: invokevirtual length : ()I
    //   3924: istore #7
    //   3926: aload #19
    //   3928: ldc '<p_item>'
    //   3930: invokevirtual indexOf : (Ljava/lang/String;)I
    //   3933: istore #8
    //   3935: aload #19
    //   3937: ldc '</p_item>'
    //   3939: invokevirtual indexOf : (Ljava/lang/String;)I
    //   3942: istore #9
    //   3944: iload #8
    //   3946: iflt -> 4132
    //   3949: iload #9
    //   3951: aload #19
    //   3953: invokevirtual length : ()I
    //   3956: if_icmpge -> 4132
    //   3959: aload #19
    //   3961: iload #8
    //   3963: iload #5
    //   3965: iadd
    //   3966: iload #9
    //   3968: invokevirtual substring : (II)Ljava/lang/String;
    //   3971: astore #10
    //   3973: iconst_0
    //   3974: istore #6
    //   3976: iconst_5
    //   3977: anewarray java/lang/Object
    //   3980: astore #11
    //   3982: aload #10
    //   3984: ldc '<p_record>'
    //   3986: invokevirtual indexOf : (Ljava/lang/String;)I
    //   3989: istore #12
    //   3991: aload #10
    //   3993: ldc '</p_record>'
    //   3995: invokevirtual indexOf : (Ljava/lang/String;)I
    //   3998: istore #13
    //   4000: iload #12
    //   4002: iflt -> 4100
    //   4005: iload #13
    //   4007: aload #10
    //   4009: invokevirtual length : ()I
    //   4012: if_icmpge -> 4100
    //   4015: aload #10
    //   4017: iload #12
    //   4019: iload #7
    //   4021: iadd
    //   4022: iload #13
    //   4024: invokevirtual substring : (II)Ljava/lang/String;
    //   4027: astore #14
    //   4029: aload #11
    //   4031: aload #20
    //   4033: iload #6
    //   4035: iaload
    //   4036: aload #20
    //   4038: iload #6
    //   4040: iaload
    //   4041: iconst_3
    //   4042: if_icmpeq -> 4050
    //   4045: aload #14
    //   4047: goto -> 4065
    //   4050: new java/lang/Byte
    //   4053: dup
    //   4054: aload #14
    //   4056: checkcast java/lang/String
    //   4059: invokestatic parseByte : (Ljava/lang/String;)B
    //   4062: invokespecial <init> : (B)V
    //   4065: aastore
    //   4066: aload #10
    //   4068: iload #13
    //   4070: iload #7
    //   4072: iadd
    //   4073: iconst_1
    //   4074: iadd
    //   4075: invokevirtual substring : (I)Ljava/lang/String;
    //   4078: astore #10
    //   4080: iinc #6, 1
    //   4083: iload #6
    //   4085: iconst_3
    //   4086: if_icmple -> 4092
    //   4089: iconst_0
    //   4090: istore #6
    //   4092: aload #10
    //   4094: invokevirtual length : ()I
    //   4097: ifgt -> 3982
    //   4100: getstatic v.b : Lz;
    //   4103: getfield a : Ljava/util/Vector;
    //   4106: aload #11
    //   4108: invokevirtual addElement : (Ljava/lang/Object;)V
    //   4111: aload #19
    //   4113: iload #9
    //   4115: iload #5
    //   4117: iadd
    //   4118: iconst_1
    //   4119: iadd
    //   4120: invokevirtual substring : (I)Ljava/lang/String;
    //   4123: dup
    //   4124: astore #19
    //   4126: invokevirtual length : ()I
    //   4129: ifgt -> 3926
    //   4132: aload #18
    //   4134: invokestatic a : (Ljava/lang/Object;)Ljava/lang/String;
    //   4137: pop
    //   4138: invokestatic H : ()V
    //   4141: getstatic v.b : Lz;
    //   4144: ldc '/'
    //   4146: putfield a : Ljava/lang/String;
    //   4149: aload_1
    //   4150: iconst_0
    //   4151: invokevirtual d : (Z)V
    //   4154: getstatic af.b : Laf;
    //   4157: getstatic af.b : Laf;
    //   4160: getfield b : Lr;
    //   4163: invokevirtual d : (Lr;)V
    //   4166: goto -> 5422
    //   4169: iconst_0
    //   4170: iconst_0
    //   4171: invokestatic b : (ZZ)V
    //   4174: getstatic v.a : [Lag;
    //   4177: aload_1
    //   4178: getfield c : B
    //   4181: aaload
    //   4182: aload_0
    //   4183: invokevirtual a : ()Ljava/lang/String;
    //   4186: invokestatic b : ()Ljava/lang/String;
    //   4189: ldc '.omb'
    //   4191: invokestatic a : (Ljava/lang/String;Ljava/lang/String;Ljava/lang/String;)Ljava/lang/String;
    //   4194: invokeinterface a : (Ljava/lang/String;)V
    //   4199: invokestatic a : ()[B
    //   4202: dup
    //   4203: astore #19
    //   4205: ifnull -> 4231
    //   4208: getstatic v.a : [Lag;
    //   4211: aload_1
    //   4212: getfield c : B
    //   4215: aaload
    //   4216: aload #19
    //   4218: invokeinterface a : ([B)Z
    //   4223: ifeq -> 4231
    //   4226: bipush #24
    //   4228: goto -> 4233
    //   4231: bipush #38
    //   4233: istore_3
    //   4234: sipush #202
    //   4237: istore #4
    //   4239: aload_0
    //   4240: iconst_1
    //   4241: putfield j : Z
    //   4244: aload_0
    //   4245: invokevirtual b : ()V
    //   4248: goto -> 5422
    //   4251: getstatic v.a : [Lag;
    //   4254: aload_1
    //   4255: getfield c : B
    //   4258: aaload
    //   4259: aload_0
    //   4260: invokevirtual a : ()Ljava/lang/String;
    //   4263: aload_0
    //   4264: getfield b : Ljava/lang/String;
    //   4267: invokestatic a : (Ljava/lang/String;Ljava/lang/String;)Ljava/lang/String;
    //   4270: invokeinterface a : (Ljava/lang/String;)V
    //   4275: getstatic v.a : [Lag;
    //   4278: aload_1
    //   4279: getfield c : B
    //   4282: aaload
    //   4283: invokeinterface a : ()[B
    //   4288: invokestatic a : ([B)Z
    //   4291: pop
    //   4292: goto -> 5422
    //   4295: aload_0
    //   4296: invokespecial y : ()V
    //   4299: invokestatic b : ()[B
    //   4302: dup
    //   4303: astore #20
    //   4305: ifnull -> 5422
    //   4308: getstatic v.a : [Lag;
    //   4311: aload_1
    //   4312: getfield c : B
    //   4315: aaload
    //   4316: aload #20
    //   4318: invokeinterface a : ([B)Z
    //   4323: ifeq -> 5422
    //   4326: aload_0
    //   4327: invokevirtual b : ()V
    //   4330: goto -> 5422
    //   4333: getstatic v.a : [Lag;
    //   4336: aload_1
    //   4337: getfield c : B
    //   4340: aaload
    //   4341: aload_0
    //   4342: invokevirtual a : ()Ljava/lang/String;
    //   4345: aload_0
    //   4346: getfield b : Ljava/lang/String;
    //   4349: invokestatic a : (Ljava/lang/String;Ljava/lang/String;)Ljava/lang/String;
    //   4352: invokeinterface a : (Ljava/lang/String;)V
    //   4357: getstatic v.a : [Lag;
    //   4360: aload_1
    //   4361: getfield c : B
    //   4364: aaload
    //   4365: invokeinterface a : ()[B
    //   4370: invokestatic b : ([B)V
    //   4373: getstatic af.b : Laf;
    //   4376: invokevirtual repaint : ()V
    //   4379: goto -> 5422
    //   4382: aload_0
    //   4383: iconst_0
    //   4384: putfield j : Z
    //   4387: getstatic af.b : Laf;
    //   4390: ldc 53262
    //   4392: invokevirtual b : (I)V
    //   4395: goto -> 5422
    //   4398: getstatic v.a : [Lag;
    //   4401: aload_1
    //   4402: getfield c : B
    //   4405: aaload
    //   4406: aload_0
    //   4407: invokevirtual a : ()Ljava/lang/String;
    //   4410: aload_0
    //   4411: getfield b : Ljava/lang/String;
    //   4414: invokestatic a : (Ljava/lang/String;Ljava/lang/String;)Ljava/lang/String;
    //   4417: invokeinterface a : (Ljava/lang/String;)V
    //   4422: getstatic v.a : [Lag;
    //   4425: aload_1
    //   4426: getfield c : B
    //   4429: aaload
    //   4430: invokeinterface a : ()[B
    //   4435: astore #5
    //   4437: getstatic ai.d : I
    //   4440: bipush #43
    //   4442: if_icmpne -> 4459
    //   4445: aload #5
    //   4447: iconst_0
    //   4448: aload #5
    //   4450: arraylength
    //   4451: invokestatic a : ([BII)[B
    //   4454: astore #5
    //   4456: goto -> 4527
    //   4459: new java/lang/StringBuffer
    //   4462: dup
    //   4463: aload #5
    //   4465: arraylength
    //   4466: invokespecial <init> : (I)V
    //   4469: astore #7
    //   4471: iconst_0
    //   4472: istore #8
    //   4474: iload #8
    //   4476: aload #5
    //   4478: arraylength
    //   4479: if_icmpge -> 4514
    //   4482: aload #5
    //   4484: iload #8
    //   4486: baload
    //   4487: sipush #255
    //   4490: iand
    //   4491: bipush #32
    //   4493: if_icmple -> 4508
    //   4496: aload #7
    //   4498: aload #5
    //   4500: iload #8
    //   4502: baload
    //   4503: i2c
    //   4504: invokevirtual append : (C)Ljava/lang/StringBuffer;
    //   4507: pop
    //   4508: iinc #8, 1
    //   4511: goto -> 4474
    //   4514: aload #7
    //   4516: invokevirtual toString : ()Ljava/lang/String;
    //   4519: invokevirtual getBytes : ()[B
    //   4522: invokestatic a : ([B)[B
    //   4525: astore #5
    //   4527: getstatic ai.d : I
    //   4530: bipush #43
    //   4532: if_icmpne -> 4551
    //   4535: aload_0
    //   4536: aload_0
    //   4537: getfield b : Ljava/lang/String;
    //   4540: ldc '.base64'
    //   4542: invokestatic a : (Ljava/lang/String;Ljava/lang/String;)Ljava/lang/String;
    //   4545: putfield d : Ljava/lang/String;
    //   4548: goto -> 4604
    //   4551: aload_0
    //   4552: getfield b : Ljava/lang/String;
    //   4555: bipush #46
    //   4557: invokevirtual lastIndexOf : (I)I
    //   4560: dup
    //   4561: istore #7
    //   4563: iconst_m1
    //   4564: if_icmpeq -> 4596
    //   4567: aload_0
    //   4568: getfield b : Ljava/lang/String;
    //   4571: ldc '.base64'
    //   4573: invokevirtual endsWith : (Ljava/lang/String;)Z
    //   4576: ifeq -> 4596
    //   4579: aload_0
    //   4580: aload_0
    //   4581: getfield b : Ljava/lang/String;
    //   4584: iconst_0
    //   4585: iload #7
    //   4587: invokevirtual substring : (II)Ljava/lang/String;
    //   4590: putfield d : Ljava/lang/String;
    //   4593: goto -> 4604
    //   4596: aload_0
    //   4597: aload_0
    //   4598: getfield b : Ljava/lang/String;
    //   4601: putfield d : Ljava/lang/String;
    //   4604: getstatic v.a : [Lag;
    //   4607: aload_1
    //   4608: getfield c : B
    //   4611: aaload
    //   4612: aload_0
    //   4613: invokevirtual a : ()Ljava/lang/String;
    //   4616: aload_0
    //   4617: getfield d : Ljava/lang/String;
    //   4620: invokestatic a : (Ljava/lang/String;Ljava/lang/String;)Ljava/lang/String;
    //   4623: invokeinterface a : (Ljava/lang/String;)V
    //   4628: getstatic v.a : [Lag;
    //   4631: aload_1
    //   4632: getfield c : B
    //   4635: aaload
    //   4636: aload #5
    //   4638: invokeinterface a : ([B)Z
    //   4643: pop
    //   4644: iconst_0
    //   4645: istore_3
    //   4646: sipush #570
    //   4649: istore #4
    //   4651: aload_0
    //   4652: invokevirtual b : ()V
    //   4655: goto -> 5422
    //   4658: getstatic w.b : Ljava/util/Vector;
    //   4661: invokevirtual size : ()I
    //   4664: istore #6
    //   4666: new java/io/ByteArrayOutputStream
    //   4669: dup
    //   4670: invokespecial <init> : ()V
    //   4673: astore #17
    //   4675: iconst_0
    //   4676: istore #7
    //   4678: iload #7
    //   4680: iload #6
    //   4682: if_icmpge -> 4862
    //   4685: getstatic w.b : Ljava/util/Vector;
    //   4688: iload #7
    //   4690: invokevirtual elementAt : (I)Ljava/lang/Object;
    //   4693: checkcast [Ljava/lang/String;
    //   4696: astore #8
    //   4698: aload_0
    //   4699: getfield a : Ljava/lang/StringBuffer;
    //   4702: iconst_0
    //   4703: invokevirtual setLength : (I)V
    //   4706: aload_0
    //   4707: getfield a : Ljava/lang/StringBuffer;
    //   4710: iload #7
    //   4712: ifne -> 4724
    //   4715: sipush #498
    //   4718: invokestatic d : (I)Ljava/lang/String;
    //   4721: goto -> 4726
    //   4724: ldc ''
    //   4726: invokevirtual append : (Ljava/lang/String;)Ljava/lang/StringBuffer;
    //   4729: bipush #10
    //   4731: invokevirtual append : (C)Ljava/lang/StringBuffer;
    //   4734: ldc '<p_item>'
    //   4736: invokevirtual append : (Ljava/lang/String;)Ljava/lang/StringBuffer;
    //   4739: bipush #10
    //   4741: invokevirtual append : (C)Ljava/lang/StringBuffer;
    //   4744: pop
    //   4745: iconst_0
    //   4746: istore #9
    //   4748: iload #9
    //   4750: aload #8
    //   4752: arraylength
    //   4753: if_icmpge -> 4798
    //   4756: aload_0
    //   4757: getfield a : Ljava/lang/StringBuffer;
    //   4760: bipush #32
    //   4762: invokevirtual append : (C)Ljava/lang/StringBuffer;
    //   4765: ldc '<p_record>'
    //   4767: invokevirtual append : (Ljava/lang/String;)Ljava/lang/StringBuffer;
    //   4770: aload #8
    //   4772: iload #9
    //   4774: aaload
    //   4775: invokestatic i : (Ljava/lang/String;)Ljava/lang/String;
    //   4778: invokevirtual append : (Ljava/lang/String;)Ljava/lang/StringBuffer;
    //   4781: ldc '</p_record>'
    //   4783: invokevirtual append : (Ljava/lang/String;)Ljava/lang/StringBuffer;
    //   4786: bipush #10
    //   4788: invokevirtual append : (C)Ljava/lang/StringBuffer;
    //   4791: pop
    //   4792: iinc #9, 1
    //   4795: goto -> 4748
    //   4798: aload_0
    //   4799: getfield a : Ljava/lang/StringBuffer;
    //   4802: ldc '</p_item>'
    //   4804: invokevirtual append : (Ljava/lang/String;)Ljava/lang/StringBuffer;
    //   4807: pop
    //   4808: aload_0
    //   4809: getfield a : Ljava/lang/StringBuffer;
    //   4812: invokevirtual toString : ()Ljava/lang/String;
    //   4815: invokevirtual toCharArray : ()[C
    //   4818: dup
    //   4819: astore #9
    //   4821: iconst_0
    //   4822: aload #9
    //   4824: arraylength
    //   4825: aconst_null
    //   4826: iconst_0
    //   4827: iconst_1
    //   4828: invokestatic a : ([CII[BIZ)I
    //   4831: newarray byte
    //   4833: astore #10
    //   4835: aload #9
    //   4837: iconst_0
    //   4838: aload #9
    //   4840: arraylength
    //   4841: aload #10
    //   4843: iconst_0
    //   4844: iconst_0
    //   4845: invokestatic a : ([CII[BIZ)I
    //   4848: pop
    //   4849: aload #17
    //   4851: aload #10
    //   4853: invokevirtual write : ([B)V
    //   4856: iinc #7, 1
    //   4859: goto -> 4678
    //   4862: aload_0
    //   4863: invokespecial y : ()V
    //   4866: getstatic v.a : [Lag;
    //   4869: aload_1
    //   4870: getfield c : B
    //   4873: aaload
    //   4874: aload #17
    //   4876: invokevirtual toByteArray : ()[B
    //   4879: iconst_0
    //   4880: aload #17
    //   4882: invokevirtual size : ()I
    //   4885: invokeinterface a : ([BII)Z
    //   4890: pop
    //   4891: aload #17
    //   4893: invokestatic a : (Ljava/lang/Object;)Ljava/lang/String;
    //   4896: pop
    //   4897: aload_0
    //   4898: invokevirtual b : ()V
    //   4901: goto -> 5422
    //   4904: aload_0
    //   4905: iconst_0
    //   4906: putfield j : Z
    //   4909: getstatic v.a : [Lag;
    //   4912: aload_1
    //   4913: getfield c : B
    //   4916: aaload
    //   4917: aload_0
    //   4918: invokevirtual a : ()Ljava/lang/String;
    //   4921: aload_0
    //   4922: getfield b : Ljava/lang/String;
    //   4925: invokestatic a : (Ljava/lang/String;Ljava/lang/String;)Ljava/lang/String;
    //   4928: invokeinterface a : (Ljava/lang/String;)V
    //   4933: new java/io/ByteArrayInputStream
    //   4936: dup
    //   4937: getstatic v.a : [Lag;
    //   4940: aload_1
    //   4941: getfield c : B
    //   4944: aaload
    //   4945: invokeinterface a : ()[B
    //   4950: invokespecial <init> : ([B)V
    //   4953: astore #18
    //   4955: ldc ''
    //   4957: astore #7
    //   4959: aload_0
    //   4960: aload #18
    //   4962: iconst_0
    //   4963: aload #18
    //   4965: invokevirtual available : ()I
    //   4968: invokespecial a : (Ljava/io/InputStream;II)Ljava/lang/String;
    //   4971: astore #7
    //   4973: goto -> 5007
    //   4976: pop
    //   4977: getstatic af.b : Laf;
    //   4980: sipush #319
    //   4983: invokestatic d : (I)Ljava/lang/String;
    //   4986: invokevirtual c : (Ljava/lang/String;)V
    //   4989: goto -> 5007
    //   4992: pop
    //   4993: invokestatic C : ()V
    //   4996: getstatic af.b : Laf;
    //   4999: bipush #62
    //   5001: invokestatic d : (I)Ljava/lang/String;
    //   5004: invokevirtual c : (Ljava/lang/String;)V
    //   5007: new java/util/Vector
    //   5010: dup
    //   5011: iconst_0
    //   5012: invokespecial <init> : (I)V
    //   5015: putstatic w.b : Ljava/util/Vector;
    //   5018: ldc '<p_item>'
    //   5020: invokevirtual length : ()I
    //   5023: istore #8
    //   5025: ldc '<p_record>'
    //   5027: invokevirtual length : ()I
    //   5030: istore #9
    //   5032: aload #7
    //   5034: ldc '<p_item>'
    //   5036: invokevirtual indexOf : (Ljava/lang/String;)I
    //   5039: istore #10
    //   5041: aload #7
    //   5043: ldc '</p_item>'
    //   5045: invokevirtual indexOf : (Ljava/lang/String;)I
    //   5048: istore #6
    //   5050: iload #10
    //   5052: iflt -> 5195
    //   5055: iload #6
    //   5057: aload #7
    //   5059: invokevirtual length : ()I
    //   5062: if_icmpge -> 5195
    //   5065: aload #7
    //   5067: iload #10
    //   5069: iload #8
    //   5071: iadd
    //   5072: iload #6
    //   5074: invokevirtual substring : (II)Ljava/lang/String;
    //   5077: astore #11
    //   5079: iconst_0
    //   5080: istore #12
    //   5082: bipush #10
    //   5084: anewarray java/lang/String
    //   5087: astore #13
    //   5089: aload #11
    //   5091: ldc '<p_record>'
    //   5093: invokevirtual indexOf : (Ljava/lang/String;)I
    //   5096: istore #14
    //   5098: aload #11
    //   5100: ldc '</p_record>'
    //   5102: invokevirtual indexOf : (Ljava/lang/String;)I
    //   5105: istore #5
    //   5107: iload #14
    //   5109: iflt -> 5166
    //   5112: iload #5
    //   5114: aload #11
    //   5116: invokevirtual length : ()I
    //   5119: if_icmpge -> 5166
    //   5122: aload #13
    //   5124: iload #12
    //   5126: iinc #12, 1
    //   5129: aload #11
    //   5131: iload #14
    //   5133: iload #9
    //   5135: iadd
    //   5136: iload #5
    //   5138: invokevirtual substring : (II)Ljava/lang/String;
    //   5141: invokevirtual trim : ()Ljava/lang/String;
    //   5144: aastore
    //   5145: aload #11
    //   5147: iload #5
    //   5149: iload #9
    //   5151: iadd
    //   5152: iconst_1
    //   5153: iadd
    //   5154: invokevirtual substring : (I)Ljava/lang/String;
    //   5157: dup
    //   5158: astore #11
    //   5160: invokevirtual length : ()I
    //   5163: ifgt -> 5089
    //   5166: getstatic w.b : Ljava/util/Vector;
    //   5169: aload #13
    //   5171: invokevirtual addElement : (Ljava/lang/Object;)V
    //   5174: aload #7
    //   5176: iload #6
    //   5178: iload #8
    //   5180: iadd
    //   5181: iconst_1
    //   5182: iadd
    //   5183: invokevirtual substring : (I)Ljava/lang/String;
    //   5186: dup
    //   5187: astore #7
    //   5189: invokevirtual length : ()I
    //   5192: ifgt -> 5032
    //   5195: aload #18
    //   5197: invokestatic a : (Ljava/lang/Object;)Ljava/lang/String;
    //   5200: pop
    //   5201: aconst_null
    //   5202: invokestatic c : (Ljava/io/DataOutputStream;)Ljava/io/DataOutputStream;
    //   5205: pop
    //   5206: aload_1
    //   5207: sipush #17466
    //   5210: invokevirtual d : (I)V
    //   5213: goto -> 5422
    //   5216: invokestatic C : ()V
    //   5219: getstatic v.cc : Z
    //   5222: ifeq -> 5246
    //   5225: getstatic v.a : Ljavax/microedition/lcdui/Image;
    //   5228: invokevirtual getWidth : ()I
    //   5231: getstatic v.a : Ljavax/microedition/lcdui/Image;
    //   5234: invokevirtual getHeight : ()I
    //   5237: getstatic v.a : Ljavax/microedition/lcdui/Image;
    //   5240: invokestatic a : (IILjavax/microedition/lcdui/Image;)[B
    //   5243: goto -> 5264
    //   5246: getstatic v.a : Ljavax/microedition/lcdui/Image;
    //   5249: invokevirtual getWidth : ()I
    //   5252: getstatic v.a : Ljavax/microedition/lcdui/Image;
    //   5255: invokevirtual getHeight : ()I
    //   5258: getstatic v.a : Ljavax/microedition/lcdui/Image;
    //   5261: invokestatic b : (IILjavax/microedition/lcdui/Image;)[B
    //   5264: dup
    //   5265: astore #7
    //   5267: ifnull -> 5422
    //   5270: aload #7
    //   5272: arraylength
    //   5273: ifle -> 5422
    //   5276: getstatic v.a : [Lag;
    //   5279: aload_1
    //   5280: getfield c : B
    //   5283: aaload
    //   5284: invokeinterface a : ()Ljava/lang/String;
    //   5289: astore #8
    //   5291: getstatic v.z : Ljava/lang/String;
    //   5294: invokestatic g : (Ljava/lang/String;)Ljava/lang/String;
    //   5297: invokestatic b : ()Ljava/lang/String;
    //   5300: getstatic v.cc : Z
    //   5303: ifeq -> 5311
    //   5306: ldc '.png'
    //   5308: goto -> 5313
    //   5311: ldc '.bmp'
    //   5313: invokestatic a : (Ljava/lang/String;Ljava/lang/String;Ljava/lang/String;)Ljava/lang/String;
    //   5316: astore #9
    //   5318: getstatic v.a : [Lag;
    //   5321: aload_1
    //   5322: getfield c : B
    //   5325: aaload
    //   5326: aload #9
    //   5328: invokeinterface a : (Ljava/lang/String;)V
    //   5333: getstatic v.a : [Lag;
    //   5336: aload_1
    //   5337: getfield c : B
    //   5340: aaload
    //   5341: invokeinterface b : ()Z
    //   5346: ifeq -> 5364
    //   5349: getstatic v.a : [Lag;
    //   5352: aload_1
    //   5353: getfield c : B
    //   5356: aaload
    //   5357: iconst_0
    //   5358: invokeinterface a : (Z)Z
    //   5363: pop
    //   5364: getstatic v.a : [Lag;
    //   5367: aload_1
    //   5368: getfield c : B
    //   5371: aaload
    //   5372: invokeinterface a : ()Z
    //   5377: pop
    //   5378: getstatic v.a : [Lag;
    //   5381: aload_1
    //   5382: getfield c : B
    //   5385: aaload
    //   5386: aload #7
    //   5388: invokeinterface a : ([B)Z
    //   5393: pop
    //   5394: getstatic v.a : [Lag;
    //   5397: aload_1
    //   5398: getfield c : B
    //   5401: aaload
    //   5402: aload #8
    //   5404: invokeinterface a : (Ljava/lang/String;)V
    //   5409: getstatic v.ca : Z
    //   5412: ifeq -> 5422
    //   5415: iconst_0
    //   5416: istore_3
    //   5417: sipush #702
    //   5420: istore #4
    //   5422: iconst_0
    //   5423: putstatic ai.c : Z
    //   5426: aconst_null
    //   5427: putstatic ai.a : Ljava/lang/Thread;
    //   5430: goto -> 5526
    //   5433: astore #5
    //   5435: getstatic ai.d : I
    //   5438: bipush #47
    //   5440: if_icmpeq -> 5449
    //   5443: getstatic ai.a : Ljava/util/Vector;
    //   5446: invokevirtual removeAllElements : ()V
    //   5449: getstatic af.b : Laf;
    //   5452: iconst_0
    //   5453: putfield C : Z
    //   5456: getstatic ai.d : I
    //   5459: bipush #47
    //   5461: if_icmpne -> 5493
    //   5464: getstatic v.cc : Z
    //   5467: ifeq -> 5493
    //   5470: aload #5
    //   5472: instanceof java/lang/OutOfMemoryError
    //   5475: ifeq -> 5493
    //   5478: getstatic af.b : Laf;
    //   5481: sipush #707
    //   5484: invokestatic d : (I)Ljava/lang/String;
    //   5487: invokevirtual c : (Ljava/lang/String;)V
    //   5490: goto -> 5504
    //   5493: getstatic af.b : Laf;
    //   5496: aload #5
    //   5498: invokevirtual toString : ()Ljava/lang/String;
    //   5501: invokevirtual c : (Ljava/lang/String;)V
    //   5504: iconst_0
    //   5505: putstatic ai.c : Z
    //   5508: aconst_null
    //   5509: putstatic ai.a : Ljava/lang/Thread;
    //   5512: goto -> 5526
    //   5515: astore_0
    //   5516: iconst_0
    //   5517: putstatic ai.c : Z
    //   5520: aconst_null
    //   5521: putstatic ai.a : Ljava/lang/Thread;
    //   5524: aload_0
    //   5525: athrow
    //   5526: getstatic v.aP : Z
    //   5529: ifne -> 5535
    //   5532: invokestatic O : ()V
    //   5535: getstatic ai.a : Ljava/util/Vector;
    //   5538: invokevirtual isEmpty : ()Z
    //   5541: ifne -> 5548
    //   5544: iconst_1
    //   5545: goto -> 5549
    //   5548: iconst_0
    //   5549: putstatic ai.a : Z
    //   5552: getstatic af.b : Laf;
    //   5555: iload_2
    //   5556: aload_1
    //   5557: invokevirtual b : (ZLv;)V
    //   5560: iload_3
    //   5561: iconst_m1
    //   5562: if_icmpeq -> 5589
    //   5565: iload #4
    //   5567: iconst_m1
    //   5568: if_icmpeq -> 5589
    //   5571: getstatic af.b : Laf;
    //   5574: sipush #1000
    //   5577: iload_3
    //   5578: invokestatic d : (I)Ljava/lang/String;
    //   5581: iload #4
    //   5583: invokestatic d : (I)Ljava/lang/String;
    //   5586: invokevirtual a : (ILjava/lang/String;Ljava/lang/String;)V
    //   5589: aload_0
    //   5590: getfield j : Z
    //   5593: ifeq -> 5614
    //   5596: aload_0
    //   5597: iconst_0
    //   5598: putfield j : Z
    //   5601: getstatic af.b : Laf;
    //   5604: invokestatic a : (Ljavax/microedition/lcdui/Displayable;)V
    //   5607: aload_1
    //   5608: sipush #26189
    //   5611: invokevirtual d : (I)V
    //   5614: iconst_0
    //   5615: putstatic ai.d : I
    //   5618: return
    // Exception table:
    //   from	to	target	type
    //   54	212	5433	java/lang/Throwable
    //   54	212	5515	finally
    //   221	3282	5433	java/lang/Throwable
    //   221	3282	5515	finally
    //   428	462	465	finally
    //   465	470	465	finally
    //   2280	2419	2441	java/lang/Exception
    //   2280	2419	2505	java/lang/OutOfMemoryError
    //   2280	2419	2592	finally
    //   2441	2483	2592	finally
    //   2505	2570	2592	finally
    //   3291	3306	3309	java/lang/Exception
    //   3291	5422	5433	java/lang/Throwable
    //   3291	5422	5515	finally
    //   3829	3843	3846	java/lang/Exception
    //   3829	3843	3862	java/lang/OutOfMemoryError
    //   4959	4973	4976	java/lang/Exception
    //   4959	4973	4992	java/lang/OutOfMemoryError
    //   5433	5504	5515	finally
  }
  
  private void y() {
    // Byte code:
    //   0: aload_0
    //   1: getfield e : Ljava/lang/String;
    //   4: ifnull -> 114
    //   7: aload_0
    //   8: getfield e : Ljava/lang/String;
    //   11: invokevirtual length : ()I
    //   14: ifle -> 114
    //   17: getstatic ai.a : Z
    //   20: ifne -> 114
    //   23: getstatic v.a : [Lag;
    //   26: getstatic af.b : Laf;
    //   29: getfield a : Lv;
    //   32: getfield c : B
    //   35: aaload
    //   36: invokeinterface a : ()Ljava/lang/String;
    //   41: astore_1
    //   42: getstatic v.a : [Lag;
    //   45: getstatic af.b : Laf;
    //   48: getfield a : Lv;
    //   51: getfield c : B
    //   54: aaload
    //   55: aload_0
    //   56: getfield e : Ljava/lang/String;
    //   59: invokeinterface a : (Ljava/lang/String;)V
    //   64: getstatic v.a : [Lag;
    //   67: getstatic af.b : Laf;
    //   70: getfield a : Lv;
    //   73: getfield c : B
    //   76: aaload
    //   77: iconst_0
    //   78: invokeinterface a : (Z)Z
    //   83: pop
    //   84: aload_1
    //   85: ifnull -> 114
    //   88: aload_1
    //   89: invokevirtual length : ()I
    //   92: ifeq -> 114
    //   95: getstatic v.a : [Lag;
    //   98: getstatic af.b : Laf;
    //   101: getfield a : Lv;
    //   104: getfield c : B
    //   107: aaload
    //   108: aload_1
    //   109: invokeinterface a : (Ljava/lang/String;)V
    //   114: aload_0
    //   115: ldc ''
    //   117: putfield e : Ljava/lang/String;
    //   120: return
  }
  
  public final void a() {
    while (a != null && d)
      Thread.yield(); 
    ((v)((af)af.b).a).aM = 0;
    if (a().length() != 0) {
      b(20);
      return;
    } 
    b("");
    b(21);
  }
  
  public final void a(String paramString, boolean paramBoolean) {
    // Byte code:
    //   0: getstatic ai.a : Ljava/lang/Thread;
    //   3: ifnull -> 12
    //   6: getstatic ai.d : I
    //   9: ifne -> 902
    //   12: aload_1
    //   13: ldc 61472
    //   15: invokestatic c : (I)Ljava/lang/String;
    //   18: invokevirtual equals : (Ljava/lang/Object;)Z
    //   21: ifeq -> 46
    //   24: aload_0
    //   25: dup
    //   26: getfield a : I
    //   29: getstatic v.aN : I
    //   32: iadd
    //   33: putfield a : I
    //   36: getstatic af.b : Laf;
    //   39: sipush #26189
    //   42: invokevirtual b : (I)V
    //   45: return
    //   46: aload_1
    //   47: ldc 61473
    //   49: invokestatic c : (I)Ljava/lang/String;
    //   52: invokevirtual equals : (Ljava/lang/Object;)Z
    //   55: ifeq -> 92
    //   58: aload_0
    //   59: dup
    //   60: getfield a : I
    //   63: getstatic v.aN : I
    //   66: isub
    //   67: putfield a : I
    //   70: aload_0
    //   71: aload_0
    //   72: getfield a : I
    //   75: iconst_0
    //   76: invokestatic a : (II)I
    //   79: putfield a : I
    //   82: getstatic af.b : Laf;
    //   85: sipush #26189
    //   88: invokevirtual b : (I)V
    //   91: return
    //   92: getstatic ai.a : Ljava/util/Vector;
    //   95: ifnull -> 148
    //   98: getstatic ai.a : Ljava/util/Vector;
    //   101: invokevirtual isEmpty : ()Z
    //   104: ifne -> 148
    //   107: getstatic ai.a : Z
    //   110: ifeq -> 148
    //   113: aload_1
    //   114: invokestatic g : (Ljava/lang/String;)Z
    //   117: ifeq -> 148
    //   120: getstatic ai.c : I
    //   123: iconst_4
    //   124: if_icmpeq -> 148
    //   127: getstatic ai.c : I
    //   130: iconst_5
    //   131: if_icmpeq -> 148
    //   134: aload_0
    //   135: aload_1
    //   136: putfield b : Ljava/lang/String;
    //   139: getstatic af.b : Laf;
    //   142: ldc 45085
    //   144: invokevirtual b : (I)V
    //   147: return
    //   148: getstatic ai.c : I
    //   151: iconst_4
    //   152: if_icmpeq -> 165
    //   155: getstatic ai.c : I
    //   158: iconst_5
    //   159: if_icmpeq -> 165
    //   162: invokestatic s : ()V
    //   165: aload_0
    //   166: invokevirtual a : ()Ljava/lang/String;
    //   169: invokevirtual length : ()I
    //   172: ifne -> 191
    //   175: aload_0
    //   176: aload_1
    //   177: invokevirtual b : (Ljava/lang/String;)V
    //   180: iconst_1
    //   181: putstatic v.i : Z
    //   184: aload_0
    //   185: bipush #20
    //   187: invokespecial b : (I)V
    //   190: return
    //   191: aload_1
    //   192: ldc '..'
    //   194: invokevirtual equals : (Ljava/lang/Object;)Z
    //   197: ifeq -> 282
    //   200: aload_0
    //   201: invokevirtual a : ()Ljava/lang/String;
    //   204: bipush #47
    //   206: aload_0
    //   207: invokevirtual a : ()Ljava/lang/String;
    //   210: invokevirtual length : ()I
    //   213: iconst_2
    //   214: isub
    //   215: invokevirtual lastIndexOf : (II)I
    //   218: istore_2
    //   219: getstatic v.d : [Ljava/lang/String;
    //   222: getstatic af.b : Laf;
    //   225: getfield a : Lv;
    //   228: getfield c : B
    //   231: aload_0
    //   232: invokevirtual a : ()Ljava/lang/String;
    //   235: iload_2
    //   236: iconst_1
    //   237: iadd
    //   238: invokevirtual substring : (I)Ljava/lang/String;
    //   241: aastore
    //   242: iload_2
    //   243: iconst_m1
    //   244: if_icmpeq -> 269
    //   247: aload_0
    //   248: aload_0
    //   249: invokevirtual a : ()Ljava/lang/String;
    //   252: iconst_0
    //   253: iload_2
    //   254: iconst_1
    //   255: iadd
    //   256: invokevirtual substring : (II)Ljava/lang/String;
    //   259: invokevirtual b : (Ljava/lang/String;)V
    //   262: aload_0
    //   263: bipush #20
    //   265: invokespecial b : (I)V
    //   268: return
    //   269: aload_0
    //   270: ldc ''
    //   272: invokevirtual b : (Ljava/lang/String;)V
    //   275: aload_0
    //   276: bipush #21
    //   278: invokespecial b : (I)V
    //   281: return
    //   282: aload_1
    //   283: invokestatic e : (Ljava/lang/String;)Z
    //   286: ifne -> 341
    //   289: getstatic ai.a : Ljava/lang/Thread;
    //   292: ifnull -> 301
    //   295: getstatic ai.d : I
    //   298: ifne -> 902
    //   301: getstatic ai.c : I
    //   304: iconst_4
    //   305: if_icmpeq -> 318
    //   308: getstatic ai.c : I
    //   311: iconst_5
    //   312: if_icmpeq -> 318
    //   315: invokestatic s : ()V
    //   318: aload_0
    //   319: aload_0
    //   320: invokevirtual a : ()Ljava/lang/String;
    //   323: aload_1
    //   324: invokestatic a : (Ljava/lang/String;Ljava/lang/String;)Ljava/lang/String;
    //   327: invokevirtual b : (Ljava/lang/String;)V
    //   330: aload_0
    //   331: bipush #20
    //   333: invokespecial b : (I)V
    //   336: iconst_1
    //   337: putstatic v.i : Z
    //   340: return
    //   341: aload_0
    //   342: aload_1
    //   343: putfield b : Ljava/lang/String;
    //   346: getstatic v.d : [Ljava/lang/String;
    //   349: getstatic af.b : Laf;
    //   352: getfield a : Lv;
    //   355: getfield c : B
    //   358: aload_0
    //   359: getfield b : Ljava/lang/String;
    //   362: aastore
    //   363: aload_1
    //   364: invokevirtual toLowerCase : ()Ljava/lang/String;
    //   367: astore_2
    //   368: aload_0
    //   369: getfield b : I
    //   372: iconst_4
    //   373: if_icmpne -> 385
    //   376: aload_2
    //   377: ldc '.htm'
    //   379: invokevirtual endsWith : (Ljava/lang/String;)Z
    //   382: ifne -> 599
    //   385: aload_0
    //   386: getfield b : I
    //   389: bipush #6
    //   391: if_icmpne -> 421
    //   394: aload_2
    //   395: ldc '.oms'
    //   397: invokevirtual endsWith : (Ljava/lang/String;)Z
    //   400: ifne -> 599
    //   403: aload_2
    //   404: ldc '.omc'
    //   406: invokevirtual endsWith : (Ljava/lang/String;)Z
    //   409: ifeq -> 421
    //   412: aload_2
    //   413: ldc 'opr'
    //   415: invokevirtual startsWith : (Ljava/lang/String;)Z
    //   418: ifne -> 599
    //   421: aload_0
    //   422: getfield b : I
    //   425: iconst_5
    //   426: if_icmpne -> 438
    //   429: aload_2
    //   430: ldc '.oms'
    //   432: invokevirtual endsWith : (Ljava/lang/String;)Z
    //   435: ifne -> 599
    //   438: aload_0
    //   439: getfield b : I
    //   442: bipush #11
    //   444: if_icmpeq -> 456
    //   447: aload_0
    //   448: getfield b : I
    //   451: bipush #10
    //   453: if_icmpne -> 465
    //   456: aload_2
    //   457: ldc '.col'
    //   459: invokevirtual endsWith : (Ljava/lang/String;)Z
    //   462: ifne -> 599
    //   465: aload_0
    //   466: getfield b : I
    //   469: bipush #14
    //   471: if_icmpeq -> 483
    //   474: aload_0
    //   475: getfield b : I
    //   478: bipush #13
    //   480: if_icmpne -> 492
    //   483: aload_2
    //   484: ldc '.omt'
    //   486: invokevirtual endsWith : (Ljava/lang/String;)Z
    //   489: ifne -> 599
    //   492: aload_0
    //   493: getfield b : I
    //   496: bipush #9
    //   498: if_icmpeq -> 599
    //   501: aload_0
    //   502: getfield b : I
    //   505: bipush #16
    //   507: if_icmpeq -> 599
    //   510: aload_0
    //   511: getfield b : I
    //   514: bipush #21
    //   516: if_icmpeq -> 528
    //   519: aload_0
    //   520: getfield b : I
    //   523: bipush #22
    //   525: if_icmpne -> 537
    //   528: aload_2
    //   529: ldc '.omw'
    //   531: invokevirtual endsWith : (Ljava/lang/String;)Z
    //   534: ifne -> 599
    //   537: aload_0
    //   538: getfield b : I
    //   541: bipush #23
    //   543: if_icmpeq -> 555
    //   546: aload_0
    //   547: getfield b : I
    //   550: bipush #24
    //   552: if_icmpne -> 564
    //   555: aload_2
    //   556: ldc '.oml'
    //   558: invokevirtual endsWith : (Ljava/lang/String;)Z
    //   561: ifne -> 599
    //   564: aload_0
    //   565: getfield b : I
    //   568: bipush #18
    //   570: if_icmpne -> 582
    //   573: aload_2
    //   574: ldc '.omb'
    //   576: invokevirtual endsWith : (Ljava/lang/String;)Z
    //   579: ifne -> 599
    //   582: aload_0
    //   583: getfield b : I
    //   586: iconst_1
    //   587: if_icmpeq -> 599
    //   590: aload_0
    //   591: getfield b : I
    //   594: bipush #8
    //   596: if_icmpne -> 711
    //   599: aload_0
    //   600: iconst_1
    //   601: invokevirtual a : (Z)V
    //   604: aload_0
    //   605: getfield a : Lr;
    //   608: ifnull -> 902
    //   611: new java/lang/StringBuffer
    //   614: dup
    //   615: invokespecial <init> : ()V
    //   618: astore_1
    //   619: aload_0
    //   620: getfield b : I
    //   623: bipush #9
    //   625: if_icmpne -> 660
    //   628: aload_1
    //   629: aload_0
    //   630: getfield b : Ljava/lang/String;
    //   633: invokevirtual append : (Ljava/lang/String;)Ljava/lang/StringBuffer;
    //   636: pop
    //   637: aload_0
    //   638: getfield b : Ljava/lang/String;
    //   641: invokestatic d : (Ljava/lang/String;)Ljava/lang/String;
    //   644: invokevirtual length : ()I
    //   647: ifne -> 699
    //   650: aload_1
    //   651: ldc '.txt'
    //   653: invokevirtual append : (Ljava/lang/String;)Ljava/lang/StringBuffer;
    //   656: pop
    //   657: goto -> 699
    //   660: aload_0
    //   661: getfield b : Ljava/lang/String;
    //   664: bipush #46
    //   666: invokevirtual lastIndexOf : (I)I
    //   669: istore_2
    //   670: aload_1
    //   671: aload_0
    //   672: getfield b : Ljava/lang/String;
    //   675: iconst_0
    //   676: iload_2
    //   677: iconst_m1
    //   678: if_icmpeq -> 685
    //   681: iload_2
    //   682: goto -> 692
    //   685: aload_0
    //   686: getfield b : Ljava/lang/String;
    //   689: invokevirtual length : ()I
    //   692: invokevirtual substring : (II)Ljava/lang/String;
    //   695: invokevirtual append : (Ljava/lang/String;)Ljava/lang/StringBuffer;
    //   698: pop
    //   699: aload_0
    //   700: getfield a : Lr;
    //   703: aload_1
    //   704: invokevirtual toString : ()Ljava/lang/String;
    //   707: invokevirtual setString : (Ljava/lang/String;)V
    //   710: return
    //   711: aload_0
    //   712: aload_0
    //   713: getfield b : Ljava/lang/String;
    //   716: aload_1
    //   717: astore_2
    //   718: astore_1
    //   719: astore_0
    //   720: aload_2
    //   721: invokevirtual toLowerCase : ()Ljava/lang/String;
    //   724: astore_2
    //   725: aload_1
    //   726: invokevirtual toLowerCase : ()Ljava/lang/String;
    //   729: astore_3
    //   730: aload_2
    //   731: invokestatic h : (Ljava/lang/String;)Z
    //   734: ifeq -> 746
    //   737: aload_0
    //   738: getstatic v.bg : I
    //   741: aconst_null
    //   742: invokevirtual a : (ILjava/lang/String;)V
    //   745: return
    //   746: aload_2
    //   747: ldc '.oms'
    //   749: invokevirtual endsWith : (Ljava/lang/String;)Z
    //   752: ifne -> 773
    //   755: aload_2
    //   756: ldc '.omc'
    //   758: invokevirtual endsWith : (Ljava/lang/String;)Z
    //   761: ifeq -> 780
    //   764: aload_2
    //   765: ldc 'opr'
    //   767: invokevirtual startsWith : (Ljava/lang/String;)Z
    //   770: ifeq -> 780
    //   773: aload_0
    //   774: bipush #23
    //   776: invokespecial b : (I)V
    //   779: return
    //   780: aload_3
    //   781: ldc '.col'
    //   783: invokevirtual endsWith : (Ljava/lang/String;)Z
    //   786: ifeq -> 814
    //   789: getstatic v.d : [Ljava/lang/String;
    //   792: getstatic af.b : Laf;
    //   795: getfield a : Lv;
    //   798: getfield c : B
    //   801: ldc ''
    //   803: aastore
    //   804: invokestatic B : ()V
    //   807: aload_0
    //   808: bipush #30
    //   810: invokespecial b : (I)V
    //   813: return
    //   814: aload_3
    //   815: invokestatic b : (Ljava/lang/String;)Z
    //   818: ifne -> 828
    //   821: aload_3
    //   822: invokestatic c : (Ljava/lang/String;)Z
    //   825: ifeq -> 864
    //   828: getstatic v.d : [Ljava/lang/String;
    //   831: getstatic af.b : Laf;
    //   834: getfield a : Lv;
    //   837: getfield c : B
    //   840: ldc ''
    //   842: aastore
    //   843: aconst_null
    //   844: putstatic x.a : [Ljava/lang/String;
    //   847: aload_0
    //   848: invokevirtual a : ()Ljava/lang/String;
    //   851: aload_1
    //   852: invokestatic a : (Ljava/lang/String;Ljava/lang/String;)Ljava/lang/String;
    //   855: putstatic x.a : Ljava/lang/String;
    //   858: aload_0
    //   859: iconst_0
    //   860: invokevirtual d : (Z)V
    //   863: return
    //   864: aload_3
    //   865: invokestatic d : (Ljava/lang/String;)Z
    //   868: ifeq -> 902
    //   871: getstatic v.d : [Ljava/lang/String;
    //   874: getstatic af.b : Laf;
    //   877: getfield a : Lv;
    //   880: getfield c : B
    //   883: ldc ''
    //   885: aastore
    //   886: aload_0
    //   887: invokevirtual a : ()Ljava/lang/String;
    //   890: aload_1
    //   891: invokestatic a : (Ljava/lang/String;Ljava/lang/String;)Ljava/lang/String;
    //   894: putstatic x.a : Ljava/lang/String;
    //   897: aload_0
    //   898: iconst_0
    //   899: invokevirtual d : (Z)V
    //   902: return
  }
  
  public static String[] a(String paramString) {
    // Byte code:
    //   0: getstatic v.a : [Lag;
    //   3: getstatic af.b : Laf;
    //   6: getfield a : Lv;
    //   9: getfield c : B
    //   12: aaload
    //   13: aload_0
    //   14: aconst_null
    //   15: invokeinterface a : (Ljava/lang/String;Ljava/util/Vector;)Ljava/util/Vector;
    //   20: dup
    //   21: astore_0
    //   22: invokevirtual size : ()I
    //   25: anewarray java/lang/String
    //   28: astore_1
    //   29: aload_0
    //   30: aload_1
    //   31: invokevirtual copyInto : ([Ljava/lang/Object;)V
    //   34: aload_1
    //   35: areturn
  }
  
  private static boolean h(String paramString) {
    if (v.P != null && v.P.length() > 0) {
      String[] arrayOfString = v.a(v.P, 0, ';');
      for (byte b = 0; b < arrayOfString.length; b++) {
        if (paramString.endsWith(arrayOfString[b]))
          return true; 
      } 
    } 
    return paramString.endsWith(".txt");
  }
  
  public final void b() {
    // Byte code:
    //   0: aload_0
    //   1: iconst_0
    //   2: putfield a : I
    //   5: aload_0
    //   6: dup
    //   7: astore_1
    //   8: monitorenter
    //   9: getstatic v.a : [Lag;
    //   12: getstatic af.b : Laf;
    //   15: getfield a : Lv;
    //   18: getfield c : B
    //   21: aaload
    //   22: aload_0
    //   23: invokevirtual a : ()Ljava/lang/String;
    //   26: invokeinterface a : (Ljava/lang/String;)V
    //   31: aload_0
    //   32: aload_0
    //   33: getstatic v.s : I
    //   36: getstatic v.ab : Z
    //   39: istore #4
    //   41: istore_3
    //   42: astore_2
    //   43: getstatic v.a : [Lag;
    //   46: getstatic af.b : Laf;
    //   49: getfield a : Lv;
    //   52: getfield c : B
    //   55: aaload
    //   56: invokeinterface a : ()[Ljava/lang/String;
    //   61: astore #5
    //   63: new java/util/Vector
    //   66: dup
    //   67: aload #5
    //   69: arraylength
    //   70: invokespecial <init> : (I)V
    //   73: astore #6
    //   75: iconst_0
    //   76: istore #7
    //   78: iload #7
    //   80: aload #5
    //   82: arraylength
    //   83: if_icmpge -> 138
    //   86: bipush #6
    //   88: anewarray java/lang/String
    //   91: dup
    //   92: astore #8
    //   94: iconst_0
    //   95: getstatic v.cJ : Z
    //   98: ifeq -> 119
    //   101: getstatic v.bd : I
    //   104: iconst_4
    //   105: if_icmpeq -> 119
    //   108: aload #5
    //   110: iload #7
    //   112: aaload
    //   113: invokestatic b : (Ljava/lang/String;)Ljava/lang/String;
    //   116: goto -> 124
    //   119: aload #5
    //   121: iload #7
    //   123: aaload
    //   124: aastore
    //   125: aload #6
    //   127: aload #8
    //   129: invokevirtual addElement : (Ljava/lang/Object;)V
    //   132: iinc #7, 1
    //   135: goto -> 78
    //   138: iload_3
    //   139: iflt -> 449
    //   142: iload_3
    //   143: bipush #6
    //   145: if_icmpgt -> 449
    //   148: aload #6
    //   150: invokevirtual isEmpty : ()Z
    //   153: ifne -> 449
    //   156: iload_3
    //   157: bipush #6
    //   159: if_icmpeq -> 411
    //   162: aload #6
    //   164: iconst_0
    //   165: invokevirtual elementAt : (I)Ljava/lang/Object;
    //   168: checkcast [Ljava/lang/Object;
    //   171: iload_3
    //   172: aaload
    //   173: checkcast java/lang/String
    //   176: ifnonnull -> 411
    //   179: iconst_0
    //   180: istore #7
    //   182: iload #7
    //   184: aload #6
    //   186: invokevirtual size : ()I
    //   189: if_icmpge -> 411
    //   192: aload #6
    //   194: iload #7
    //   196: invokevirtual elementAt : (I)Ljava/lang/Object;
    //   199: checkcast [Ljava/lang/Object;
    //   202: astore #8
    //   204: aload_2
    //   205: getfield a : Ljava/lang/StringBuffer;
    //   208: iconst_0
    //   209: invokevirtual setLength : (I)V
    //   212: iload_3
    //   213: lookupswitch default -> 405, 1 -> 240, 2 -> 316
    //   240: getstatic v.a : [Lag;
    //   243: getstatic af.b : Laf;
    //   246: getfield a : Lv;
    //   249: getfield c : B
    //   252: aaload
    //   253: aload_2
    //   254: getfield a : Ljava/lang/StringBuffer;
    //   257: aload_2
    //   258: invokevirtual a : ()Ljava/lang/String;
    //   261: invokevirtual append : (Ljava/lang/String;)Ljava/lang/StringBuffer;
    //   264: aload #8
    //   266: iconst_0
    //   267: aaload
    //   268: invokevirtual append : (Ljava/lang/Object;)Ljava/lang/StringBuffer;
    //   271: invokevirtual toString : ()Ljava/lang/String;
    //   274: invokeinterface a : (Ljava/lang/String;)V
    //   279: aload #8
    //   281: iconst_1
    //   282: getstatic v.a : [Lag;
    //   285: getstatic af.b : Laf;
    //   288: getfield a : Lv;
    //   291: getfield c : B
    //   294: aaload
    //   295: invokeinterface b : ()J
    //   300: invokestatic valueOf : (J)Ljava/lang/String;
    //   303: aastore
    //   304: aload #6
    //   306: aload #8
    //   308: iload #7
    //   310: invokevirtual setElementAt : (Ljava/lang/Object;I)V
    //   313: goto -> 405
    //   316: getstatic v.a : [Lag;
    //   319: getstatic af.b : Laf;
    //   322: getfield a : Lv;
    //   325: getfield c : B
    //   328: aaload
    //   329: aload_2
    //   330: getfield a : Ljava/lang/StringBuffer;
    //   333: aload_2
    //   334: invokevirtual a : ()Ljava/lang/String;
    //   337: invokevirtual append : (Ljava/lang/String;)Ljava/lang/StringBuffer;
    //   340: aload #8
    //   342: iconst_0
    //   343: aaload
    //   344: invokevirtual append : (Ljava/lang/Object;)Ljava/lang/StringBuffer;
    //   347: invokevirtual toString : ()Ljava/lang/String;
    //   350: invokeinterface a : (Ljava/lang/String;)V
    //   355: aload #8
    //   357: iconst_2
    //   358: getstatic v.a : [Lag;
    //   361: getstatic af.b : Laf;
    //   364: getfield a : Lv;
    //   367: getfield c : B
    //   370: aaload
    //   371: invokeinterface c : ()J
    //   376: getstatic v.N : I
    //   379: ldc 3600000
    //   381: imul
    //   382: i2l
    //   383: ladd
    //   384: getstatic v.O : I
    //   387: ldc 60000
    //   389: imul
    //   390: i2l
    //   391: ladd
    //   392: invokestatic valueOf : (J)Ljava/lang/String;
    //   395: aastore
    //   396: aload #6
    //   398: aload #8
    //   400: iload #7
    //   402: invokevirtual setElementAt : (Ljava/lang/Object;I)V
    //   405: iinc #7, 1
    //   408: goto -> 182
    //   411: iload_3
    //   412: iconst_1
    //   413: if_icmpeq -> 422
    //   416: iload_3
    //   417: bipush #6
    //   419: if_icmpne -> 435
    //   422: aload #6
    //   424: iconst_0
    //   425: aload #6
    //   427: invokevirtual size : ()I
    //   430: iconst_0
    //   431: iconst_0
    //   432: invokestatic a : (Ljava/util/Vector;IIIZ)V
    //   435: aload #6
    //   437: iconst_0
    //   438: aload #6
    //   440: invokevirtual size : ()I
    //   443: iload_3
    //   444: iload #4
    //   446: invokestatic a : (Ljava/util/Vector;IIIZ)V
    //   449: aload #6
    //   451: invokevirtual size : ()I
    //   454: anewarray java/lang/String
    //   457: astore #7
    //   459: aload #6
    //   461: invokevirtual size : ()I
    //   464: istore #8
    //   466: iload #8
    //   468: iinc #8, -1
    //   471: ifle -> 496
    //   474: aload #6
    //   476: iload #8
    //   478: invokevirtual elementAt : (I)Ljava/lang/Object;
    //   481: checkcast [Ljava/lang/String;
    //   484: astore_2
    //   485: aload #7
    //   487: iload #8
    //   489: aload_2
    //   490: iconst_0
    //   491: aaload
    //   492: aastore
    //   493: goto -> 466
    //   496: aload #7
    //   498: aload_0
    //   499: getfield b : I
    //   502: invokestatic a : ([Ljava/lang/String;I)[Ljava/lang/String;
    //   505: putfield a : [Ljava/lang/String;
    //   508: iconst_0
    //   509: putstatic ai.d : I
    //   512: aload_1
    //   513: monitorexit
    //   514: goto -> 522
    //   517: astore_0
    //   518: aload_1
    //   519: monitorexit
    //   520: aload_0
    //   521: athrow
    //   522: aload_0
    //   523: iconst_1
    //   524: putfield j : Z
    //   527: return
    // Exception table:
    //   from	to	target	type
    //   9	514	517	finally
    //   517	520	517	finally
  }
  
  public static String[] a(String[] paramArrayOfString, int paramInt) {
    String[] arrayOfString;
    (arrayOfString = new String[1])[0] = "..";
    if (paramArrayOfString != null && paramArrayOfString.length > 0) {
      int i = paramArrayOfString.length;
      byte b1 = 0;
      String[] arrayOfString1 = new String[i];
      (arrayOfString = new String[i + 1])[0] = "..";
      byte b2 = 1;
      byte b3;
      for (b3 = 0; b3 < i; b3++) {
        if (!e(paramArrayOfString[b3])) {
          arrayOfString[b2++] = paramArrayOfString[b3];
        } else {
          arrayOfString1[b1++] = paramArrayOfString[b3];
        } 
      } 
      for (b3 = 0; b3 < b1; b3++) {
        String str1 = d(arrayOfString1[b3].toLowerCase());
        String str2 = arrayOfString1[b3];
        switch (paramInt) {
          default:
            arrayOfString[b2++] = str2;
            break;
          case 21:
          case 22:
            if (str1.equals(".omw"))
              arrayOfString[b2++] = str2; 
            break;
          case 17:
          case 18:
            if (str1.equals(".omb"))
              arrayOfString[b2++] = str2; 
            break;
          case 3:
          case 4:
            if (str1.equals(".png") || str1.equals(".htm"))
              arrayOfString[b2++] = str2; 
            break;
          case 5:
          case 6:
            if (str1.equals(".oms") || str1.equals(".omc"))
              arrayOfString[b2++] = str2; 
            break;
          case 10:
          case 11:
            if (str1.equals(".col"))
              arrayOfString[b2++] = str2; 
            break;
          case 13:
          case 14:
            if (str1.equals(".omt"))
              arrayOfString[b2++] = str2; 
            break;
          case 23:
          case 24:
            if (str1.equals(".oml"))
              arrayOfString[b2++] = str2; 
            break;
        } 
      } 
      String[] arrayOfString2 = new String[b2];
      System.arraycopy(arrayOfString, 0, arrayOfString2, 0, b2);
      arrayOfString = arrayOfString2;
    } 
    return arrayOfString;
  }
  
  private void c(String paramString) {
    String str = ((this.b == 5 || this.b == 12 || this.b == 9) && paramString != null) ? paramString : v.b();
    if (this.b == 23)
      str = v.a("Queue_", str); 
    if (str.length() == 0 && ((af)af.b).a != null)
      str = (((af)af.b).a.b(true) != null) ? ((af)af.b).a.b(true) : v.i(paramString); 
    if (!((v)((af)af.b).a).cq)
      str = a(str, false); 
    a(v.d(322), str);
  }
  
  private void a(String paramString1, String paramString2) {
    this.a = (StringBuffer)new r(paramString1, (paramString2.length() > 255) ? paramString2.substring(0, 254) : paramString2, 256, 256, 0, null);
    this.a.addCommand((Command)a);
    this.a.addCommand(b);
    af.b((r)this.a);
    af.b((r)this.a, true);
    this.a.setCommandListener(this);
    v.a((Displayable)this.a);
  }
  
  private String a(InputStream paramInputStream, int paramInt1, int paramInt2) {
    StringBuffer stringBuffer = new StringBuffer(paramInt2);
    byte b = 0;
    this.f = 0;
    if (paramInputStream.skip(paramInt1) != paramInt1)
      return ""; 
    while ((paramInt1 = paramInputStream.read()) > 0 && b++ < paramInt2) {
      this.f++;
      if ((paramInt1 &= 0xFF) != 10 && paramInt1 != 13) {
        int i;
        int j;
        switch (paramInt1 >> 4) {
          case 0:
          case 1:
          case 2:
          case 3:
          case 4:
          case 5:
          case 6:
          case 7:
            stringBuffer.append((char)paramInt1);
            break;
          case 12:
          case 13:
            i = paramInputStream.read();
            this.f++;
            if ((i & 0xC0) == 128)
              stringBuffer.append((char)((paramInt1 & 0x1F) << 6 | i & 0x3F)); 
            break;
          case 14:
            i = paramInputStream.read();
            j = paramInputStream.read();
            this.f += 2;
            if ((i & 0xC0) == 128 && (j & 0xC0) == 128)
              stringBuffer.append((char)((paramInt1 & 0xF) << 12 | (i & 0x3F) << 6 | j & 0x3F)); 
            break;
        } 
        continue;
      } 
      stringBuffer.append((char)paramInt1);
    } 
    return stringBuffer.toString();
  }
  
  private static char[] a(InputStream paramInputStream, int paramInt1, int paramInt2, int paramInt3) {
    char[] arrayOfChar;
    if (paramInputStream.skip(paramInt1) != paramInt1)
      return new char[0]; 
    byte[] arrayOfByte = new byte[paramInt2];
    int i;
    if ((i = paramInputStream.read(arrayOfByte, 0, paramInt2)) == -1)
      i = 0; 
    if (paramInt3 != 3) {
      arrayOfChar = new char[i];
    } else {
      arrayOfChar = new char[i * 3];
    } 
    byte b = 0;
    paramInt1 %= v.bh;
    while (b < i) {
      if (paramInt3 != 3) {
        char c = (char)(arrayOfByte[b] & 0xFF);
        if (paramInt3 == 1)
          c = a(c); 
        arrayOfChar[b] = (c > '\037' || c == '\n' || c == '\r') ? c : ' ';
      } else {
        String str;
        if ((str = Integer.toHexString(arrayOfByte[b] & 0xFF)).length() == 1) {
          arrayOfChar[b * 3] = '0';
          arrayOfChar[b * 3 + 1] = str.charAt(0);
        } else {
          arrayOfChar[b * 3] = str.charAt(0);
          arrayOfChar[b * 3 + 1] = str.charAt(1);
        } 
        if (++paramInt1 == v.bh) {
          arrayOfChar[b * 3 + 2] = '\n';
          paramInt1 = 0;
        } else {
          arrayOfChar[b * 3 + 2] = ' ';
        } 
      } 
      b++;
    } 
    return arrayOfChar;
  }
  
  public static char a(int paramInt) {
    char c;
    paramInt = (byte)paramInt & 0xFF;
    null = Character.MIN_VALUE;
    if (paramInt >= 0 && paramInt < 192)
      null = (char)paramInt; 
    switch ((byte)paramInt) {
      case -95:
        return '';
      case -94:
        return '';
      case -91:
        return '';
      case -88:
        return '';
      case -86:
        return '';
      case -81:
        return '';
      case -78:
        return '';
      case -77:
        return '';
      case -76:
        return '';
      case -72:
        return '';
      case -70:
        return '';
      case -65:
        return '';
    } 
    if (paramInt < 0 || paramInt >= 192)
      c = (char)(0x400 | (paramInt & 0x7F) - 48); 
    return c;
  }
  
  private static byte[] a(char[] paramArrayOfchar) {
    int i;
    byte[] arrayOfByte = new byte[i = paramArrayOfchar.length];
    for (byte b = 0; b < i; b++) {
      switch (c) {
        case '':
        
        case '':
        
        case '':
        
        case '':
        
        case '':
        
        case '':
        
        case '':
        
        case '':
        
        case '':
        
        case '':
        
        case '':
        
        case '':
        
        default:
          break;
      } 
      char c;
      arrayOfByte[b] = ((c = paramArrayOfchar[b]) > '\000' && c < '') ? (byte)c : (byte)(c + 176);
    } 
    return arrayOfByte;
  }
  
  private static byte[] b(char[] paramArrayOfchar) {
    try {
      int i = paramArrayOfchar.length;
      ByteArrayOutputStream byteArrayOutputStream = new ByteArrayOutputStream(i / 3);
      DataOutputStream dataOutputStream = new DataOutputStream(byteArrayOutputStream);
      StringBuffer stringBuffer = new StringBuffer(256);
      int j;
      for (j = 0; j < i; j += b) {
        stringBuffer.setLength(0);
        byte b;
        for (b = 0; stringBuffer.length() < 256 && j + b < i; b++) {
          if ("0123456789abcdefABCDEF".indexOf(paramArrayOfchar[j + b]) != -1)
            stringBuffer.append(String.valueOf(paramArrayOfchar[j + b])); 
        } 
        dataOutputStream.write(v.b(stringBuffer.toString()));
      } 
      return byteArrayOutputStream.toByteArray();
    } catch (Throwable throwable) {
      return new byte[0];
    } 
  }
  
  public static String a(String paramString) {
    try {
      byte[] arrayOfByte = a(paramString.toCharArray());
      return new String(arrayOfByte, 0, arrayOfByte.length);
    } catch (Exception exception) {
      return paramString;
    } 
  }
  
  public static String b(String paramString) {
    try {
      StringBuffer stringBuffer = new StringBuffer(paramString.length());
      for (byte b = 0; b < paramString.length(); b++)
        stringBuffer.append(a(paramString.charAt(b) & 0xFF)); 
      return stringBuffer.toString();
    } catch (Exception exception) {
      return paramString;
    } 
  }
  
  public static String a(String paramString, int paramInt, boolean paramBoolean) {
    if (paramInt != 41) {
      int i = (paramString = a(paramString, (paramInt == 8))).lastIndexOf('.');
      if (paramString.length() > 255)
        if (i > 0 && paramString.length() - i < 5) {
          paramString = v.a(paramString.substring(0, v.b(255, i)), paramString.substring(i));
        } else {
          paramString = paramString.substring(0, 255);
        }  
      if (paramString.length() == 0 || paramString.equals("/") || paramString.equals(".."))
        return null; 
      if (paramInt == 7 || (paramBoolean && v.bd == 4))
        paramString = v.g(paramString); 
    } 
    return paramString;
  }
  
  public final void commandAction(Command paramCommand, Displayable paramDisplayable) {
    // Byte code:
    //   0: aload_2
    //   1: instanceof r
    //   4: ifeq -> 310
    //   7: aload_2
    //   8: checkcast r
    //   11: astore_3
    //   12: aload_1
    //   13: getstatic af.a : [Lf;
    //   16: bipush #25
    //   18: aaload
    //   19: if_acmpne -> 30
    //   22: aload_3
    //   23: iconst_1
    //   24: invokevirtual c : (Z)V
    //   27: goto -> 310
    //   30: aload_1
    //   31: getstatic af.a : [Lf;
    //   34: bipush #26
    //   36: aaload
    //   37: if_acmpne -> 48
    //   40: aload_3
    //   41: iconst_0
    //   42: invokevirtual c : (Z)V
    //   45: goto -> 310
    //   48: aload_1
    //   49: getstatic af.a : [Lf;
    //   52: bipush #18
    //   54: aaload
    //   55: if_acmpne -> 99
    //   58: aload_3
    //   59: invokevirtual e : ()V
    //   62: aload_3
    //   63: invokestatic a : (Lr;)V
    //   66: aload_3
    //   67: getstatic af.b : Laf;
    //   70: getfield a : Lr;
    //   73: if_acmpne -> 87
    //   76: getstatic af.b : Laf;
    //   79: aload_3
    //   80: iconst_1
    //   81: invokevirtual a : (Lr;Z)V
    //   84: goto -> 310
    //   87: aload_3
    //   88: invokestatic b : (Lr;)V
    //   91: aload_3
    //   92: iconst_1
    //   93: invokestatic b : (Lr;Z)V
    //   96: goto -> 310
    //   99: aload_1
    //   100: getstatic af.a : [Lf;
    //   103: bipush #19
    //   105: aaload
    //   106: if_acmpne -> 150
    //   109: aload_3
    //   110: invokevirtual f : ()V
    //   113: aload_3
    //   114: invokestatic a : (Lr;)V
    //   117: aload_3
    //   118: getstatic af.b : Laf;
    //   121: getfield a : Lr;
    //   124: if_acmpne -> 138
    //   127: getstatic af.b : Laf;
    //   130: aload_3
    //   131: iconst_1
    //   132: invokevirtual a : (Lr;Z)V
    //   135: goto -> 310
    //   138: aload_3
    //   139: invokestatic b : (Lr;)V
    //   142: aload_3
    //   143: iconst_1
    //   144: invokestatic b : (Lr;Z)V
    //   147: goto -> 310
    //   150: aload_1
    //   151: getstatic af.a : [Lf;
    //   154: bipush #20
    //   156: aaload
    //   157: if_acmpne -> 204
    //   160: aload_3
    //   161: getstatic v.bK : Z
    //   164: invokevirtual a : (Z)V
    //   167: aload_3
    //   168: invokestatic a : (Lr;)V
    //   171: aload_3
    //   172: getstatic af.b : Laf;
    //   175: getfield a : Lr;
    //   178: if_acmpne -> 192
    //   181: getstatic af.b : Laf;
    //   184: aload_3
    //   185: iconst_1
    //   186: invokevirtual a : (Lr;Z)V
    //   189: goto -> 310
    //   192: aload_3
    //   193: invokestatic b : (Lr;)V
    //   196: aload_3
    //   197: iconst_1
    //   198: invokestatic b : (Lr;Z)V
    //   201: goto -> 310
    //   204: aload_1
    //   205: getstatic af.a : [Lf;
    //   208: bipush #21
    //   210: aaload
    //   211: if_acmpne -> 224
    //   214: aload_3
    //   215: getstatic v.bT : Z
    //   218: invokevirtual b : (Z)V
    //   221: goto -> 310
    //   224: aload_1
    //   225: getstatic af.a : [Lf;
    //   228: bipush #22
    //   230: aaload
    //   231: if_acmpne -> 274
    //   234: invokestatic g : ()V
    //   237: aload_3
    //   238: invokestatic a : (Lr;)V
    //   241: aload_3
    //   242: getstatic af.b : Laf;
    //   245: getfield a : Lr;
    //   248: if_acmpne -> 262
    //   251: getstatic af.b : Laf;
    //   254: aload_3
    //   255: iconst_1
    //   256: invokevirtual a : (Lr;Z)V
    //   259: goto -> 310
    //   262: aload_3
    //   263: invokestatic b : (Lr;)V
    //   266: aload_3
    //   267: iconst_1
    //   268: invokestatic b : (Lr;Z)V
    //   271: goto -> 310
    //   274: aload_1
    //   275: getstatic af.a : [Lf;
    //   278: bipush #23
    //   280: aaload
    //   281: if_acmpne -> 292
    //   284: getstatic af.b : Laf;
    //   287: aload_3
    //   288: invokevirtual c : (Lr;)V
    //   291: return
    //   292: aload_1
    //   293: getstatic af.a : [Lf;
    //   296: bipush #24
    //   298: aaload
    //   299: if_acmpne -> 310
    //   302: getstatic af.b : Laf;
    //   305: aload_3
    //   306: invokevirtual d : (Lr;)V
    //   309: return
    //   310: aload_1
    //   311: getstatic ai.a : Ljavax/microedition/lcdui/Command;
    //   314: if_acmpne -> 1039
    //   317: ldc ''
    //   319: astore_3
    //   320: aload_0
    //   321: getfield a : Lr;
    //   324: ifnull -> 350
    //   327: aload_0
    //   328: getfield a : Lr;
    //   331: invokevirtual getString : ()Ljava/lang/String;
    //   334: getstatic ai.c : I
    //   337: aload_0
    //   338: getfield d : Z
    //   341: invokestatic a : (Ljava/lang/String;IZ)Ljava/lang/String;
    //   344: dup
    //   345: astore_3
    //   346: ifnonnull -> 350
    //   349: return
    //   350: getstatic ai.c : I
    //   353: tableswitch default -> 1030, 4 -> 995, 5 -> 995, 6 -> 1030, 7 -> 536, 8 -> 580, 9 -> 1030, 10 -> 558, 11 -> 1030, 12 -> 1030, 13 -> 1030, 14 -> 1030, 15 -> 1030, 16 -> 1030, 17 -> 1030, 18 -> 1030, 19 -> 1030, 20 -> 1030, 21 -> 1030, 22 -> 598, 23 -> 1030, 24 -> 1030, 25 -> 1030, 26 -> 617, 27 -> 1030, 28 -> 1030, 29 -> 1030, 30 -> 1030, 31 -> 661, 32 -> 680, 33 -> 803, 34 -> 1030, 35 -> 1030, 36 -> 1030, 37 -> 1030, 38 -> 822, 39 -> 1030, 40 -> 1030, 41 -> 841, 42 -> 1030, 43 -> 1030, 44 -> 1030, 45 -> 976
    //   536: iconst_0
    //   537: putstatic ai.c : I
    //   540: aload_0
    //   541: aload_3
    //   542: putfield g : Ljava/lang/String;
    //   545: getstatic af.b : Laf;
    //   548: invokestatic a : (Ljavax/microedition/lcdui/Displayable;)V
    //   551: aload_0
    //   552: bipush #7
    //   554: invokespecial b : (I)V
    //   557: return
    //   558: iconst_0
    //   559: putstatic ai.c : I
    //   562: aload_0
    //   563: aload_3
    //   564: putfield g : Ljava/lang/String;
    //   567: getstatic af.b : Laf;
    //   570: invokestatic a : (Ljavax/microedition/lcdui/Displayable;)V
    //   573: aload_0
    //   574: bipush #10
    //   576: invokespecial b : (I)V
    //   579: return
    //   580: aload_0
    //   581: aload_3
    //   582: putfield h : Ljava/lang/String;
    //   585: getstatic af.b : Laf;
    //   588: invokestatic a : (Ljavax/microedition/lcdui/Displayable;)V
    //   591: aload_0
    //   592: bipush #8
    //   594: invokespecial b : (I)V
    //   597: return
    //   598: aload_0
    //   599: aload_3
    //   600: iconst_0
    //   601: invokestatic a : (Ljava/lang/String;Z)Ljava/lang/String;
    //   604: ldc '.oms'
    //   606: invokestatic a : (Ljava/lang/String;Ljava/lang/String;)Ljava/lang/String;
    //   609: putfield d : Ljava/lang/String;
    //   612: aload_0
    //   613: invokespecial z : ()V
    //   616: return
    //   617: getstatic ai.a : [B
    //   620: ifnull -> 660
    //   623: getstatic ai.e : I
    //   626: iconst_m1
    //   627: if_icmpeq -> 660
    //   630: aload_0
    //   631: aload_3
    //   632: putfield d : Ljava/lang/String;
    //   635: getstatic af.b : Laf;
    //   638: getfield a : Lv;
    //   641: getfield cq : Z
    //   644: ifne -> 656
    //   647: aload_0
    //   648: aload_3
    //   649: iconst_0
    //   650: invokestatic a : (Ljava/lang/String;Z)Ljava/lang/String;
    //   653: putfield d : Ljava/lang/String;
    //   656: aload_0
    //   657: invokespecial z : ()V
    //   660: return
    //   661: aload_0
    //   662: aload_3
    //   663: iconst_0
    //   664: invokestatic a : (Ljava/lang/String;Z)Ljava/lang/String;
    //   667: ldc '.col'
    //   669: invokestatic a : (Ljava/lang/String;Ljava/lang/String;)Ljava/lang/String;
    //   672: putfield d : Ljava/lang/String;
    //   675: aload_0
    //   676: invokespecial z : ()V
    //   679: return
    //   680: getstatic af.b : Laf;
    //   683: getfield a : La;
    //   686: ifnull -> 1030
    //   689: getstatic af.b : Laf;
    //   692: getfield a : La;
    //   695: getstatic v.aO : I
    //   698: invokevirtual a : (I)[B
    //   701: dup
    //   702: putstatic ai.a : [B
    //   705: ifnull -> 1030
    //   708: getstatic ai.a : [B
    //   711: arraylength
    //   712: ifle -> 1030
    //   715: ldc ''
    //   717: astore_2
    //   718: getstatic ai.a : [B
    //   721: iconst_1
    //   722: baload
    //   723: bipush #80
    //   725: if_icmpne -> 751
    //   728: getstatic ai.a : [B
    //   731: iconst_2
    //   732: baload
    //   733: bipush #78
    //   735: if_icmpne -> 751
    //   738: getstatic ai.a : [B
    //   741: iconst_3
    //   742: baload
    //   743: bipush #71
    //   745: if_icmpne -> 751
    //   748: ldc '.png'
    //   750: astore_2
    //   751: getstatic ai.a : [B
    //   754: iconst_0
    //   755: baload
    //   756: iconst_m1
    //   757: if_icmpne -> 773
    //   760: getstatic ai.a : [B
    //   763: iconst_1
    //   764: baload
    //   765: bipush #-40
    //   767: if_icmpne -> 773
    //   770: ldc '.jpg'
    //   772: astore_2
    //   773: aload_2
    //   774: invokevirtual length : ()I
    //   777: ifeq -> 802
    //   780: aload_0
    //   781: aload_3
    //   782: iconst_0
    //   783: invokestatic a : (Ljava/lang/String;Z)Ljava/lang/String;
    //   786: aload_2
    //   787: invokestatic a : (Ljava/lang/String;Ljava/lang/String;)Ljava/lang/String;
    //   790: putfield d : Ljava/lang/String;
    //   793: bipush #32
    //   795: putstatic ai.c : I
    //   798: aload_0
    //   799: invokespecial z : ()V
    //   802: return
    //   803: aload_0
    //   804: aload_3
    //   805: iconst_0
    //   806: invokestatic a : (Ljava/lang/String;Z)Ljava/lang/String;
    //   809: ldc '.omt'
    //   811: invokestatic a : (Ljava/lang/String;Ljava/lang/String;)Ljava/lang/String;
    //   814: putfield d : Ljava/lang/String;
    //   817: aload_0
    //   818: invokespecial z : ()V
    //   821: return
    //   822: aload_0
    //   823: aload_3
    //   824: iconst_0
    //   825: invokestatic a : (Ljava/lang/String;Z)Ljava/lang/String;
    //   828: ldc '.omw'
    //   830: invokestatic a : (Ljava/lang/String;Ljava/lang/String;)Ljava/lang/String;
    //   833: putfield d : Ljava/lang/String;
    //   836: aload_0
    //   837: invokespecial z : ()V
    //   840: return
    //   841: aload_0
    //   842: aload_3
    //   843: astore_2
    //   844: astore_1
    //   845: aload_2
    //   846: ifnull -> 964
    //   849: aload_2
    //   850: invokevirtual length : ()I
    //   853: ifle -> 964
    //   856: aload_1
    //   857: getfield a : [Ljava/lang/String;
    //   860: ifnull -> 964
    //   863: aload_1
    //   864: getfield a : [Ljava/lang/String;
    //   867: arraylength
    //   868: ifle -> 964
    //   871: aload_2
    //   872: putstatic ai.i : Ljava/lang/String;
    //   875: invokestatic s : ()V
    //   878: getstatic v.cK : Z
    //   881: ifne -> 889
    //   884: aload_2
    //   885: invokestatic f : (Ljava/lang/String;)Ljava/lang/String;
    //   888: astore_2
    //   889: iconst_0
    //   890: istore_3
    //   891: iload_3
    //   892: aload_1
    //   893: getfield a : [Ljava/lang/String;
    //   896: arraylength
    //   897: if_icmpge -> 964
    //   900: getstatic v.cK : Z
    //   903: ifne -> 920
    //   906: aload_1
    //   907: getfield a : [Ljava/lang/String;
    //   910: iload_3
    //   911: aaload
    //   912: invokestatic f : (Ljava/lang/String;)Ljava/lang/String;
    //   915: astore #4
    //   917: goto -> 928
    //   920: aload_1
    //   921: getfield a : [Ljava/lang/String;
    //   924: iload_3
    //   925: aaload
    //   926: astore #4
    //   928: aload #4
    //   930: invokestatic g : (Ljava/lang/String;)Z
    //   933: ifeq -> 958
    //   936: aload #4
    //   938: aload_2
    //   939: iconst_0
    //   940: iconst_0
    //   941: invokestatic a : (Ljava/lang/String;Ljava/lang/String;II)Z
    //   944: ifeq -> 958
    //   947: aload_1
    //   948: aload_1
    //   949: getfield a : [Ljava/lang/String;
    //   952: iload_3
    //   953: aaload
    //   954: iconst_0
    //   955: invokevirtual b : (Ljava/lang/String;Z)V
    //   958: iinc #3, 1
    //   961: goto -> 891
    //   964: getstatic af.b : Laf;
    //   967: sipush #26189
    //   970: invokevirtual b : (I)V
    //   973: goto -> 1030
    //   976: aload_0
    //   977: aload_3
    //   978: iconst_0
    //   979: invokestatic a : (Ljava/lang/String;Z)Ljava/lang/String;
    //   982: ldc '.oml'
    //   984: invokestatic a : (Ljava/lang/String;Ljava/lang/String;)Ljava/lang/String;
    //   987: putfield d : Ljava/lang/String;
    //   990: aload_0
    //   991: invokespecial z : ()V
    //   994: return
    //   995: aload_0
    //   996: aload_3
    //   997: iconst_0
    //   998: invokestatic a : (Ljava/lang/String;Z)Ljava/lang/String;
    //   1001: putfield d : Ljava/lang/String;
    //   1004: aload_0
    //   1005: getfield d : Ljava/lang/String;
    //   1008: getstatic ai.c : Ljava/lang/String;
    //   1011: invokevirtual equals : (Ljava/lang/Object;)Z
    //   1014: ifeq -> 1021
    //   1017: iconst_0
    //   1018: goto -> 1022
    //   1021: iconst_1
    //   1022: putstatic ai.k : Z
    //   1025: aload_0
    //   1026: invokespecial z : ()V
    //   1029: return
    //   1030: iconst_0
    //   1031: putstatic ai.c : I
    //   1034: aload_0
    //   1035: invokevirtual a : ()V
    //   1038: return
    //   1039: aload_1
    //   1040: getstatic ai.b : Ljavax/microedition/lcdui/Command;
    //   1043: if_acmpeq -> 1053
    //   1046: aload_1
    //   1047: getstatic ai.d : Ljavax/microedition/lcdui/Command;
    //   1050: if_acmpne -> 1101
    //   1053: aload_0
    //   1054: ldc ''
    //   1056: putfield f : Ljava/lang/String;
    //   1059: aload_0
    //   1060: ldc ''
    //   1062: putfield e : Ljava/lang/String;
    //   1065: ldc ''
    //   1067: putstatic ai.c : Ljava/lang/String;
    //   1070: aload_0
    //   1071: ldc ''
    //   1073: putfield d : Ljava/lang/String;
    //   1076: iconst_0
    //   1077: putstatic ai.k : Z
    //   1080: iconst_0
    //   1081: putstatic ai.c : I
    //   1084: getstatic af.b : Laf;
    //   1087: getfield a : Lv;
    //   1090: iconst_0
    //   1091: putfield aM : I
    //   1094: getstatic af.b : Laf;
    //   1097: invokestatic a : (Ljavax/microedition/lcdui/Displayable;)V
    //   1100: return
    //   1101: aload_1
    //   1102: getstatic ai.c : Ljavax/microedition/lcdui/Command;
    //   1105: if_acmpne -> 1178
    //   1108: getstatic af.b : Laf;
    //   1111: invokestatic a : (Ljavax/microedition/lcdui/Displayable;)V
    //   1114: aload_0
    //   1115: getfield f : Ljava/lang/String;
    //   1118: invokevirtual length : ()I
    //   1121: ifeq -> 1166
    //   1124: getstatic ai.c : I
    //   1127: iconst_4
    //   1128: if_icmpeq -> 1166
    //   1131: getstatic ai.c : I
    //   1134: iconst_5
    //   1135: if_icmpeq -> 1166
    //   1138: getstatic v.a : [Lag;
    //   1141: getstatic af.b : Laf;
    //   1144: getfield a : Lv;
    //   1147: getfield c : B
    //   1150: aaload
    //   1151: aload_0
    //   1152: getfield f : Ljava/lang/String;
    //   1155: invokeinterface a : (Ljava/lang/String;)V
    //   1160: aload_0
    //   1161: ldc ''
    //   1163: putfield f : Ljava/lang/String;
    //   1166: aload_0
    //   1167: getstatic ai.c : I
    //   1170: invokespecial b : (I)V
    //   1173: iconst_0
    //   1174: putstatic ai.c : I
    //   1177: return
    //   1178: aload_1
    //   1179: getstatic af.a : [Lf;
    //   1182: bipush #11
    //   1184: aaload
    //   1185: if_acmpne -> 1212
    //   1188: aload_2
    //   1189: getstatic af.b : Laf;
    //   1192: getfield a : Lr;
    //   1195: if_acmpne -> 1212
    //   1198: getstatic af.b : Laf;
    //   1201: getfield a : Lr;
    //   1204: invokevirtual f : ()V
    //   1207: aload_0
    //   1208: invokevirtual u : ()V
    //   1211: return
    //   1212: aload_1
    //   1213: getstatic af.a : [Lf;
    //   1216: bipush #10
    //   1218: aaload
    //   1219: if_acmpne -> 1317
    //   1222: aload_2
    //   1223: getstatic af.b : Laf;
    //   1226: getfield a : Lr;
    //   1229: if_acmpne -> 1317
    //   1232: aload_0
    //   1233: getfield l : Z
    //   1236: ifeq -> 1317
    //   1239: aload_0
    //   1240: getfield h : I
    //   1243: iconst_m1
    //   1244: if_icmpeq -> 1280
    //   1247: aload_0
    //   1248: getfield h : I
    //   1251: getstatic v.i : Ljava/util/Vector;
    //   1254: invokevirtual size : ()I
    //   1257: if_icmpge -> 1280
    //   1260: getstatic v.i : Ljava/util/Vector;
    //   1263: aload_2
    //   1264: checkcast r
    //   1267: invokevirtual a : ()Ljava/lang/String;
    //   1270: aload_0
    //   1271: getfield h : I
    //   1274: invokevirtual setElementAt : (Ljava/lang/Object;I)V
    //   1277: goto -> 1293
    //   1280: getstatic v.i : Ljava/util/Vector;
    //   1283: aload_2
    //   1284: checkcast r
    //   1287: invokevirtual a : ()Ljava/lang/String;
    //   1290: invokevirtual addElement : (Ljava/lang/Object;)V
    //   1293: aload_0
    //   1294: iconst_0
    //   1295: putfield l : Z
    //   1298: aload_0
    //   1299: iconst_m1
    //   1300: putfield h : I
    //   1303: aload_0
    //   1304: invokevirtual u : ()V
    //   1307: iconst_1
    //   1308: putstatic v.i : Z
    //   1311: aconst_null
    //   1312: invokestatic d : (Ljava/io/DataOutputStream;)Ljava/io/DataOutputStream;
    //   1315: pop
    //   1316: return
    //   1317: aload_2
    //   1318: instanceof javax/microedition/lcdui/List
    //   1321: ifeq -> 1519
    //   1324: aload_2
    //   1325: checkcast javax/microedition/lcdui/List
    //   1328: invokevirtual getSelectedIndex : ()I
    //   1331: istore_2
    //   1332: aload_1
    //   1333: getstatic javax/microedition/lcdui/List.SELECT_COMMAND : Ljavax/microedition/lcdui/Command;
    //   1336: if_acmpne -> 1375
    //   1339: getstatic ai.c : I
    //   1342: iconst_4
    //   1343: if_icmpeq -> 1356
    //   1346: getstatic ai.c : I
    //   1349: iconst_5
    //   1350: if_icmpeq -> 1356
    //   1353: invokestatic s : ()V
    //   1356: aload_0
    //   1357: getstatic v.i : Ljava/util/Vector;
    //   1360: iload_2
    //   1361: invokevirtual elementAt : (I)Ljava/lang/Object;
    //   1364: checkcast java/lang/String
    //   1367: invokevirtual b : (Ljava/lang/String;)V
    //   1370: aload_0
    //   1371: invokevirtual a : ()V
    //   1374: return
    //   1375: aload_1
    //   1376: getstatic af.a : [Lf;
    //   1379: bipush #33
    //   1381: aaload
    //   1382: if_acmpne -> 1405
    //   1385: aload_0
    //   1386: iconst_1
    //   1387: putfield l : Z
    //   1390: aload_0
    //   1391: iconst_m1
    //   1392: putfield h : I
    //   1395: getstatic af.b : Laf;
    //   1398: ldc ''
    //   1400: aload_0
    //   1401: invokevirtual a : (Ljava/lang/String;Ljavax/microedition/lcdui/CommandListener;)V
    //   1404: return
    //   1405: aload_1
    //   1406: getstatic af.a : [Lf;
    //   1409: bipush #34
    //   1411: aaload
    //   1412: if_acmpne -> 1458
    //   1415: iload_2
    //   1416: iconst_m1
    //   1417: if_icmpeq -> 1519
    //   1420: iload_2
    //   1421: getstatic v.i : Ljava/util/Vector;
    //   1424: invokevirtual size : ()I
    //   1427: if_icmpge -> 1519
    //   1430: aload_0
    //   1431: iconst_1
    //   1432: putfield l : Z
    //   1435: aload_0
    //   1436: iload_2
    //   1437: putfield h : I
    //   1440: getstatic af.b : Laf;
    //   1443: getstatic v.i : Ljava/util/Vector;
    //   1446: iload_2
    //   1447: invokevirtual elementAt : (I)Ljava/lang/Object;
    //   1450: checkcast java/lang/String
    //   1453: aload_0
    //   1454: invokevirtual a : (Ljava/lang/String;Ljavax/microedition/lcdui/CommandListener;)V
    //   1457: return
    //   1458: aload_1
    //   1459: getstatic af.a : [Lf;
    //   1462: bipush #35
    //   1464: aaload
    //   1465: if_acmpne -> 1503
    //   1468: iload_2
    //   1469: iflt -> 1519
    //   1472: iload_2
    //   1473: getstatic v.i : Ljava/util/Vector;
    //   1476: invokevirtual size : ()I
    //   1479: if_icmpge -> 1519
    //   1482: getstatic v.i : Ljava/util/Vector;
    //   1485: iload_2
    //   1486: invokevirtual removeElementAt : (I)V
    //   1489: aload_0
    //   1490: invokevirtual u : ()V
    //   1493: iconst_1
    //   1494: putstatic v.i : Z
    //   1497: aconst_null
    //   1498: invokestatic d : (Ljava/io/DataOutputStream;)Ljava/io/DataOutputStream;
    //   1501: pop
    //   1502: return
    //   1503: aload_1
    //   1504: getstatic af.a : [Lf;
    //   1507: bipush #32
    //   1509: aaload
    //   1510: if_acmpne -> 1519
    //   1513: getstatic af.b : Laf;
    //   1516: invokestatic a : (Ljavax/microedition/lcdui/Displayable;)V
    //   1519: return
  }
  
  private void z() {
    // Byte code:
    //   0: aload_0
    //   1: aload_0
    //   2: invokevirtual a : ()Ljava/lang/String;
    //   5: aload_0
    //   6: getfield d : Ljava/lang/String;
    //   9: invokestatic a : (Ljava/lang/String;Ljava/lang/String;)Ljava/lang/String;
    //   12: putfield f : Ljava/lang/String;
    //   15: getstatic v.a : [Lag;
    //   18: getstatic af.b : Laf;
    //   21: getfield a : Lv;
    //   24: getfield c : B
    //   27: aaload
    //   28: aload_0
    //   29: getfield f : Ljava/lang/String;
    //   32: invokeinterface a : (Ljava/lang/String;)V
    //   37: aload_0
    //   38: iconst_1
    //   39: putfield h : Z
    //   42: aload_0
    //   43: invokestatic a : (Ljava/lang/Runnable;)Ljava/lang/Thread;
    //   46: pop
    //   47: return
  }
  
  public final void c() {
    v.C();
    if (v.c(v.z)) {
      af.b.c(v.d(704));
      return;
    } 
    af.b.w();
    b(47);
  }
  
  public static void d() {
    // Byte code:
    //   0: invokestatic w : ()V
    //   3: getstatic v.a : Lk;
    //   6: iconst_2
    //   7: putfield a : I
    //   10: getstatic v.a : Lk;
    //   13: bipush #27
    //   15: invokevirtual a : (I)V
    //   18: return
  }
  
  public final void e() {
    // Byte code:
    //   0: aload_0
    //   1: getfield b : I
    //   4: bipush #9
    //   6: if_icmpne -> 15
    //   9: aload_0
    //   10: iconst_1
    //   11: invokespecial c : (I)V
    //   14: return
    //   15: invokestatic w : ()V
    //   18: getstatic v.a : Lk;
    //   21: iconst_0
    //   22: putfield a : I
    //   25: getstatic v.a : Lk;
    //   28: bipush #27
    //   30: invokevirtual a : (I)V
    //   33: return
  }
  
  public final void a(boolean paramBoolean) {
    // Byte code:
    //   0: getstatic v.d : [Ljava/lang/String;
    //   3: getstatic af.b : Laf;
    //   6: getfield a : Lv;
    //   9: getfield c : B
    //   12: aload_0
    //   13: getfield b : Ljava/lang/String;
    //   16: aastore
    //   17: aload_0
    //   18: getfield b : Ljava/lang/String;
    //   21: invokestatic f : (Ljava/lang/String;)Ljava/lang/String;
    //   24: astore_2
    //   25: aload_0
    //   26: getfield b : I
    //   29: bipush #25
    //   31: if_icmpne -> 64
    //   34: aload_0
    //   35: invokevirtual a : ()Ljava/lang/String;
    //   38: aload_0
    //   39: getfield b : Ljava/lang/String;
    //   42: invokestatic e : (Ljava/lang/String;)Z
    //   45: ifeq -> 55
    //   48: aload_0
    //   49: getfield b : Ljava/lang/String;
    //   52: goto -> 57
    //   55: ldc ''
    //   57: invokestatic a : (Ljava/lang/String;Ljava/lang/String;)Ljava/lang/String;
    //   60: invokestatic b : (Ljava/lang/String;)V
    //   63: return
    //   64: aload_0
    //   65: getfield b : I
    //   68: bipush #26
    //   70: if_icmpne -> 105
    //   73: aload_0
    //   74: invokevirtual a : ()Ljava/lang/String;
    //   77: aload_0
    //   78: getfield b : Ljava/lang/String;
    //   81: bipush #47
    //   83: invokestatic a : (Ljava/lang/String;C)Z
    //   86: ifeq -> 96
    //   89: aload_0
    //   90: getfield b : Ljava/lang/String;
    //   93: goto -> 98
    //   96: ldc ''
    //   98: invokestatic a : (Ljava/lang/String;Ljava/lang/String;)Ljava/lang/String;
    //   101: invokestatic c : (Ljava/lang/String;)V
    //   104: return
    //   105: aload_0
    //   106: getfield b : I
    //   109: iconst_1
    //   110: if_icmpne -> 149
    //   113: aload_0
    //   114: invokevirtual a : ()Ljava/lang/String;
    //   117: iload_1
    //   118: ifeq -> 143
    //   121: aload_0
    //   122: getfield b : Ljava/lang/String;
    //   125: invokestatic e : (Ljava/lang/String;)Z
    //   128: ifeq -> 138
    //   131: aload_0
    //   132: getfield b : Ljava/lang/String;
    //   135: goto -> 145
    //   138: ldc ''
    //   140: goto -> 145
    //   143: ldc ''
    //   145: invokestatic a : (Ljava/lang/String;Ljava/lang/String;)V
    //   148: return
    //   149: aload_0
    //   150: getfield b : I
    //   153: bipush #8
    //   155: if_icmpne -> 188
    //   158: aload_0
    //   159: invokevirtual a : ()Ljava/lang/String;
    //   162: aload_0
    //   163: getfield b : Ljava/lang/String;
    //   166: invokestatic e : (Ljava/lang/String;)Z
    //   169: ifeq -> 179
    //   172: aload_0
    //   173: getfield b : Ljava/lang/String;
    //   176: goto -> 181
    //   179: ldc ''
    //   181: invokestatic a : (Ljava/lang/String;Ljava/lang/String;)Ljava/lang/String;
    //   184: invokestatic a : (Ljava/lang/String;)V
    //   187: return
    //   188: aload_0
    //   189: getfield b : I
    //   192: bipush #28
    //   194: if_icmpne -> 229
    //   197: aload_0
    //   198: invokevirtual a : ()Ljava/lang/String;
    //   201: aload_0
    //   202: getfield b : Ljava/lang/String;
    //   205: bipush #47
    //   207: invokestatic a : (Ljava/lang/String;C)Z
    //   210: ifeq -> 220
    //   213: aload_0
    //   214: getfield b : Ljava/lang/String;
    //   217: goto -> 222
    //   220: ldc ''
    //   222: invokestatic a : (Ljava/lang/String;Ljava/lang/String;)Ljava/lang/String;
    //   225: invokestatic d : (Ljava/lang/String;)V
    //   228: return
    //   229: aload_0
    //   230: getfield b : I
    //   233: bipush #20
    //   235: if_icmpne -> 254
    //   238: aload_0
    //   239: invokevirtual a : ()Ljava/lang/String;
    //   242: putstatic a.h : Ljava/lang/String;
    //   245: getstatic af.b : Laf;
    //   248: ldc 61450
    //   250: invokevirtual b : (I)V
    //   253: return
    //   254: aload_0
    //   255: getfield b : I
    //   258: bipush #15
    //   260: if_icmpne -> 280
    //   263: aload_0
    //   264: invokevirtual a : ()Ljava/lang/String;
    //   267: putstatic v.S : Ljava/lang/String;
    //   270: getstatic af.b : Laf;
    //   273: sipush #29518
    //   276: invokevirtual b : (I)V
    //   279: return
    //   280: aload_0
    //   281: getfield b : I
    //   284: iconst_3
    //   285: if_icmpne -> 307
    //   288: invokestatic w : ()V
    //   291: getstatic v.a : Lk;
    //   294: iconst_1
    //   295: putfield a : I
    //   298: getstatic v.a : Lk;
    //   301: bipush #27
    //   303: invokevirtual a : (I)V
    //   306: return
    //   307: aload_0
    //   308: getfield b : I
    //   311: iconst_4
    //   312: if_icmpne -> 327
    //   315: invokestatic w : ()V
    //   318: getstatic v.a : Lk;
    //   321: bipush #28
    //   323: invokevirtual a : (I)V
    //   326: return
    //   327: aload_0
    //   328: getfield b : I
    //   331: iconst_5
    //   332: if_icmpne -> 354
    //   335: bipush #22
    //   337: putstatic ai.c : I
    //   340: aload_0
    //   341: getstatic af.b : Laf;
    //   344: getfield a : La;
    //   347: getfield d : Ljava/lang/String;
    //   350: invokespecial c : (Ljava/lang/String;)V
    //   353: return
    //   354: aload_0
    //   355: getfield b : I
    //   358: bipush #6
    //   360: if_icmpne -> 397
    //   363: aload_2
    //   364: ldc '.oms'
    //   366: invokevirtual endsWith : (Ljava/lang/String;)Z
    //   369: ifne -> 390
    //   372: aload_2
    //   373: ldc '.omc'
    //   375: invokevirtual endsWith : (Ljava/lang/String;)Z
    //   378: ifeq -> 1000
    //   381: aload_2
    //   382: ldc 'opr'
    //   384: invokevirtual startsWith : (Ljava/lang/String;)Z
    //   387: ifeq -> 1000
    //   390: aload_0
    //   391: bipush #23
    //   393: invokespecial b : (I)V
    //   396: return
    //   397: aload_0
    //   398: getfield b : I
    //   401: bipush #9
    //   403: if_icmpne -> 412
    //   406: aload_0
    //   407: iconst_2
    //   408: invokespecial c : (I)V
    //   411: return
    //   412: aload_0
    //   413: getfield b : I
    //   416: bipush #11
    //   418: if_icmpne -> 432
    //   421: bipush #31
    //   423: putstatic ai.c : I
    //   426: aload_0
    //   427: aconst_null
    //   428: invokespecial c : (Ljava/lang/String;)V
    //   431: return
    //   432: aload_0
    //   433: getfield b : I
    //   436: bipush #10
    //   438: if_icmpne -> 457
    //   441: aload_2
    //   442: ldc '.col'
    //   444: invokevirtual endsWith : (Ljava/lang/String;)Z
    //   447: ifeq -> 1000
    //   450: aload_0
    //   451: bipush #30
    //   453: invokespecial b : (I)V
    //   456: return
    //   457: aload_0
    //   458: getfield b : I
    //   461: bipush #12
    //   463: if_icmpne -> 497
    //   466: bipush #32
    //   468: putstatic ai.c : I
    //   471: aload_0
    //   472: getstatic af.b : Laf;
    //   475: getfield a : La;
    //   478: iconst_1
    //   479: invokevirtual b : (Z)Ljava/lang/String;
    //   482: getstatic v.aO : I
    //   485: iconst_1
    //   486: iadd
    //   487: invokestatic valueOf : (I)Ljava/lang/String;
    //   490: invokestatic a : (Ljava/lang/String;Ljava/lang/String;)Ljava/lang/String;
    //   493: invokespecial c : (Ljava/lang/String;)V
    //   496: return
    //   497: aload_0
    //   498: getfield b : I
    //   501: bipush #13
    //   503: if_icmpne -> 517
    //   506: bipush #33
    //   508: putstatic ai.c : I
    //   511: aload_0
    //   512: aconst_null
    //   513: invokespecial c : (Ljava/lang/String;)V
    //   516: return
    //   517: aload_0
    //   518: getfield b : I
    //   521: bipush #14
    //   523: if_icmpne -> 542
    //   526: aload_2
    //   527: ldc '.omt'
    //   529: invokevirtual endsWith : (Ljava/lang/String;)Z
    //   532: ifeq -> 1000
    //   535: aload_0
    //   536: bipush #34
    //   538: invokespecial b : (I)V
    //   541: return
    //   542: aload_0
    //   543: getfield b : I
    //   546: bipush #16
    //   548: if_icmpne -> 870
    //   551: getstatic af.b : Laf;
    //   554: getfield a : Lv;
    //   557: getfield b : Lah;
    //   560: ifnull -> 859
    //   563: getstatic af.b : Laf;
    //   566: getfield a : Lv;
    //   569: getfield b : Lah;
    //   572: aload_0
    //   573: getfield b : Ljava/lang/String;
    //   576: putfield b : Ljava/lang/String;
    //   579: getstatic v.a : [Lag;
    //   582: getstatic af.b : Laf;
    //   585: getfield a : Lv;
    //   588: getfield c : B
    //   591: aaload
    //   592: aload_0
    //   593: invokevirtual a : ()Ljava/lang/String;
    //   596: aload_0
    //   597: getfield b : Ljava/lang/String;
    //   600: invokestatic a : (Ljava/lang/String;Ljava/lang/String;)Ljava/lang/String;
    //   603: invokeinterface a : (Ljava/lang/String;)V
    //   608: new java/lang/StringBuffer
    //   611: dup
    //   612: ldc 'file:///'
    //   614: invokespecial <init> : (Ljava/lang/String;)V
    //   617: aload_0
    //   618: invokevirtual a : ()Ljava/lang/String;
    //   621: invokevirtual append : (Ljava/lang/String;)Ljava/lang/StringBuffer;
    //   624: aload_0
    //   625: getfield b : Ljava/lang/String;
    //   628: invokevirtual append : (Ljava/lang/String;)Ljava/lang/StringBuffer;
    //   631: iconst_2
    //   632: invokevirtual append : (C)Ljava/lang/StringBuffer;
    //   635: getstatic v.a : [Lag;
    //   638: getstatic af.b : Laf;
    //   641: getfield a : Lv;
    //   644: getfield c : B
    //   647: aaload
    //   648: invokeinterface b : ()J
    //   653: invokevirtual append : (J)Ljava/lang/StringBuffer;
    //   656: iconst_3
    //   657: invokevirtual append : (C)Ljava/lang/StringBuffer;
    //   660: invokevirtual toString : ()Ljava/lang/String;
    //   663: invokevirtual toCharArray : ()[C
    //   666: dup
    //   667: astore_0
    //   668: iconst_0
    //   669: aload_0
    //   670: arraylength
    //   671: aconst_null
    //   672: iconst_0
    //   673: iconst_1
    //   674: invokestatic a : ([CII[BIZ)I
    //   677: istore_1
    //   678: getstatic af.b : Laf;
    //   681: getfield a : Lv;
    //   684: getfield b : Lah;
    //   687: iload_1
    //   688: newarray byte
    //   690: putfield a : [B
    //   693: aload_0
    //   694: iconst_0
    //   695: aload_0
    //   696: arraylength
    //   697: getstatic af.b : Laf;
    //   700: getfield a : Lv;
    //   703: getfield b : Lah;
    //   706: getfield a : [B
    //   709: iconst_0
    //   710: iconst_0
    //   711: invokestatic a : ([CII[BIZ)I
    //   714: pop
    //   715: getstatic af.b : Laf;
    //   718: getfield a : Lv;
    //   721: getfield b : Lah;
    //   724: aconst_null
    //   725: putfield c : Ljava/lang/String;
    //   728: getstatic af.b : Laf;
    //   731: getfield a : Lv;
    //   734: getfield b : Lah;
    //   737: getfield a : [B
    //   740: ifnonnull -> 776
    //   743: getstatic af.b : Laf;
    //   746: sipush #319
    //   749: invokestatic d : (I)Ljava/lang/String;
    //   752: invokevirtual c : (Ljava/lang/String;)V
    //   755: getstatic af.b : Laf;
    //   758: getfield a : Lv;
    //   761: aconst_null
    //   762: putfield b : Lah;
    //   765: getstatic af.b : Laf;
    //   768: getfield a : Lv;
    //   771: iconst_1
    //   772: invokevirtual d : (Z)V
    //   775: return
    //   776: getstatic af.b : Laf;
    //   779: getfield a : Lv;
    //   782: getfield b : Lah;
    //   785: getfield d : Ljava/lang/String;
    //   788: ifnull -> 848
    //   791: getstatic af.b : Laf;
    //   794: getfield a : Lv;
    //   797: getstatic af.b : Laf;
    //   800: getfield a : Lv;
    //   803: getfield b : Lah;
    //   806: getfield d : Ljava/lang/String;
    //   809: iconst_0
    //   810: iconst_1
    //   811: getstatic af.b : Laf;
    //   814: getfield a : Lv;
    //   817: getfield c : La;
    //   820: getfield b : Ljava/lang/String;
    //   823: ldc ''
    //   825: iconst_1
    //   826: anewarray ah
    //   829: dup
    //   830: iconst_0
    //   831: getstatic af.b : Laf;
    //   834: getfield a : Lv;
    //   837: getfield b : Lah;
    //   840: aastore
    //   841: invokestatic a : ([Lah;)[B
    //   844: invokevirtual a : (Ljava/lang/String;ZZLjava/lang/String;Ljava/lang/String;[B)V
    //   847: return
    //   848: getstatic af.b : Laf;
    //   851: getfield a : Lv;
    //   854: iconst_1
    //   855: invokevirtual d : (Z)V
    //   858: return
    //   859: getstatic af.b : Laf;
    //   862: getfield a : Lv;
    //   865: iconst_1
    //   866: invokevirtual d : (Z)V
    //   869: return
    //   870: aload_0
    //   871: getfield b : I
    //   874: bipush #17
    //   876: if_icmpne -> 886
    //   879: aload_0
    //   880: bipush #36
    //   882: invokespecial b : (I)V
    //   885: return
    //   886: aload_0
    //   887: getfield b : I
    //   890: bipush #18
    //   892: if_icmpne -> 911
    //   895: aload_2
    //   896: ldc '.omb'
    //   898: invokevirtual endsWith : (Ljava/lang/String;)Z
    //   901: ifeq -> 1000
    //   904: aload_0
    //   905: bipush #37
    //   907: invokespecial b : (I)V
    //   910: return
    //   911: aload_0
    //   912: getfield b : I
    //   915: bipush #21
    //   917: if_icmpne -> 931
    //   920: bipush #38
    //   922: putstatic ai.c : I
    //   925: aload_0
    //   926: aconst_null
    //   927: invokespecial c : (Ljava/lang/String;)V
    //   930: return
    //   931: aload_0
    //   932: getfield b : I
    //   935: bipush #22
    //   937: if_icmpne -> 956
    //   940: aload_2
    //   941: ldc '.omw'
    //   943: invokevirtual endsWith : (Ljava/lang/String;)Z
    //   946: ifeq -> 1000
    //   949: aload_0
    //   950: bipush #39
    //   952: invokespecial b : (I)V
    //   955: return
    //   956: aload_0
    //   957: getfield b : I
    //   960: bipush #23
    //   962: if_icmpne -> 976
    //   965: bipush #45
    //   967: putstatic ai.c : I
    //   970: aload_0
    //   971: aconst_null
    //   972: invokespecial c : (Ljava/lang/String;)V
    //   975: return
    //   976: aload_0
    //   977: getfield b : I
    //   980: bipush #24
    //   982: if_icmpne -> 1000
    //   985: aload_2
    //   986: ldc '.oml'
    //   988: invokevirtual endsWith : (Ljava/lang/String;)Z
    //   991: ifeq -> 1000
    //   994: aload_0
    //   995: bipush #46
    //   997: invokespecial b : (I)V
    //   1000: return
  }
  
  public final void b(boolean paramBoolean) {
    String str;
    if (paramBoolean) {
      c = true;
      str = (String)(v.a(this.b, '/') ? this.b : "");
    } else {
      c = true;
      str = (String)((!v.a(this.b, '/') && !"..".equals(this.b)) ? this.b : "");
    } 
    a(v.d(149 + (paramBoolean ? 171 : 172)), str);
  }
  
  public final void f() {
    c = true;
    if (a != null || !a.isEmpty()) {
      a(v.d(323), "");
      return;
    } 
    this.d = v.a(this.b, '/');
    a(v.d(323), v.h(this.b));
  }
  
  public final void g() {
    b(6);
    c = false;
  }
  
  public final void c(boolean paramBoolean) {
    c = paramBoolean ? true : true;
    c = this.b;
    a = (StringBuffer)a();
    k = false;
  }
  
  public final void h() {
    if (a == null || a.size() == 1) {
      a(v.d(322), v.h(c));
      return;
    } 
    b(c);
    c = false;
  }
  
  public final boolean a(String paramString) {
    // Byte code:
    //   0: aload_1
    //   1: ifnull -> 9
    //   4: aload_0
    //   5: aload_1
    //   6: putfield b : Ljava/lang/String;
    //   9: aload_0
    //   10: getfield b : Ljava/lang/String;
    //   13: invokestatic e : (Ljava/lang/String;)Z
    //   16: ifne -> 21
    //   19: iconst_0
    //   20: ireturn
    //   21: aload_0
    //   22: getfield b : Ljava/lang/String;
    //   25: invokevirtual toLowerCase : ()Ljava/lang/String;
    //   28: ldc '.oms'
    //   30: invokevirtual endsWith : (Ljava/lang/String;)Z
    //   33: ifeq -> 46
    //   36: aload_0
    //   37: getfield b : Ljava/lang/String;
    //   40: putstatic v.G : Ljava/lang/String;
    //   43: goto -> 76
    //   46: new java/lang/StringBuffer
    //   49: dup
    //   50: invokespecial <init> : ()V
    //   53: bipush #91
    //   55: invokevirtual append : (C)Ljava/lang/StringBuffer;
    //   58: aload_0
    //   59: getfield b : Ljava/lang/String;
    //   62: invokevirtual append : (Ljava/lang/String;)Ljava/lang/StringBuffer;
    //   65: bipush #93
    //   67: invokevirtual append : (C)Ljava/lang/StringBuffer;
    //   70: invokevirtual toString : ()Ljava/lang/String;
    //   73: putstatic v.G : Ljava/lang/String;
    //   76: new java/lang/StringBuffer
    //   79: dup
    //   80: ldc 'file:///'
    //   82: invokespecial <init> : (Ljava/lang/String;)V
    //   85: aload_0
    //   86: invokevirtual a : ()Ljava/lang/String;
    //   89: invokevirtual append : (Ljava/lang/String;)Ljava/lang/StringBuffer;
    //   92: aload_0
    //   93: getfield b : Ljava/lang/String;
    //   96: invokevirtual append : (Ljava/lang/String;)Ljava/lang/StringBuffer;
    //   99: invokevirtual toString : ()Ljava/lang/String;
    //   102: putstatic v.F : Ljava/lang/String;
    //   105: iconst_1
    //   106: putstatic v.cw : Z
    //   109: getstatic af.b : Laf;
    //   112: sipush #27697
    //   115: invokevirtual b : (I)V
    //   118: iconst_1
    //   119: ireturn
  }
  
  public final void i() {
    v.cI = !v.cI;
    b(20);
    c = false;
  }
  
  public final void a(boolean paramBoolean1, boolean paramBoolean2, boolean paramBoolean3) {
    this.e = paramBoolean1;
    this.f = paramBoolean2;
    this.g = paramBoolean3;
    b(35);
    c = false;
  }
  
  private void c(int paramInt) {
    if (((af)af.b).a != null && ((v)((a)((af)af.b).a).a).c != null && a(paramInt, (char[])((v)((a)((af)af.b).a).a).c)) {
      c = true;
      c(".txt");
    } 
  }
  
  public final void a(int paramInt, String paramString) {
    v.d[((v)((af)af.b).a).c] = this.b;
    ((v)((af)af.b).a).aQ = 0;
    if (((v)((af)af.b).a).h == null) {
      ((v)((af)af.b).a).h = (int[])new Vector(0);
    } else {
      ((v)((af)af.b).a).h.removeAllElements();
    } 
    ((v)((af)af.b).a).aP = paramInt;
    ((v)((af)af.b).a).C = v.a(a(), this.b);
    ((v)((af)af.b).a).q = this.b;
    ((v)((af)af.b).a).cq = true;
    a(paramString);
  }
  
  public final void a(String paramString) {
    int i = 1;
    String str = "";
    try {
      i = v.a(str = paramString.substring(paramString.indexOf(false) + 1), 1);
    } catch (Exception exception) {}
    if (((v)((af)af.b).a).aP == 2) {
      if (str.equals("<<")) {
        ((v)((af)af.b).a).aQ -= ((Integer)((v)((af)af.b).a).h.elementAt(((v)((af)af.b).a).h.size() - 2)).intValue();
        ((v)((af)af.b).a).h.removeElementAt(((v)((af)af.b).a).h.size() - 1);
        ((v)((af)af.b).a).h.removeElementAt(((v)((af)af.b).a).h.size() - 1);
      } else if (str.equals(">>")) {
        ((v)((af)af.b).a).aQ += ((Integer)((v)((af)af.b).a).h.lastElement()).intValue();
      } 
      if (((v)((af)af.b).a).aQ < 0)
        ((v)((af)af.b).a).aQ = 0; 
      if (((v)((af)af.b).a).aQ > ((v)((af)af.b).a).aR)
        ((v)((af)af.b).a).aQ = ((v)((af)af.b).a).aR - 1; 
    } else {
      ((v)((af)af.b).a).aQ = (i - 1) * ((((v)((af)af.b).a).aP == 3) ? v.aF : v.aE);
    } 
    ((v)((af)af.b).a).by = 0;
    b(9);
  }
  
  public final void j() {
    if (((v)((af)af.b).a).C != null && ((v)((af)af.b).a).C.length() > 0 && ((v)((af)af.b).a).aS != -1 && a(((v)((af)af.b).a).aP, (char[])((v)((af)af.b).a).c)) {
      ((v)((af)af.b).a).bf = this.b = true;
      b(40);
    } 
  }
  
  public final void k() {
    b(20);
  }
  
  public final void l() {
    b(42);
  }
  
  public final void m() {
    b(43);
  }
  
  public final void n() {
    b(44);
  }
  
  private static boolean a(int paramInt, char[] paramArrayOfchar) {
    try {
      char[] arrayOfChar;
      byte[] arrayOfByte;
      byte b;
      switch (paramInt) {
        case 3:
          e = (a = (StringBuffer)b(paramArrayOfchar)).length;
          break;
        case 2:
          a = (StringBuffer)new byte[v.a(paramArrayOfchar, 0, paramArrayOfchar.length, (byte[])null, 0, true)];
          e = v.a(paramArrayOfchar, 0, paramArrayOfchar.length, (byte[])a, 0, false);
          break;
        case 1:
          e = (a = (StringBuffer)a(paramArrayOfchar)).length;
          break;
        case 0:
          arrayOfByte = new byte[(arrayOfChar = paramArrayOfchar).length];
          for (b = 0; b < arrayOfChar.length; b++)
            arrayOfByte[b] = (byte)arrayOfChar[b]; 
          e = (a = (StringBuffer)arrayOfByte).length;
          break;
      } 
      return true;
    } catch (Throwable throwable) {
      ((af)af.b).a = null;
      ((af)af.b).b = null;
      return false;
    } 
  }
  
  public static int a() {
    return c;
  }
  
  public static void o() {
    c = false;
  }
  
  public final void p() {
    // Byte code:
    //   0: getstatic ai.b : Z
    //   3: ifeq -> 11
    //   6: aconst_null
    //   7: putstatic x.a : [Ljava/lang/String;
    //   10: return
    //   11: getstatic x.a : [Ljava/lang/String;
    //   14: ifnull -> 73
    //   17: getstatic x.a : I
    //   20: iconst_1
    //   21: iadd
    //   22: dup
    //   23: putstatic x.a : I
    //   26: getstatic x.a : [Ljava/lang/String;
    //   29: arraylength
    //   30: if_icmpge -> 73
    //   33: getstatic x.a : [Ljava/lang/String;
    //   36: getstatic x.a : I
    //   39: aaload
    //   40: dup
    //   41: putstatic x.a : Ljava/lang/String;
    //   44: invokevirtual toLowerCase : ()Ljava/lang/String;
    //   47: dup
    //   48: astore_1
    //   49: invokestatic b : (Ljava/lang/String;)Z
    //   52: ifne -> 62
    //   55: aload_1
    //   56: invokestatic c : (Ljava/lang/String;)Z
    //   59: ifeq -> 70
    //   62: aload_0
    //   63: getstatic x.d : Z
    //   66: invokevirtual d : (Z)V
    //   69: return
    //   70: goto -> 82
    //   73: getstatic x.a : I
    //   76: iconst_1
    //   77: isub
    //   78: putstatic x.a : I
    //   81: return
    //   82: getstatic x.e : Z
    //   85: ifeq -> 11
    //   88: return
  }
  
  public final void q() {
    // Byte code:
    //   0: getstatic ai.b : Z
    //   3: ifeq -> 11
    //   6: aconst_null
    //   7: putstatic x.a : [Ljava/lang/String;
    //   10: return
    //   11: getstatic x.a : [Ljava/lang/String;
    //   14: ifnull -> 69
    //   17: getstatic x.a : I
    //   20: iconst_1
    //   21: isub
    //   22: dup
    //   23: putstatic x.a : I
    //   26: iflt -> 69
    //   29: getstatic x.a : [Ljava/lang/String;
    //   32: getstatic x.a : I
    //   35: aaload
    //   36: dup
    //   37: putstatic x.a : Ljava/lang/String;
    //   40: invokevirtual toLowerCase : ()Ljava/lang/String;
    //   43: dup
    //   44: astore_1
    //   45: invokestatic b : (Ljava/lang/String;)Z
    //   48: ifne -> 58
    //   51: aload_1
    //   52: invokestatic c : (Ljava/lang/String;)Z
    //   55: ifeq -> 66
    //   58: aload_0
    //   59: getstatic x.d : Z
    //   62: invokevirtual d : (Z)V
    //   65: return
    //   66: goto -> 78
    //   69: getstatic x.a : I
    //   72: iconst_1
    //   73: iadd
    //   74: putstatic x.a : I
    //   77: return
    //   78: getstatic x.e : Z
    //   81: ifeq -> 11
    //   84: return
  }
  
  public final void d(boolean paramBoolean) {
    // Byte code:
    //   0: getstatic x.a : Ljava/lang/String;
    //   3: invokevirtual toLowerCase : ()Ljava/lang/String;
    //   6: dup
    //   7: astore_2
    //   8: invokestatic b : (Ljava/lang/String;)Z
    //   11: ifne -> 21
    //   14: aload_2
    //   15: invokestatic c : (Ljava/lang/String;)Z
    //   18: ifeq -> 97
    //   21: getstatic ai.a : Lx;
    //   24: ifnull -> 34
    //   27: getstatic ai.a : Lx;
    //   30: iconst_0
    //   31: putfield b : Z
    //   34: iconst_0
    //   35: invokestatic e : (Z)V
    //   38: iload_1
    //   39: putstatic x.d : Z
    //   42: new x
    //   45: dup
    //   46: getstatic v.cB : Z
    //   49: ldc 'file:///'
    //   51: getstatic x.a : Ljava/lang/String;
    //   54: invokestatic a : (Ljava/lang/String;Ljava/lang/String;)Ljava/lang/String;
    //   57: iconst_1
    //   58: invokespecial <init> : (ZLjava/lang/String;Z)V
    //   61: putstatic ai.a : Lx;
    //   64: iload_1
    //   65: ifne -> 75
    //   68: getstatic af.b : Laf;
    //   71: invokevirtual d : ()V
    //   74: return
    //   75: getstatic af.b : Laf;
    //   78: invokevirtual b : ()Z
    //   81: ifeq -> 110
    //   84: getstatic af.b : Laf;
    //   87: invokestatic a : (Ljavax/microedition/lcdui/Displayable;)V
    //   90: getstatic af.b : Laf;
    //   93: invokevirtual repaint : ()V
    //   96: return
    //   97: aload_2
    //   98: invokestatic d : (Ljava/lang/String;)Z
    //   101: ifeq -> 110
    //   104: aload_0
    //   105: bipush #29
    //   107: invokespecial b : (I)V
    //   110: return
  }
  
  public static void e(boolean paramBoolean) {
    if (a != null) {
      if (paramBoolean)
        x.e = '\001'; 
      a.a();
      a = null;
      if (x.d == null)
        af.b.d(); 
      v.C();
      if (af.b.b()) {
        v.a((Displayable)af.b);
        af.b.repaint();
      } 
    } 
  }
  
  public static String[] a(Enumeration paramEnumeration, String paramString) {
    Vector vector = new Vector(0);
    StringBuffer stringBuffer = new StringBuffer(0);
    while (paramEnumeration.hasMoreElements())
      vector.addElement(paramEnumeration.nextElement()); 
    String[] arrayOfString = new String[vector.size()];
    for (byte b = 0; b < vector.size(); b++) {
      stringBuffer.setLength(0);
      arrayOfString[b] = stringBuffer.append(paramString).append(vector.elementAt(b)).toString();
    } 
    return arrayOfString;
  }
  
  public static void r() {
    if (g != ((v)((af)af.b).a).c)
      a.removeAllElements(); 
    a = !a.isEmpty() ? 1 : 0;
  }
  
  public final void b(String paramString, boolean paramBoolean) {
    if (a.isEmpty()) {
      g = ((v)((af)af.b).a).c;
    } else {
      r();
    } 
    if (!"..".equals(paramString))
      if (a.contains(paramString)) {
        if (paramBoolean)
          a.removeElement(paramString); 
      } else {
        a.addElement(paramString);
      }  
    a = !a.isEmpty() ? 1 : 0;
    a = (StringBuffer)a();
  }
  
  public static void s() {
    a.removeAllElements();
    a = false;
  }
  
  public static String c(String paramString) {
    return paramString.substring(paramString.lastIndexOf('/', paramString.length() - 2) + 1);
  }
  
  public static String d(String paramString) {
    int i;
    return ((i = paramString.lastIndexOf('.')) != -1) ? paramString.substring(i) : "";
  }
  
  private static String i(String paramString) {
    if ((paramString = d(paramString)).length() > 0)
      paramString = paramString.substring(1); 
    return paramString;
  }
  
  private static String j(String paramString) {
    int i;
    return ((i = paramString.lastIndexOf('.')) != -1) ? paramString.substring(0, i) : paramString;
  }
  
  public static boolean b(String paramString) {
    return ((paramString = d(v.i(paramString))).equals(".mid") || paramString.equals(".midi") || paramString.equals(".kar") || paramString.equals(".amr") || paramString.equals(".wav") || paramString.equals(".wave") || paramString.equals(".mp3") || paramString.equals(".mmf") || paramString.equals(".imy") || paramString.equals(".bas") || paramString.equals(".m4a") || paramString.equals(".aac") || paramString.equals(".jts"));
  }
  
  public static boolean c(String paramString) {
    return ((paramString = d(v.i(paramString))).equals(".3gp") || paramString.equals(".mpg") || paramString.equals(".mp4"));
  }
  
  public static boolean d(String paramString) {
    return ((paramString = d(v.i(paramString))).equals(".jpg") || paramString.equals(".jpeg") || paramString.equals(".png") || paramString.equals(".gif") || paramString.equals(".bmp"));
  }
  
  public static int a(String paramString, boolean paramBoolean) {
    String str;
    return ((str = d(paramString = paramString.toLowerCase())).equals(".oms") || str.equals(".omc")) ? 3 : (str.equals(".key") ? 9 : (str.equals(".col") ? 8 : ((b(paramString) || c(paramString)) ? 6 : (d(paramString) ? 5 : (paramBoolean ? 0 : (paramString.equals("..") ? 1 : (v.a(paramString, '/') ? 2 : (h(str) ? 4 : 11))))))));
  }
  
  public static boolean e(String paramString) {
    return (g(paramString) && !f(paramString));
  }
  
  public static boolean f(String paramString) {
    return (v.a(paramString, '/') || v.a(paramString, '\\'));
  }
  
  public static boolean g(String paramString) {
    return (paramString != null && paramString.length() != 0 && !paramString.equals(".."));
  }
  
  public static long a(String paramString) {
    // Byte code:
    //   0: aload_0
    //   1: invokestatic e : (Ljava/lang/String;)Z
    //   4: ifeq -> 26
    //   7: getstatic v.a : [Lag;
    //   10: getstatic af.b : Laf;
    //   13: getfield a : Lv;
    //   16: getfield c : B
    //   19: aaload
    //   20: invokeinterface b : ()J
    //   25: lreturn
    //   26: getstatic v.a : [Lag;
    //   29: getstatic af.b : Laf;
    //   32: getfield a : Lv;
    //   35: getfield c : B
    //   38: aaload
    //   39: iconst_1
    //   40: invokeinterface a : (Z)J
    //   45: lreturn
  }
  
  public static String e(String paramString) {
    return paramString.substring(paramString.lastIndexOf('/') + 1);
  }
  
  public static String f(String paramString) {
    return paramString.substring(0, paramString.lastIndexOf('/') + 1);
  }
  
  public static String g(String paramString) {
    return paramString.substring(0, paramString.lastIndexOf('/') + 1);
  }
  
  public static String h(String paramString) {
    return a(paramString, false);
  }
  
  private static String a(String paramString, boolean paramBoolean) {
    if (paramString == null)
      return ""; 
    int i = paramString.length();
    StringBuffer stringBuffer = new StringBuffer(i);
    char c = Character.MIN_VALUE;
    for (byte b = 0; b < i; b++) {
      char c1 = paramString.charAt(b);
      if ("\"'*/:<>?\\`|?".indexOf(c1) == -1 && c1 >= ' ') {
        if (c1 == ' ') {
          if (c != ' ')
            stringBuffer.append(' '); 
        } else {
          stringBuffer.append(c1);
        } 
        c = c1;
      } else if (paramBoolean && "*".indexOf(c1) != -1) {
        stringBuffer.append(c1);
        c = c1;
      } 
    } 
    return stringBuffer.toString();
  }
  
  public final void t() {
    if (v.i == null)
      v.i = new Vector(1); 
    if (!v.i.contains(a())) {
      v.i.addElement(a());
      v.d((DataOutputStream)null);
    } 
    u();
  }
  
  public final void u() {
    if (v.i == null)
      v.i = new Vector(0); 
    t.a(541, v.i, null, "m", false, this.h, true, false, this);
    this.h = -1;
  }
  
  public final void v() {
    if (!g(this.b))
      return; 
    c = false;
    b(this.b, true);
    v.d[((v)((af)af.b).a).c] = this.b;
    af.b.a(26189, false);
  }
  
  public final void w() {
    c = true;
    a("mask", i);
  }
  
  public static boolean a(String paramString1, String paramString2, int paramInt1, int paramInt2) {
    while (true) {
      int i = paramInt1;
      if (paramInt1 < paramString2.length() && paramInt2 < paramString1.length()) {
        boolean bool1 = false;
        boolean bool2 = false;
        if (paramString2.charAt(paramInt1) == '*') {
          bool1 = true;
          i++;
        } 
        if (i >= paramString2.length())
          return true; 
        int j = paramString2.indexOf('*', i);
        String str;
        if ((str = paramString2.substring(i, (j != -1) ? j : paramString2.length())).length() + i >= paramString2.length())
          bool2 = true; 
        if (!bool2 && bool1) {
          if ((i = paramString1.indexOf(str, paramInt2)) == -1)
            return false; 
          paramInt2 = paramInt2 + i + str.length();
          paramInt1 = paramInt1 + str.length() + 1;
          paramString2 = paramString2;
          paramString1 = paramString1;
          continue;
        } 
        if (bool2)
          return !!paramString1.endsWith(str); 
        if (!paramString1.startsWith(str, paramInt2))
          return false; 
        paramInt2 += str.length();
        paramInt1 = paramInt1 + str.length() + 1;
        paramString2 = paramString2;
        paramString1 = paramString1;
        continue;
      } 
      break;
    } 
    return !((paramInt1 != paramString2.length() - 1 || (paramInt1 == paramString2.length() - 1 && paramString2.charAt(paramInt1) != '*')) && paramInt2 >= paramString1.length());
  }
  
  public final void x() {
    if (this.a == null)
      return; 
    c = false;
    for (byte b = 0; b < this.a.length; b++) {
      if (g((String)this.a[b]))
        b((String)this.a[b], true); 
    } 
    af.b.a(26189, false);
  }
  
  public static int a(String paramString1, long paramLong1, String paramString2, long paramLong2) {
    switch (af.b.a(v.d(277) + '\n' + paramString1 + ' ' + v.a(paramLong1) + " (" + paramLong1 + v.d(309) + ')' + "\n>>\n" + paramString2 + ' ' + v.a(paramLong2) + " (" + paramLong2 + v.d(309) + ')', false)) {
      case 0:
        return 2;
      case 1:
        return 1;
      case 3:
        return 3;
    } 
    return 4;
  }
  
  public final void b(String paramString) {
    if (this.b != true) {
      v.e[((v)((af)af.b).a).c] = paramString;
    } else {
      v.O = paramString;
    } 
    v.i = true;
  }
  
  public final String a() {
    return (String)((this.b != true) ? v.e[((v)((af)af.b).a).c] : v.O);
  }
}


/* Location:              D:\Desktop\kemulator\LocID_BitByByte.jar!\ai.class
 * Java compiler version: 2 (46.0)
 * JD-Core Version:       1.1.3
 */