import java.util.Hashtable;

public final class dk extends bg {
  private Hashtable h = new Hashtable();
  
  private Hashtable i = new Hashtable();
  
  private Hashtable j = new Hashtable();
  
  private boolean k = false;
  
  public static final byte[] c = dh.b("0,0,0,0,0,0B,1F,40,3,E7,3,E7,0,0,0,0", ',', 16);
  
  public static final byte[] d = dh.b("00,22,00,01,01,10,16,4f,00,01,00,04,01,10,16,4f,00,13,00,04,01,10,16,4f,00,02,00,01,01,10,16,4f,00,03,00,01,01,10,16,4f,00,15,00,01,01,10,16,4f,00,04,00,01,01,10,16,4f,00,06,00,01,01,10,16,4f,00,09,00,01,01,10,16,4f,00,0a,00,01,01,10,16,4f,00,0b,00,01,01,10,16,4f", ',', 16);
  
  public static final short[] e = new short[] { 
      34, 1, 1, 4, 19, 4, 2, 1, 3, 1, 
      21, 1, 4, 1, 6, 1, 9, 1, 10, 1, 
      11, 1 };
  
  public int f = 30000;
  
  private String l;
  
  private String m;
  
  private String n;
  
  private String o;
  
  private int p;
  
  private long q = 0L;
  
  private boolean r;
  
  private String s;
  
  private byte[] t;
  
  private boolean u;
  
  public ek g;
  
  public dk(String paramString1, String paramString2, String paramString3, String paramString4) {
    super(true, false);
    this.l = paramString1;
    this.m = paramString2;
    this.n = paramString3;
    this.o = paramString4;
  }
  
  private void a(String paramString) throws cr {
    int i = 0;
    try {
      i = ((i = Integer.parseInt(em.d(140))) > 0) ? i : 1;
    } catch (NumberFormatException numberFormatException) {
      i = 1;
    } 
    byte b = 0;
    while (b < i) {
      this.q = System.currentTimeMillis();
      if (this.k || this.g != cd.i)
        return; 
      try {
        this.g.a(paramString, true);
        return;
      } catch (cr cr) {
        this.g.a();
        if (b >= i - 1 || this.q + this.f < System.currentTimeMillis()) {
          this.p = -1;
          throw cr;
        } 
        b++;
      } 
    } 
  }
  
  public final void b() throws cr {
    this.p = 0;
    this.q = System.currentTimeMillis();
    if (this.l.length() == 0 || this.m.length() == 0) {
      this.p = -1;
      throw new cr((short)605, 117, 0);
    } 
    this.g = cd.i;
    a(this.n + ":" + this.o);
    this.p = 1;
    this.q = System.currentTimeMillis();
  }
  
  public final boolean a(dd paramdd) throws cr {
    // Byte code:
    //   0: aload_0
    //   1: getfield k : Z
    //   4: ifne -> 17
    //   7: aload_0
    //   8: getfield g : Lek;
    //   11: getstatic cd.i : Lek;
    //   14: if_acmpeq -> 19
    //   17: iconst_0
    //   18: ireturn
    //   19: aload_0
    //   20: iconst_1
    //   21: putfield r : Z
    //   24: iconst_0
    //   25: istore_2
    //   26: aload_0
    //   27: getfield p : I
    //   30: iconst_1
    //   31: if_icmpne -> 203
    //   34: aload_1
    //   35: instanceof cm
    //   38: ifeq -> 3336
    //   41: aload_1
    //   42: checkcast cm
    //   45: aconst_null
    //   46: astore_3
    //   47: invokevirtual a : ()I
    //   50: iconst_1
    //   51: if_icmpne -> 200
    //   54: bipush #41
    //   56: invokestatic h : (I)Z
    //   59: ifeq -> 155
    //   62: aload_0
    //   63: getfield g : Lek;
    //   66: new cm
    //   69: dup
    //   70: invokespecial <init> : ()V
    //   73: invokevirtual a : (Ldd;)V
    //   76: iconst_4
    //   77: aload_0
    //   78: getfield l : Ljava/lang/String;
    //   81: invokevirtual length : ()I
    //   84: iadd
    //   85: newarray byte
    //   87: dup
    //   88: astore #4
    //   90: iconst_0
    //   91: iconst_1
    //   92: invokestatic b : ([BII)V
    //   95: aload #4
    //   97: iconst_2
    //   98: aload_0
    //   99: getfield l : Ljava/lang/String;
    //   102: invokevirtual length : ()I
    //   105: invokestatic b : ([BII)V
    //   108: aload_0
    //   109: getfield l : Ljava/lang/String;
    //   112: invokestatic a : (Ljava/lang/String;)[B
    //   115: dup
    //   116: astore #5
    //   118: iconst_0
    //   119: aload #4
    //   121: iconst_4
    //   122: aload #5
    //   124: arraylength
    //   125: invokestatic arraycopy : (Ljava/lang/Object;ILjava/lang/Object;II)V
    //   128: aload_0
    //   129: getfield g : Lek;
    //   132: new bj
    //   135: dup
    //   136: bipush #23
    //   138: bipush #6
    //   140: lconst_0
    //   141: iconst_0
    //   142: newarray byte
    //   144: aload #4
    //   146: invokespecial <init> : (IIJ[B[B)V
    //   149: invokevirtual a : (Ldd;)V
    //   152: goto -> 181
    //   155: new cm
    //   158: dup
    //   159: aload_0
    //   160: getfield l : Ljava/lang/String;
    //   163: aload_0
    //   164: getfield m : Ljava/lang/String;
    //   167: invokespecial <init> : (Ljava/lang/String;Ljava/lang/String;)V
    //   170: astore #4
    //   172: aload_0
    //   173: getfield g : Lek;
    //   176: aload #4
    //   178: invokevirtual a : (Ldd;)V
    //   181: aload_0
    //   182: bipush #41
    //   184: invokestatic h : (I)Z
    //   187: ifne -> 194
    //   190: iconst_3
    //   191: goto -> 195
    //   194: iconst_2
    //   195: putfield p : I
    //   198: iconst_1
    //   199: istore_2
    //   200: goto -> 3336
    //   203: aload_0
    //   204: getfield p : I
    //   207: iconst_2
    //   208: if_icmpne -> 518
    //   211: aload_1
    //   212: instanceof bj
    //   215: ifeq -> 513
    //   218: aload_1
    //   219: checkcast bj
    //   222: dup
    //   223: astore_3
    //   224: getfield a : I
    //   227: bipush #23
    //   229: if_icmpne -> 499
    //   232: aload_3
    //   233: getfield b : I
    //   236: bipush #7
    //   238: if_icmpne -> 499
    //   241: aload_3
    //   242: invokevirtual a : ()[B
    //   245: dup
    //   246: astore #4
    //   248: iconst_0
    //   249: invokestatic c : ([BI)I
    //   252: dup
    //   253: istore #5
    //   255: newarray byte
    //   257: astore #6
    //   259: aload #4
    //   261: iconst_2
    //   262: aload #6
    //   264: iconst_0
    //   265: iload #5
    //   267: invokestatic arraycopy : (Ljava/lang/Object;ILjava/lang/Object;II)V
    //   270: iconst_4
    //   271: aload_0
    //   272: getfield l : Ljava/lang/String;
    //   275: invokevirtual length : ()I
    //   278: iadd
    //   279: iconst_2
    //   280: iadd
    //   281: iconst_2
    //   282: iadd
    //   283: bipush #16
    //   285: iadd
    //   286: newarray byte
    //   288: astore #7
    //   290: iconst_0
    //   291: istore #8
    //   293: aload #7
    //   295: iconst_0
    //   296: iconst_1
    //   297: invokestatic b : ([BII)V
    //   300: aload #7
    //   302: iconst_2
    //   303: aload_0
    //   304: getfield l : Ljava/lang/String;
    //   307: invokevirtual length : ()I
    //   310: invokestatic b : ([BII)V
    //   313: aload_0
    //   314: getfield l : Ljava/lang/String;
    //   317: invokestatic a : (Ljava/lang/String;)[B
    //   320: dup
    //   321: astore #9
    //   323: iconst_0
    //   324: aload #7
    //   326: iconst_4
    //   327: aload #9
    //   329: arraylength
    //   330: invokestatic arraycopy : (Ljava/lang/Object;ILjava/lang/Object;II)V
    //   333: iconst_4
    //   334: aload #9
    //   336: arraylength
    //   337: iadd
    //   338: istore #8
    //   340: aload #7
    //   342: iload #8
    //   344: bipush #37
    //   346: invokestatic b : ([BII)V
    //   349: iinc #8, 2
    //   352: aload #7
    //   354: iload #8
    //   356: bipush #16
    //   358: invokestatic b : ([BII)V
    //   361: iinc #8, 2
    //   364: aload #6
    //   366: arraylength
    //   367: aload_0
    //   368: getfield m : Ljava/lang/String;
    //   371: invokevirtual length : ()I
    //   374: iadd
    //   375: getstatic dh.G : [B
    //   378: arraylength
    //   379: iadd
    //   380: newarray byte
    //   382: astore #10
    //   384: iconst_0
    //   385: istore #11
    //   387: aload #6
    //   389: iconst_0
    //   390: aload #10
    //   392: iconst_0
    //   393: aload #6
    //   395: arraylength
    //   396: invokestatic arraycopy : (Ljava/lang/Object;ILjava/lang/Object;II)V
    //   399: iconst_0
    //   400: aload #6
    //   402: arraylength
    //   403: iadd
    //   404: istore #11
    //   406: aload_0
    //   407: getfield m : Ljava/lang/String;
    //   410: invokestatic a : (Ljava/lang/String;)[B
    //   413: dup
    //   414: astore #12
    //   416: iconst_0
    //   417: aload #10
    //   419: iload #11
    //   421: aload #12
    //   423: arraylength
    //   424: invokestatic arraycopy : (Ljava/lang/Object;ILjava/lang/Object;II)V
    //   427: iload #11
    //   429: aload #12
    //   431: arraylength
    //   432: iadd
    //   433: istore #11
    //   435: getstatic dh.G : [B
    //   438: iconst_0
    //   439: aload #10
    //   441: iload #11
    //   443: getstatic dh.G : [B
    //   446: arraylength
    //   447: invokestatic arraycopy : (Ljava/lang/Object;ILjava/lang/Object;II)V
    //   450: aload #10
    //   452: invokestatic e : ([B)[B
    //   455: aconst_null
    //   456: astore #13
    //   458: iconst_0
    //   459: aload #7
    //   461: iload #8
    //   463: bipush #16
    //   465: invokestatic arraycopy : (Ljava/lang/Object;ILjava/lang/Object;II)V
    //   468: aload_0
    //   469: getfield g : Lek;
    //   472: new bj
    //   475: dup
    //   476: bipush #23
    //   478: iconst_2
    //   479: lconst_0
    //   480: iconst_0
    //   481: newarray byte
    //   483: aload #7
    //   485: invokespecial <init> : (IIJ[B[B)V
    //   488: invokevirtual a : (Ldd;)V
    //   491: aload_0
    //   492: iconst_3
    //   493: putfield p : I
    //   496: goto -> 513
    //   499: new cr
    //   502: dup
    //   503: sipush #597
    //   506: bipush #100
    //   508: iconst_0
    //   509: invokespecial <init> : (SII)V
    //   512: athrow
    //   513: iconst_1
    //   514: istore_2
    //   515: goto -> 3336
    //   518: aload_0
    //   519: getfield p : I
    //   522: iconst_3
    //   523: if_icmpne -> 1031
    //   526: iconst_m1
    //   527: istore_3
    //   528: bipush #41
    //   530: invokestatic h : (I)Z
    //   533: ifeq -> 688
    //   536: aload_1
    //   537: instanceof bj
    //   540: ifeq -> 678
    //   543: aload_1
    //   544: checkcast bj
    //   547: dup
    //   548: astore #4
    //   550: getfield a : I
    //   553: bipush #23
    //   555: if_icmpne -> 675
    //   558: aload #4
    //   560: getfield b : I
    //   563: iconst_3
    //   564: if_icmpne -> 675
    //   567: aload #4
    //   569: invokevirtual a : ()[B
    //   572: astore #5
    //   574: iconst_0
    //   575: istore #6
    //   577: iload #6
    //   579: aload #5
    //   581: arraylength
    //   582: if_icmpge -> 675
    //   585: aload #5
    //   587: iload #6
    //   589: invokestatic e : ([BI)[B
    //   592: astore #7
    //   594: aload #5
    //   596: iload #6
    //   598: invokestatic c : ([BI)I
    //   601: istore #8
    //   603: iload #6
    //   605: iconst_4
    //   606: aload #7
    //   608: arraylength
    //   609: iadd
    //   610: iadd
    //   611: istore #6
    //   613: iload #8
    //   615: tableswitch default -> 672, 5 -> 654, 6 -> 666, 7 -> 672, 8 -> 644
    //   644: aload #7
    //   646: iconst_0
    //   647: invokestatic c : ([BI)I
    //   650: istore_3
    //   651: goto -> 577
    //   654: aload_0
    //   655: aload #7
    //   657: invokestatic a : ([B)Ljava/lang/String;
    //   660: putfield s : Ljava/lang/String;
    //   663: goto -> 577
    //   666: aload_0
    //   667: aload #7
    //   669: putfield t : [B
    //   672: goto -> 577
    //   675: goto -> 747
    //   678: aload_1
    //   679: instanceof eq
    //   682: ifeq -> 747
    //   685: goto -> 745
    //   688: aload_1
    //   689: instanceof eq
    //   692: ifeq -> 747
    //   695: aload_1
    //   696: checkcast eq
    //   699: dup
    //   700: astore #4
    //   702: invokevirtual a : ()I
    //   705: iconst_1
    //   706: if_icmpne -> 730
    //   709: aload_0
    //   710: aload #4
    //   712: invokevirtual c : ()[B
    //   715: putfield t : [B
    //   718: aload_0
    //   719: aload #4
    //   721: invokevirtual b : ()Ljava/lang/String;
    //   724: putfield s : Ljava/lang/String;
    //   727: goto -> 745
    //   730: aload #4
    //   732: invokevirtual a : ()I
    //   735: iconst_2
    //   736: if_icmpne -> 745
    //   739: aload #4
    //   741: invokevirtual d : ()I
    //   744: istore_3
    //   745: iconst_1
    //   746: istore_2
    //   747: iload_3
    //   748: iconst_m1
    //   749: if_icmpeq -> 968
    //   752: iload_3
    //   753: tableswitch default -> 954, 1 -> 884, 2 -> 954, 3 -> 954, 4 -> 898, 5 -> 898, 6 -> 954, 7 -> 912, 8 -> 912, 9 -> 954, 10 -> 954, 11 -> 954, 12 -> 954, 13 -> 954, 14 -> 954, 15 -> 954, 16 -> 954, 17 -> 954, 18 -> 954, 19 -> 954, 20 -> 954, 21 -> 926, 22 -> 926, 23 -> 954, 24 -> 940, 25 -> 954, 26 -> 954, 27 -> 954, 28 -> 954, 29 -> 940
    //   884: new cr
    //   887: dup
    //   888: sipush #602
    //   891: bipush #110
    //   893: iload_3
    //   894: invokespecial <init> : (SII)V
    //   897: athrow
    //   898: new cr
    //   901: dup
    //   902: sipush #599
    //   905: bipush #111
    //   907: iload_3
    //   908: invokespecial <init> : (SII)V
    //   911: athrow
    //   912: new cr
    //   915: dup
    //   916: sipush #600
    //   919: bipush #112
    //   921: iload_3
    //   922: invokespecial <init> : (SII)V
    //   925: athrow
    //   926: new cr
    //   929: dup
    //   930: sipush #601
    //   933: bipush #113
    //   935: iload_3
    //   936: invokespecial <init> : (SII)V
    //   939: athrow
    //   940: new cr
    //   943: dup
    //   944: sipush #602
    //   947: bipush #114
    //   949: iload_3
    //   950: invokespecial <init> : (SII)V
    //   953: athrow
    //   954: new cr
    //   957: dup
    //   958: sipush #597
    //   961: bipush #100
    //   963: iload_3
    //   964: invokespecial <init> : (SII)V
    //   967: athrow
    //   968: iload_2
    //   969: aload_0
    //   970: getfield s : Ljava/lang/String;
    //   973: ifnull -> 980
    //   976: iconst_1
    //   977: goto -> 981
    //   980: iconst_0
    //   981: iand
    //   982: aload_0
    //   983: getfield t : [B
    //   986: ifnull -> 993
    //   989: iconst_1
    //   990: goto -> 994
    //   993: iconst_0
    //   994: iand
    //   995: ifeq -> 1028
    //   998: aload_0
    //   999: getfield g : Lek;
    //   1002: instanceof dn
    //   1005: ifne -> 1015
    //   1008: aload_0
    //   1009: getfield g : Lek;
    //   1012: invokevirtual a : ()V
    //   1015: aload_0
    //   1016: aload_0
    //   1017: getfield s : Ljava/lang/String;
    //   1020: invokespecial a : (Ljava/lang/String;)V
    //   1023: aload_0
    //   1024: iconst_4
    //   1025: putfield p : I
    //   1028: goto -> 3336
    //   1031: aload_0
    //   1032: getfield p : I
    //   1035: iconst_4
    //   1036: if_icmpne -> 1091
    //   1039: aload_1
    //   1040: instanceof cm
    //   1043: ifeq -> 3336
    //   1046: aload_1
    //   1047: checkcast cm
    //   1050: aconst_null
    //   1051: astore_3
    //   1052: invokevirtual a : ()I
    //   1055: iconst_1
    //   1056: if_icmpne -> 1088
    //   1059: new cm
    //   1062: dup
    //   1063: aload_0
    //   1064: getfield t : [B
    //   1067: invokespecial <init> : ([B)V
    //   1070: astore #4
    //   1072: aload_0
    //   1073: getfield g : Lek;
    //   1076: aload #4
    //   1078: invokevirtual a : (Ldd;)V
    //   1081: aload_0
    //   1082: iconst_5
    //   1083: putfield p : I
    //   1086: iconst_1
    //   1087: istore_2
    //   1088: goto -> 3336
    //   1091: aload_0
    //   1092: getfield p : I
    //   1095: iconst_5
    //   1096: if_icmpne -> 1170
    //   1099: new java/io/ByteArrayOutputStream
    //   1102: dup
    //   1103: invokespecial <init> : ()V
    //   1106: astore_3
    //   1107: iconst_0
    //   1108: istore #4
    //   1110: iload #4
    //   1112: getstatic dk.e : [S
    //   1115: arraylength
    //   1116: if_icmpge -> 1136
    //   1119: aload_3
    //   1120: getstatic dk.e : [S
    //   1123: iload #4
    //   1125: saload
    //   1126: iconst_1
    //   1127: invokestatic a : (Ljava/io/ByteArrayOutputStream;IZ)V
    //   1130: iinc #4, 1
    //   1133: goto -> 1110
    //   1136: aload_0
    //   1137: getfield g : Lek;
    //   1140: new bj
    //   1143: dup
    //   1144: iconst_1
    //   1145: bipush #23
    //   1147: lconst_0
    //   1148: iconst_0
    //   1149: newarray byte
    //   1151: aload_3
    //   1152: invokevirtual toByteArray : ()[B
    //   1155: invokespecial <init> : (IIJ[B[B)V
    //   1158: invokevirtual a : (Ldd;)V
    //   1161: aload_0
    //   1162: bipush #6
    //   1164: putfield p : I
    //   1167: goto -> 3336
    //   1170: aload_0
    //   1171: getfield p : I
    //   1174: bipush #6
    //   1176: if_icmpne -> 1505
    //   1179: new bj
    //   1182: dup
    //   1183: iconst_1
    //   1184: bipush #14
    //   1186: ldc2_w 14
    //   1189: iconst_0
    //   1190: newarray byte
    //   1192: iconst_0
    //   1193: newarray byte
    //   1195: invokespecial <init> : (IIJ[B[B)V
    //   1198: astore_3
    //   1199: aload_0
    //   1200: getfield g : Lek;
    //   1203: aload_3
    //   1204: invokevirtual a : (Ldd;)V
    //   1207: bipush #6
    //   1209: newarray byte
    //   1211: dup
    //   1212: astore #4
    //   1214: iconst_0
    //   1215: ldc2_w 720898
    //   1218: invokestatic a : ([BIJ)V
    //   1221: aload #4
    //   1223: iconst_4
    //   1224: bipush #15
    //   1226: invokestatic b : ([BII)V
    //   1229: new bj
    //   1232: dup
    //   1233: bipush #19
    //   1235: iconst_2
    //   1236: ldc2_w 2
    //   1239: iconst_0
    //   1240: newarray byte
    //   1242: aload #4
    //   1244: invokespecial <init> : (IIJ[B[B)V
    //   1247: astore_3
    //   1248: aload_0
    //   1249: getfield g : Lek;
    //   1252: aload_3
    //   1253: invokevirtual a : (Ldd;)V
    //   1256: new bj
    //   1259: dup
    //   1260: iconst_2
    //   1261: iconst_2
    //   1262: ldc2_w 2
    //   1265: iconst_0
    //   1266: newarray byte
    //   1268: iconst_0
    //   1269: newarray byte
    //   1271: invokespecial <init> : (IIJ[B[B)V
    //   1274: astore_3
    //   1275: aload_0
    //   1276: getfield g : Lek;
    //   1279: aload_3
    //   1280: invokevirtual a : (Ldd;)V
    //   1283: bipush #6
    //   1285: newarray byte
    //   1287: dup
    //   1288: astore #4
    //   1290: iconst_0
    //   1291: ldc2_w 327682
    //   1294: invokestatic a : ([BIJ)V
    //   1297: aload #4
    //   1299: iconst_4
    //   1300: iconst_3
    //   1301: invokestatic b : ([BII)V
    //   1304: new bj
    //   1307: dup
    //   1308: iconst_3
    //   1309: iconst_2
    //   1310: ldc2_w 2
    //   1313: iconst_0
    //   1314: newarray byte
    //   1316: aload #4
    //   1318: invokespecial <init> : (IIJ[B[B)V
    //   1321: astore_3
    //   1322: aload_0
    //   1323: getfield g : Lek;
    //   1326: aload_3
    //   1327: invokevirtual a : (Ldd;)V
    //   1330: new bj
    //   1333: dup
    //   1334: iconst_4
    //   1335: iconst_4
    //   1336: ldc2_w 4
    //   1339: iconst_0
    //   1340: newarray byte
    //   1342: iconst_0
    //   1343: newarray byte
    //   1345: invokespecial <init> : (IIJ[B[B)V
    //   1348: astore_3
    //   1349: aload_0
    //   1350: getfield g : Lek;
    //   1353: aload_3
    //   1354: invokevirtual a : (Ldd;)V
    //   1357: new bj
    //   1360: dup
    //   1361: bipush #9
    //   1363: iconst_2
    //   1364: ldc2_w 2
    //   1367: iconst_0
    //   1368: newarray byte
    //   1370: iconst_0
    //   1371: newarray byte
    //   1373: invokespecial <init> : (IIJ[B[B)V
    //   1376: astore_3
    //   1377: aload_0
    //   1378: getfield g : Lek;
    //   1381: aload_3
    //   1382: invokevirtual a : (Ldd;)V
    //   1385: invokestatic c : ()I
    //   1388: i2l
    //   1389: lstore #5
    //   1391: invokestatic d : ()I
    //   1394: istore #7
    //   1396: lload #5
    //   1398: ldc2_w -1
    //   1401: lcmp
    //   1402: ifne -> 1411
    //   1405: iload #7
    //   1407: iconst_m1
    //   1408: if_icmpeq -> 1417
    //   1411: invokestatic e : ()I
    //   1414: ifne -> 1448
    //   1417: new bj
    //   1420: dup
    //   1421: bipush #19
    //   1423: iconst_4
    //   1424: lconst_0
    //   1425: iconst_0
    //   1426: newarray byte
    //   1428: iconst_0
    //   1429: newarray byte
    //   1431: invokespecial <init> : (IIJ[B[B)V
    //   1434: astore #8
    //   1436: aload_0
    //   1437: getfield g : Lek;
    //   1440: aload #8
    //   1442: invokevirtual a : (Ldd;)V
    //   1445: goto -> 1496
    //   1448: bipush #6
    //   1450: newarray byte
    //   1452: dup
    //   1453: astore #8
    //   1455: iconst_0
    //   1456: lload #5
    //   1458: invokestatic a : ([BIJ)V
    //   1461: aload #8
    //   1463: iconst_4
    //   1464: iload #7
    //   1466: invokestatic b : ([BII)V
    //   1469: new bj
    //   1472: dup
    //   1473: bipush #19
    //   1475: iconst_5
    //   1476: lconst_0
    //   1477: iconst_0
    //   1478: newarray byte
    //   1480: aload #8
    //   1482: invokespecial <init> : (IIJ[B[B)V
    //   1485: astore #9
    //   1487: aload_0
    //   1488: getfield g : Lek;
    //   1491: aload #9
    //   1493: invokevirtual a : (Ldd;)V
    //   1496: aload_0
    //   1497: bipush #7
    //   1499: putfield p : I
    //   1502: goto -> 3336
    //   1505: aload_0
    //   1506: getfield p : I
    //   1509: bipush #7
    //   1511: if_icmpne -> 2713
    //   1514: aload_1
    //   1515: instanceof bj
    //   1518: ifeq -> 3336
    //   1521: aload_1
    //   1522: checkcast bj
    //   1525: dup
    //   1526: astore_3
    //   1527: getfield a : I
    //   1530: bipush #19
    //   1532: if_icmpne -> 1554
    //   1535: aload_3
    //   1536: getfield b : I
    //   1539: bipush #15
    //   1541: if_icmpne -> 1554
    //   1544: aload_0
    //   1545: iconst_1
    //   1546: putfield u : Z
    //   1549: iconst_1
    //   1550: istore_2
    //   1551: goto -> 2386
    //   1554: aload_3
    //   1555: getfield a : I
    //   1558: bipush #19
    //   1560: if_icmpne -> 2386
    //   1563: aload_3
    //   1564: getfield b : I
    //   1567: bipush #6
    //   1569: if_icmpne -> 2386
    //   1572: aload_3
    //   1573: getfield c : I
    //   1576: iconst_1
    //   1577: if_icmpeq -> 1585
    //   1580: aload_0
    //   1581: iconst_1
    //   1582: putfield u : Z
    //   1585: new java/util/Vector
    //   1588: dup
    //   1589: invokespecial <init> : ()V
    //   1592: astore #4
    //   1594: aload_3
    //   1595: invokevirtual a : ()[B
    //   1598: astore #5
    //   1600: iconst_0
    //   1601: istore #6
    //   1603: aload #5
    //   1605: arraylength
    //   1606: iconst_3
    //   1607: if_icmpge -> 1624
    //   1610: new cr
    //   1613: dup
    //   1614: sipush #603
    //   1617: bipush #115
    //   1619: iconst_0
    //   1620: invokespecial <init> : (SII)V
    //   1623: athrow
    //   1624: iinc #6, 1
    //   1627: aload #5
    //   1629: iconst_1
    //   1630: invokestatic c : ([BI)I
    //   1633: istore #7
    //   1635: iinc #6, 2
    //   1638: iconst_0
    //   1639: istore #8
    //   1641: iload #8
    //   1643: iload #7
    //   1645: if_icmpge -> 2323
    //   1648: aload #5
    //   1650: arraylength
    //   1651: iload #6
    //   1653: iconst_2
    //   1654: iadd
    //   1655: if_icmpge -> 1672
    //   1658: new cr
    //   1661: dup
    //   1662: sipush #603
    //   1665: bipush #115
    //   1667: iconst_1
    //   1668: invokespecial <init> : (SII)V
    //   1671: athrow
    //   1672: aload #5
    //   1674: iload #6
    //   1676: invokestatic c : ([BI)I
    //   1679: istore #9
    //   1681: iinc #6, 2
    //   1684: aload #5
    //   1686: arraylength
    //   1687: iload #6
    //   1689: iload #9
    //   1691: iadd
    //   1692: iconst_2
    //   1693: iadd
    //   1694: iconst_2
    //   1695: iadd
    //   1696: iconst_2
    //   1697: iadd
    //   1698: iconst_2
    //   1699: iadd
    //   1700: if_icmpge -> 1717
    //   1703: new cr
    //   1706: dup
    //   1707: sipush #603
    //   1710: bipush #115
    //   1712: iconst_2
    //   1713: invokespecial <init> : (SII)V
    //   1716: athrow
    //   1717: aload #5
    //   1719: iload #6
    //   1721: iload #9
    //   1723: aload #5
    //   1725: iload #6
    //   1727: iload #9
    //   1729: invokestatic f : ([BII)Z
    //   1732: invokestatic b : ([BIIZ)Ljava/lang/String;
    //   1735: astore #10
    //   1737: iload #6
    //   1739: iload #9
    //   1741: iadd
    //   1742: istore #6
    //   1744: aload #5
    //   1746: iload #6
    //   1748: invokestatic c : ([BI)I
    //   1751: istore #11
    //   1753: aload #5
    //   1755: iload #6
    //   1757: iconst_2
    //   1758: iadd
    //   1759: invokestatic c : ([BI)I
    //   1762: istore #12
    //   1764: aload #5
    //   1766: iload #6
    //   1768: iconst_4
    //   1769: iadd
    //   1770: invokestatic c : ([BI)I
    //   1773: istore #13
    //   1775: iinc #6, 6
    //   1778: aload #5
    //   1780: iload #6
    //   1782: invokestatic c : ([BI)I
    //   1785: istore #14
    //   1787: iinc #6, 2
    //   1790: aload #5
    //   1792: arraylength
    //   1793: iload #6
    //   1795: iload #14
    //   1797: iadd
    //   1798: if_icmpge -> 1815
    //   1801: new cr
    //   1804: dup
    //   1805: sipush #603
    //   1808: bipush #115
    //   1810: iconst_3
    //   1811: invokespecial <init> : (SII)V
    //   1814: athrow
    //   1815: iload #13
    //   1817: ifeq -> 1842
    //   1820: iload #13
    //   1822: bipush #25
    //   1824: if_icmpeq -> 1834
    //   1827: iload #13
    //   1829: bipush #27
    //   1831: if_icmpne -> 2063
    //   1834: bipush #23
    //   1836: invokestatic h : (I)Z
    //   1839: ifeq -> 2063
    //   1842: new java/lang/String
    //   1845: dup
    //   1846: aload #10
    //   1848: invokespecial <init> : (Ljava/lang/String;)V
    //   1851: astore #15
    //   1853: iconst_0
    //   1854: istore #16
    //   1856: iload #14
    //   1858: ifle -> 1949
    //   1861: aload #5
    //   1863: iload #6
    //   1865: invokestatic e : ([BI)[B
    //   1868: dup
    //   1869: astore #17
    //   1871: ifnonnull -> 1888
    //   1874: new cr
    //   1877: dup
    //   1878: sipush #603
    //   1881: bipush #115
    //   1883: iconst_4
    //   1884: invokespecial <init> : (SII)V
    //   1887: athrow
    //   1888: aload #5
    //   1890: iload #6
    //   1892: invokestatic c : ([BI)I
    //   1895: dup
    //   1896: istore #18
    //   1898: sipush #305
    //   1901: if_icmpne -> 1915
    //   1904: aload #17
    //   1906: iconst_1
    //   1907: invokestatic a : ([BZ)Ljava/lang/String;
    //   1910: astore #15
    //   1912: goto -> 1925
    //   1915: iload #18
    //   1917: bipush #102
    //   1919: if_icmpne -> 1925
    //   1922: iconst_1
    //   1923: istore #16
    //   1925: iinc #14, -4
    //   1928: iload #14
    //   1930: aload #17
    //   1932: arraylength
    //   1933: isub
    //   1934: istore #14
    //   1936: iload #6
    //   1938: iconst_4
    //   1939: aload #17
    //   1941: arraylength
    //   1942: iadd
    //   1943: iadd
    //   1944: istore #6
    //   1946: goto -> 1856
    //   1949: iload #14
    //   1951: ifeq -> 1968
    //   1954: new cr
    //   1957: dup
    //   1958: sipush #603
    //   1961: bipush #115
    //   1963: iconst_5
    //   1964: invokespecial <init> : (SII)V
    //   1967: athrow
    //   1968: new dm
    //   1971: dup
    //   1972: iload #12
    //   1974: iload #11
    //   1976: aload #10
    //   1978: aload #15
    //   1980: iload #16
    //   1982: iconst_1
    //   1983: invokespecial <init> : (IILjava/lang/String;Ljava/lang/String;ZZ)V
    //   1986: astore #17
    //   1988: aload #4
    //   1990: aload #17
    //   1992: invokevirtual addElement : (Ljava/lang/Object;)V
    //   1995: iload #13
    //   1997: bipush #25
    //   1999: if_icmpeq -> 2009
    //   2002: iload #13
    //   2004: bipush #27
    //   2006: if_icmpne -> 2052
    //   2009: aload #17
    //   2011: bipush #32
    //   2013: iconst_1
    //   2014: invokevirtual a : (IZ)V
    //   2017: aload #17
    //   2019: invokevirtual getUinString : ()Ljava/lang/String;
    //   2022: getstatic cp.c : Ljava/lang/String;
    //   2025: invokevirtual equals : (Ljava/lang/Object;)Z
    //   2028: ifne -> 2044
    //   2031: aload #17
    //   2033: invokevirtual getUinString : ()Ljava/lang/String;
    //   2036: ldc '410454751'
    //   2038: invokevirtual equals : (Ljava/lang/Object;)Z
    //   2041: ifeq -> 2052
    //   2044: aload #4
    //   2046: aload #17
    //   2048: invokevirtual removeElement : (Ljava/lang/Object;)Z
    //   2051: pop
    //   2052: goto -> 2317
    //   2055: pop
    //   2056: goto -> 2317
    //   2059: pop
    //   2060: goto -> 2317
    //   2063: iload #13
    //   2065: iconst_1
    //   2066: if_icmpne -> 2100
    //   2069: iload #6
    //   2071: iload #14
    //   2073: iadd
    //   2074: istore #6
    //   2076: iload #11
    //   2078: ifeq -> 2317
    //   2081: aload #4
    //   2083: new bu
    //   2086: dup
    //   2087: iload #11
    //   2089: aload #10
    //   2091: invokespecial <init> : (ILjava/lang/String;)V
    //   2094: invokevirtual addElement : (Ljava/lang/Object;)V
    //   2097: goto -> 2317
    //   2100: iload #13
    //   2102: iconst_2
    //   2103: if_icmpne -> 2135
    //   2106: iload #6
    //   2108: iload #14
    //   2110: iadd
    //   2111: istore #6
    //   2113: aload_0
    //   2114: getfield j : Ljava/util/Hashtable;
    //   2117: aload #10
    //   2119: new java/lang/Integer
    //   2122: dup
    //   2123: iload #12
    //   2125: invokespecial <init> : (I)V
    //   2128: invokevirtual put : (Ljava/lang/Object;Ljava/lang/Object;)Ljava/lang/Object;
    //   2131: pop
    //   2132: goto -> 2317
    //   2135: iload #13
    //   2137: iconst_3
    //   2138: if_icmpne -> 2170
    //   2141: iload #6
    //   2143: iload #14
    //   2145: iadd
    //   2146: istore #6
    //   2148: aload_0
    //   2149: getfield i : Ljava/util/Hashtable;
    //   2152: aload #10
    //   2154: new java/lang/Integer
    //   2157: dup
    //   2158: iload #12
    //   2160: invokespecial <init> : (I)V
    //   2163: invokevirtual put : (Ljava/lang/Object;Ljava/lang/Object;)Ljava/lang/Object;
    //   2166: pop
    //   2167: goto -> 2317
    //   2170: iload #13
    //   2172: bipush #14
    //   2174: if_icmpne -> 2206
    //   2177: iload #6
    //   2179: iload #14
    //   2181: iadd
    //   2182: istore #6
    //   2184: aload_0
    //   2185: getfield h : Ljava/util/Hashtable;
    //   2188: aload #10
    //   2190: new java/lang/Integer
    //   2193: dup
    //   2194: iload #12
    //   2196: invokespecial <init> : (I)V
    //   2199: invokevirtual put : (Ljava/lang/Object;Ljava/lang/Object;)Ljava/lang/Object;
    //   2202: pop
    //   2203: goto -> 2317
    //   2206: iload #13
    //   2208: iconst_4
    //   2209: if_icmpne -> 2310
    //   2212: iload #14
    //   2214: ifle -> 2290
    //   2217: aload #5
    //   2219: iload #6
    //   2221: invokestatic e : ([BI)[B
    //   2224: dup
    //   2225: astore #15
    //   2227: ifnonnull -> 2245
    //   2230: new cr
    //   2233: dup
    //   2234: sipush #603
    //   2237: bipush #115
    //   2239: bipush #110
    //   2241: invokespecial <init> : (SII)V
    //   2244: athrow
    //   2245: aload #5
    //   2247: iload #6
    //   2249: invokestatic c : ([BI)I
    //   2252: sipush #202
    //   2255: if_icmpne -> 2266
    //   2258: invokestatic a : ()Lcd;
    //   2261: iload #12
    //   2263: putfield o : I
    //   2266: iinc #14, -4
    //   2269: iload #14
    //   2271: aload #15
    //   2273: arraylength
    //   2274: isub
    //   2275: istore #14
    //   2277: iload #6
    //   2279: iconst_4
    //   2280: aload #15
    //   2282: arraylength
    //   2283: iadd
    //   2284: iadd
    //   2285: istore #6
    //   2287: goto -> 2212
    //   2290: iload #14
    //   2292: ifeq -> 2317
    //   2295: new cr
    //   2298: dup
    //   2299: sipush #603
    //   2302: bipush #115
    //   2304: bipush #111
    //   2306: invokespecial <init> : (SII)V
    //   2309: athrow
    //   2310: iload #6
    //   2312: iload #14
    //   2314: iadd
    //   2315: istore #6
    //   2317: iinc #8, 1
    //   2320: goto -> 1641
    //   2323: aload #5
    //   2325: arraylength
    //   2326: iload #6
    //   2328: iconst_4
    //   2329: iadd
    //   2330: if_icmpeq -> 2348
    //   2333: new cr
    //   2336: dup
    //   2337: sipush #603
    //   2340: bipush #115
    //   2342: bipush #6
    //   2344: invokespecial <init> : (SII)V
    //   2347: athrow
    //   2348: aload #5
    //   2350: iload #6
    //   2352: invokestatic d : ([BI)J
    //   2355: l2i
    //   2356: istore #8
    //   2358: aload #4
    //   2360: invokevirtual size : ()I
    //   2363: anewarray er
    //   2366: astore #9
    //   2368: aload #4
    //   2370: aload #9
    //   2372: invokevirtual copyInto : ([Ljava/lang/Object;)V
    //   2375: iload #8
    //   2377: iload #7
    //   2379: aload #9
    //   2381: invokestatic a : (II[Ler;)V
    //   2384: iconst_1
    //   2385: istore_2
    //   2386: aload_0
    //   2387: getfield u : Z
    //   2390: ifeq -> 2710
    //   2393: iconst_0
    //   2394: istore #4
    //   2396: iload #4
    //   2398: invokestatic e : ()I
    //   2401: if_icmpge -> 2522
    //   2404: iload #4
    //   2406: invokestatic b : (I)Ldm;
    //   2409: dup
    //   2410: astore #5
    //   2412: invokevirtual getUinString : ()Ljava/lang/String;
    //   2415: astore #6
    //   2417: aload_0
    //   2418: getfield i : Ljava/util/Hashtable;
    //   2421: aload #6
    //   2423: invokevirtual get : (Ljava/lang/Object;)Ljava/lang/Object;
    //   2426: checkcast java/lang/Integer
    //   2429: astore #7
    //   2431: aload #5
    //   2433: aload #7
    //   2435: ifnull -> 2446
    //   2438: aload #7
    //   2440: invokevirtual intValue : ()I
    //   2443: goto -> 2447
    //   2446: iconst_0
    //   2447: invokevirtual h : (I)V
    //   2450: aload_0
    //   2451: getfield j : Ljava/util/Hashtable;
    //   2454: aload #6
    //   2456: invokevirtual get : (Ljava/lang/Object;)Ljava/lang/Object;
    //   2459: checkcast java/lang/Integer
    //   2462: astore #8
    //   2464: aload #5
    //   2466: aload #8
    //   2468: ifnull -> 2479
    //   2471: aload #8
    //   2473: invokevirtual intValue : ()I
    //   2476: goto -> 2480
    //   2479: iconst_0
    //   2480: invokevirtual g : (I)V
    //   2483: aload_0
    //   2484: getfield h : Ljava/util/Hashtable;
    //   2487: aload #6
    //   2489: invokevirtual get : (Ljava/lang/Object;)Ljava/lang/Object;
    //   2492: checkcast java/lang/Integer
    //   2495: astore #9
    //   2497: aload #5
    //   2499: aload #9
    //   2501: ifnull -> 2512
    //   2504: aload #9
    //   2506: invokevirtual intValue : ()I
    //   2509: goto -> 2513
    //   2512: iconst_0
    //   2513: putfield y : I
    //   2516: iinc #4, 1
    //   2519: goto -> 2396
    //   2522: new bj
    //   2525: dup
    //   2526: bipush #19
    //   2528: bipush #7
    //   2530: ldc2_w 7
    //   2533: iconst_0
    //   2534: newarray byte
    //   2536: iconst_0
    //   2537: newarray byte
    //   2539: invokespecial <init> : (IIJ[B[B)V
    //   2542: astore #4
    //   2544: aload_0
    //   2545: getfield g : Lek;
    //   2548: aload #4
    //   2550: invokevirtual a : (Ldd;)V
    //   2553: invokestatic b : ()V
    //   2556: sipush #209
    //   2559: invokestatic f : (I)I
    //   2562: ifle -> 2586
    //   2565: new bj
    //   2568: dup
    //   2569: iconst_4
    //   2570: iconst_2
    //   2571: lconst_0
    //   2572: iconst_0
    //   2573: newarray byte
    //   2575: getstatic dk.c : [B
    //   2578: invokespecial <init> : (IIJ[B[B)V
    //   2581: astore #6
    //   2583: goto -> 2612
    //   2586: getstatic dk.c : [B
    //   2589: dup
    //   2590: astore #5
    //   2592: iconst_5
    //   2593: iconst_3
    //   2594: bastore
    //   2595: new bj
    //   2598: dup
    //   2599: iconst_4
    //   2600: iconst_2
    //   2601: lconst_0
    //   2602: iconst_0
    //   2603: newarray byte
    //   2605: aload #5
    //   2607: invokespecial <init> : (IIJ[B[B)V
    //   2610: astore #6
    //   2612: aload_0
    //   2613: getfield g : Lek;
    //   2616: aload #6
    //   2618: invokevirtual a : (Ldd;)V
    //   2621: invokestatic g : ()V
    //   2624: getstatic cp.g : Lcp;
    //   2627: iconst_4
    //   2628: aconst_null
    //   2629: aconst_null
    //   2630: sipush #20000
    //   2633: invokevirtual a : (I[Ljava/lang/Object;Ljava/lang/Object;I)Ljava/lang/Object;
    //   2636: pop
    //   2637: sipush #300
    //   2640: invokestatic i : (I)J
    //   2643: l2i
    //   2644: istore #7
    //   2646: invokestatic c : ()Li/I;
    //   2649: ifnonnull -> 2685
    //   2652: iconst_4
    //   2653: istore #8
    //   2655: iload #7
    //   2657: sipush #512
    //   2660: if_icmpne -> 2666
    //   2663: iconst_2
    //   2664: istore #8
    //   2666: iload #7
    //   2668: sipush #256
    //   2671: if_icmpne -> 2677
    //   2674: iconst_3
    //   2675: istore #8
    //   2677: iload #8
    //   2679: invokestatic a : (B)V
    //   2682: goto -> 2695
    //   2685: sipush #238
    //   2688: invokestatic f : (I)I
    //   2691: i2b
    //   2692: invokestatic a : (B)V
    //   2695: invokestatic l : ()I
    //   2698: iload #7
    //   2700: ior
    //   2701: invokestatic a : (I)V
    //   2704: aload_0
    //   2705: bipush #8
    //   2707: putfield p : I
    //   2710: goto -> 3336
    //   2713: aload_0
    //   2714: getfield p : I
    //   2717: bipush #8
    //   2719: if_icmpne -> 2787
    //   2722: new bj
    //   2725: dup
    //   2726: iconst_1
    //   2727: iconst_2
    //   2728: lconst_0
    //   2729: iconst_0
    //   2730: newarray byte
    //   2732: getstatic dk.d : [B
    //   2735: invokespecial <init> : (IIJ[B[B)V
    //   2738: astore_3
    //   2739: aload_0
    //   2740: getfield g : Lek;
    //   2743: aload_3
    //   2744: invokevirtual a : (Ldd;)V
    //   2747: new dg
    //   2750: dup
    //   2751: lconst_0
    //   2752: aload_0
    //   2753: getfield l : Ljava/lang/String;
    //   2756: bipush #60
    //   2758: iconst_0
    //   2759: newarray byte
    //   2761: iconst_0
    //   2762: newarray byte
    //   2764: invokespecial <init> : (JLjava/lang/String;I[B[B)V
    //   2767: astore #4
    //   2769: aload_0
    //   2770: getfield g : Lek;
    //   2773: aload #4
    //   2775: invokevirtual a : (Ldd;)V
    //   2778: aload_0
    //   2779: bipush #9
    //   2781: putfield p : I
    //   2784: goto -> 3336
    //   2787: aload_0
    //   2788: getfield p : I
    //   2791: bipush #9
    //   2793: if_icmpne -> 3336
    //   2796: aload_1
    //   2797: instanceof bj
    //   2800: ifeq -> 2904
    //   2803: aload_1
    //   2804: checkcast bj
    //   2807: astore_3
    //   2808: getstatic java/lang/System.out : Ljava/io/PrintStream;
    //   2811: new java/lang/StringBuffer
    //   2814: dup
    //   2815: invokespecial <init> : ()V
    //   2818: ldc 'SnPacket '
    //   2820: invokevirtual append : (Ljava/lang/String;)Ljava/lang/StringBuffer;
    //   2823: aload_3
    //   2824: getfield a : I
    //   2827: invokevirtual append : (I)Ljava/lang/StringBuffer;
    //   2830: ldc ' '
    //   2832: invokevirtual append : (Ljava/lang/String;)Ljava/lang/StringBuffer;
    //   2835: aload_3
    //   2836: getfield b : I
    //   2839: invokevirtual append : (I)Ljava/lang/StringBuffer;
    //   2842: invokevirtual toString : ()Ljava/lang/String;
    //   2845: invokevirtual println : (Ljava/lang/String;)V
    //   2848: aload_3
    //   2849: getfield a : I
    //   2852: bipush #21
    //   2854: if_icmpne -> 2873
    //   2857: aload_3
    //   2858: getfield b : I
    //   2861: iconst_1
    //   2862: if_icmpne -> 2873
    //   2865: aload_0
    //   2866: bipush #10
    //   2868: putfield p : I
    //   2871: iconst_1
    //   2872: istore_2
    //   2873: bipush #85
    //   2875: invokestatic h : (I)Z
    //   2878: ifeq -> 2904
    //   2881: aload_3
    //   2882: getfield a : I
    //   2885: iconst_3
    //   2886: if_icmpne -> 2904
    //   2889: aload_3
    //   2890: getfield b : I
    //   2893: bipush #12
    //   2895: if_icmpne -> 2904
    //   2898: aload_0
    //   2899: bipush #10
    //   2901: putfield p : I
    //   2904: aload_1
    //   2905: instanceof ex
    //   2908: ifeq -> 2960
    //   2911: iload_2
    //   2912: ifne -> 2960
    //   2915: aload_1
    //   2916: checkcast ex
    //   2919: astore_3
    //   2920: getstatic java/lang/System.out : Ljava/io/PrintStream;
    //   2923: new java/lang/StringBuffer
    //   2926: dup
    //   2927: invokespecial <init> : ()V
    //   2930: ldc 'fromIcqSrvPacket '
    //   2932: invokevirtual append : (Ljava/lang/String;)Ljava/lang/StringBuffer;
    //   2935: aload_3
    //   2936: getfield a : I
    //   2939: invokevirtual append : (I)Ljava/lang/StringBuffer;
    //   2942: ldc ' '
    //   2944: invokevirtual append : (Ljava/lang/String;)Ljava/lang/StringBuffer;
    //   2947: aload_3
    //   2948: getfield b : I
    //   2951: invokevirtual append : (I)Ljava/lang/StringBuffer;
    //   2954: invokevirtual toString : ()Ljava/lang/String;
    //   2957: invokevirtual println : (Ljava/lang/String;)V
    //   2960: aload_1
    //   2961: instanceof ex
    //   2964: ifeq -> 3336
    //   2967: iload_2
    //   2968: ifne -> 3336
    //   2971: aload_1
    //   2972: checkcast ex
    //   2975: astore_3
    //   2976: getstatic java/lang/System.out : Ljava/io/PrintStream;
    //   2979: new java/lang/StringBuffer
    //   2982: dup
    //   2983: invokespecial <init> : ()V
    //   2986: ldc '2 '
    //   2988: invokevirtual append : (Ljava/lang/String;)Ljava/lang/StringBuffer;
    //   2991: aload_3
    //   2992: getfield a : I
    //   2995: invokevirtual append : (I)Ljava/lang/StringBuffer;
    //   2998: ldc ' '
    //   3000: invokevirtual append : (Ljava/lang/String;)Ljava/lang/StringBuffer;
    //   3003: aload_3
    //   3004: getfield b : I
    //   3007: invokevirtual append : (I)Ljava/lang/StringBuffer;
    //   3010: invokevirtual toString : ()Ljava/lang/String;
    //   3013: invokevirtual println : (Ljava/lang/String;)V
    //   3016: aload_3
    //   3017: getfield a : I
    //   3020: bipush #21
    //   3022: if_icmpne -> 3336
    //   3025: aload_3
    //   3026: getfield k : I
    //   3029: bipush #65
    //   3031: if_icmpne -> 3288
    //   3034: aload_3
    //   3035: invokevirtual a : ()[B
    //   3038: dup
    //   3039: astore #4
    //   3041: arraylength
    //   3042: bipush #14
    //   3044: if_icmpge -> 3049
    //   3047: iconst_0
    //   3048: ireturn
    //   3049: aload #4
    //   3051: iconst_0
    //   3052: iconst_0
    //   3053: invokestatic b : ([BIZ)J
    //   3056: lconst_0
    //   3057: lstore #5
    //   3059: invokestatic valueOf : (J)Ljava/lang/String;
    //   3062: astore #7
    //   3064: aload #4
    //   3066: iconst_4
    //   3067: iconst_0
    //   3068: invokestatic a : ([BIZ)I
    //   3071: aload #4
    //   3073: bipush #6
    //   3075: invokestatic a : ([BI)I
    //   3078: aload #4
    //   3080: bipush #7
    //   3082: invokestatic a : ([BI)I
    //   3085: aload #4
    //   3087: bipush #8
    //   3089: invokestatic a : ([BI)I
    //   3092: aload #4
    //   3094: bipush #9
    //   3096: invokestatic a : ([BI)I
    //   3099: iconst_0
    //   3100: invokestatic a : (IIIIII)J
    //   3103: lstore #8
    //   3105: aload #4
    //   3107: bipush #10
    //   3109: iconst_0
    //   3110: invokestatic a : ([BIZ)I
    //   3113: istore #10
    //   3115: aload #4
    //   3117: bipush #12
    //   3119: iconst_0
    //   3120: invokestatic a : ([BIZ)I
    //   3123: istore #11
    //   3125: aconst_null
    //   3126: astore #12
    //   3128: aload #4
    //   3130: arraylength
    //   3131: bipush #14
    //   3133: iload #11
    //   3135: iadd
    //   3136: if_icmplt -> 3162
    //   3139: aload #4
    //   3141: bipush #14
    //   3143: iload #11
    //   3145: aload #4
    //   3147: bipush #14
    //   3149: iload #11
    //   3151: invokestatic f : ([BII)Z
    //   3154: invokestatic b : ([BIIZ)Ljava/lang/String;
    //   3157: invokestatic c : (Ljava/lang/String;)Ljava/lang/String;
    //   3160: astore #12
    //   3162: aload #12
    //   3164: ifnonnull -> 3170
    //   3167: goto -> 3283
    //   3170: iload #10
    //   3172: iconst_1
    //   3173: if_icmpne -> 3204
    //   3176: new ce
    //   3179: dup
    //   3180: aload #7
    //   3182: aload #7
    //   3184: lload #8
    //   3186: invokestatic b : (J)J
    //   3189: aload #12
    //   3191: iconst_1
    //   3192: invokespecial <init> : (Ljava/lang/String;Ljava/lang/String;JLjava/lang/String;Z)V
    //   3195: aconst_null
    //   3196: astore #13
    //   3198: invokestatic a : (Lej;)V
    //   3201: goto -> 3283
    //   3204: iload #10
    //   3206: iconst_4
    //   3207: if_icmpne -> 3283
    //   3210: aload #12
    //   3212: sipush #254
    //   3215: invokevirtual indexOf : (I)I
    //   3218: dup
    //   3219: istore #13
    //   3221: iconst_m1
    //   3222: if_icmpeq -> 3249
    //   3225: aload #12
    //   3227: iconst_0
    //   3228: iload #13
    //   3230: invokevirtual substring : (II)Ljava/lang/String;
    //   3233: astore #14
    //   3235: aload #12
    //   3237: iload #13
    //   3239: iconst_1
    //   3240: iadd
    //   3241: invokevirtual substring : (I)Ljava/lang/String;
    //   3244: astore #15
    //   3246: goto -> 3257
    //   3249: aload #12
    //   3251: astore #14
    //   3253: ldc ''
    //   3255: astore #15
    //   3257: new bp
    //   3260: dup
    //   3261: aload #7
    //   3263: aload #7
    //   3265: lload #8
    //   3267: invokestatic b : (J)J
    //   3270: aload #15
    //   3272: aload #14
    //   3274: invokespecial <init> : (Ljava/lang/String;Ljava/lang/String;JLjava/lang/String;Ljava/lang/String;)V
    //   3277: aconst_null
    //   3278: astore #16
    //   3280: invokestatic a : (Lej;)V
    //   3283: iconst_1
    //   3284: istore_2
    //   3285: goto -> 3336
    //   3288: aload_3
    //   3289: getfield k : I
    //   3292: bipush #66
    //   3294: if_icmpne -> 3336
    //   3297: new dg
    //   3300: dup
    //   3301: lconst_0
    //   3302: aload_0
    //   3303: getfield l : Ljava/lang/String;
    //   3306: bipush #62
    //   3308: iconst_0
    //   3309: newarray byte
    //   3311: iconst_0
    //   3312: newarray byte
    //   3314: invokespecial <init> : (JLjava/lang/String;I[B[B)V
    //   3317: astore #4
    //   3319: aload_0
    //   3320: getfield g : Lek;
    //   3323: aload #4
    //   3325: invokevirtual a : (Ldd;)V
    //   3328: aload_0
    //   3329: bipush #10
    //   3331: putfield p : I
    //   3334: iconst_1
    //   3335: istore_2
    //   3336: aload_0
    //   3337: invokestatic currentTimeMillis : ()J
    //   3340: putfield q : J
    //   3343: aload_0
    //   3344: iconst_0
    //   3345: putfield r : Z
    //   3348: iload_2
    //   3349: ireturn
    //   3350: astore_2
    //   3351: aload_0
    //   3352: invokestatic currentTimeMillis : ()J
    //   3355: putfield q : J
    //   3358: aload_0
    //   3359: iconst_0
    //   3360: putfield r : Z
    //   3363: aload_2
    //   3364: getfield a : Z
    //   3367: ifeq -> 3375
    //   3370: aload_0
    //   3371: iconst_m1
    //   3372: putfield p : I
    //   3375: aload_2
    //   3376: athrow
    // Exception table:
    //   from	to	target	type
    //   24	3048	3350	cr
    //   1968	2052	2055	java/lang/NumberFormatException
    //   1968	2052	2059	java/lang/Exception
    //   3049	3349	3350	cr
  }
  
  public final boolean c() {
    return (this.p == 10);
  }
  
  public final boolean d() {
    if (this.k || this.g != cd.i)
      return true; 
    if (this.p != -1 && !this.r && this.q + this.f < System.currentTimeMillis()) {
      cr cr;
      if (!cd.a(cr = new cr((short)606, 118, 0)))
        cr.a(cr); 
      this.p = -1;
    } 
    return (this.p == -1);
  }
  
  public final int e() {
    switch (this.p) {
      case 0:
        return 3;
      case 1:
        return 12;
      case 2:
        return 20;
      case 3:
        return 32;
      case 4:
        return 45;
      case 5:
        return 57;
      case 6:
        return 64;
      case 7:
        return 71;
      case 8:
        return 79;
      case 9:
        return 87;
      case 10:
        return 100;
    } 
    return 0;
  }
  
  public final String f() {
    switch (this.p) {
      case 2:
        return bb.a((short)745);
      case 3:
        return bb.a((short)746);
      case 4:
        return bb.a((short)747);
      case 5:
        return bb.a((short)748);
      case 6:
      case 7:
        return bb.a((short)749);
      case 8:
        return bb.a((short)750);
      case 9:
        return bb.a((short)751);
      case 10:
        return bb.a((short)752);
    } 
    return this.n;
  }
  
  public final void a(int paramInt) {
    switch (paramInt) {
      case 1:
        bi.i();
        bi.r();
        if (em.h(29))
          ew.a(); 
        if (em.f(241) != 0)
          ew.c(); 
        if (em.h(75)) {
          ew.b();
          return;
        } 
        break;
      case 2:
        cd.m = false;
        this.k = true;
        cd.d();
        fb.c();
        break;
    } 
  }
}


/* Location:              D:\Desktop\kemulator\LocID_BitByByte.jar!\dk.class
 * Java compiler version: 1 (45.3)
 * JD-Core Version:       1.1.3
 */