package KD;

import javax.microedition.lcdui.Command;
import javax.microedition.lcdui.CommandListener;
import javax.microedition.lcdui.Displayable;
import javax.microedition.lcdui.Image;
import javax.microedition.lcdui.List;

public final class d implements CommandListener {
  public ae a;
  
  public int b = 0;
  
  public int c = 0;
  
  public String d = null;
  
  public int e = 0;
  
  public String f = null;
  
  public int[] g = null;
  
  private Command S;
  
  private Command T;
  
  private Command U;
  
  private Command V;
  
  private Command W;
  
  private h X;
  
  private ah Y;
  
  public ab h;
  
  public a i;
  
  public x j;
  
  public int k = 1;
  
  public Command l;
  
  public z m;
  
  public Command n;
  
  public Command o;
  
  public Command p;
  
  public Command q;
  
  public Command r;
  
  public Command s;
  
  public w t;
  
  public aj u;
  
  public Command v;
  
  public Command w;
  
  public Command x;
  
  public int y = 0;
  
  public p z;
  
  public Command A;
  
  public Command B;
  
  public Command C;
  
  public Command D;
  
  public Command E;
  
  public Command F;
  
  public r G;
  
  public Command H;
  
  public Command I;
  
  private g Z;
  
  private am aa;
  
  public q J;
  
  private j ab;
  
  private Command ac;
  
  private o ad;
  
  private Command ae;
  
  public ai K;
  
  public ak L;
  
  public Command M;
  
  public Command N;
  
  public Command O;
  
  public Command P;
  
  public Command Q;
  
  public List R;
  
  public d(ae paramae) {
    this.a = paramae;
    this.T = new Command("Выбрать", 4, 0);
    this.U = new Command("Информация", 4, 1);
    this.V = new Command("Воспроизвести", 4, 2);
    this.S = new Command("Назад", 2, 3);
    this.W = new Command("Выход", 7, 1);
    this.l = new Command("", 4, 0);
  }
  
  public final void a() {
    if (this.b != 0) {
      if (this.b == 1) {
        d();
        return;
      } 
      if (this.b == 2) {
        this.a.e();
        s();
        return;
      } 
      if (this.b == 4) {
        this.a.e();
        A();
        return;
      } 
      if (this.b == 3) {
        f();
        return;
      } 
      if (this.b == 5) {
        h();
        return;
      } 
      if (this.b == 6) {
        this.a.e();
        n();
        return;
      } 
      if (this.b == 7) {
        this.a.e();
        o();
        return;
      } 
      if (this.b == 8) {
        this.a.e();
        q();
        return;
      } 
      if (this.b == 20) {
        this.a.e();
        t();
        return;
      } 
      if (this.b == 21) {
        this.a.e();
        x();
        return;
      } 
      if (this.b == 22) {
        this.a.e();
        y();
        return;
      } 
      if (this.b == 23) {
        this.a.e();
        v();
        return;
      } 
      if (this.b == 14) {
        R();
        return;
      } 
      if (this.b == 15) {
        this.a.e();
        T();
        return;
      } 
      if (this.b == 16) {
        j();
        return;
      } 
      if (this.b == 24) {
        C();
        return;
      } 
      if (this.b == 25) {
        this.a.e();
        F();
        return;
      } 
      if (this.b == 26) {
        E();
        return;
      } 
      if (this.b == 27) {
        H();
        return;
      } 
      if (this.b == 28) {
        L();
        return;
      } 
      if (this.b == 17) {
        P();
        return;
      } 
      if (this.b == 18) {
        this.a.e();
        N();
        return;
      } 
      if (this.b == 19) {
        l();
        return;
      } 
      this.b = 0;
    } 
    b();
  }
  
  public final void commandAction(Command paramCommand, Displayable paramDisplayable) {
    // Byte code:
    //   0: aload_1
    //   1: aload_0
    //   2: getfield W : Ljavax/microedition/lcdui/Command;
    //   5: if_acmpne -> 16
    //   8: aload_0
    //   9: getfield a : LKD/ae;
    //   12: invokevirtual i : ()V
    //   15: return
    //   16: aload_1
    //   17: aload_0
    //   18: getfield T : Ljavax/microedition/lcdui/Command;
    //   21: if_acmpne -> 575
    //   24: iconst_0
    //   25: istore_3
    //   26: aload_0
    //   27: getfield b : I
    //   30: ifne -> 79
    //   33: aload_0
    //   34: getfield h : LKD/ab;
    //   37: invokevirtual getSelectedIndex : ()I
    //   40: dup
    //   41: istore_3
    //   42: ifne -> 59
    //   45: aload_0
    //   46: getfield a : LKD/ae;
    //   49: invokevirtual g : ()V
    //   52: aload_0
    //   53: invokespecial c : ()V
    //   56: goto -> 3237
    //   59: iload_3
    //   60: ifle -> 574
    //   63: aload_0
    //   64: iload_3
    //   65: putfield b : I
    //   68: aload_0
    //   69: invokevirtual a : ()V
    //   72: aload_0
    //   73: invokespecial c : ()V
    //   76: goto -> 3237
    //   79: aload_0
    //   80: getfield b : I
    //   83: iconst_1
    //   84: if_icmpne -> 118
    //   87: aload_0
    //   88: getfield i : LKD/a;
    //   91: invokevirtual getSelectedIndex : ()I
    //   94: dup
    //   95: istore_3
    //   96: iflt -> 574
    //   99: aload_0
    //   100: bipush #6
    //   102: iload_3
    //   103: iadd
    //   104: putfield b : I
    //   107: aload_0
    //   108: invokevirtual a : ()V
    //   111: aload_0
    //   112: invokespecial e : ()V
    //   115: goto -> 3237
    //   118: aload_0
    //   119: getfield b : I
    //   122: iconst_3
    //   123: if_icmpne -> 157
    //   126: aload_0
    //   127: getfield j : LKD/x;
    //   130: invokevirtual getSelectedIndex : ()I
    //   133: dup
    //   134: istore_3
    //   135: iflt -> 574
    //   138: aload_0
    //   139: bipush #14
    //   141: iload_3
    //   142: iadd
    //   143: putfield b : I
    //   146: aload_0
    //   147: invokevirtual a : ()V
    //   150: aload_0
    //   151: invokespecial g : ()V
    //   154: goto -> 3237
    //   157: aload_0
    //   158: getfield b : I
    //   161: iconst_5
    //   162: if_icmpne -> 196
    //   165: aload_0
    //   166: getfield J : LKD/q;
    //   169: invokevirtual getSelectedIndex : ()I
    //   172: dup
    //   173: istore_3
    //   174: iflt -> 574
    //   177: aload_0
    //   178: bipush #17
    //   180: iload_3
    //   181: iadd
    //   182: putfield b : I
    //   185: aload_0
    //   186: invokevirtual a : ()V
    //   189: aload_0
    //   190: invokespecial i : ()V
    //   193: goto -> 3237
    //   196: aload_0
    //   197: getfield b : I
    //   200: bipush #6
    //   202: if_icmpne -> 209
    //   205: iconst_1
    //   206: goto -> 210
    //   209: iconst_0
    //   210: aload_0
    //   211: getfield b : I
    //   214: iconst_2
    //   215: if_icmpne -> 222
    //   218: iconst_1
    //   219: goto -> 223
    //   222: iconst_0
    //   223: ior
    //   224: ifeq -> 270
    //   227: aload_0
    //   228: getfield R : Ljavax/microedition/lcdui/List;
    //   231: invokevirtual getSelectedIndex : ()I
    //   234: dup
    //   235: istore_3
    //   236: iflt -> 574
    //   239: aload_0
    //   240: getfield a : LKD/ae;
    //   243: invokevirtual e : ()V
    //   246: aload_0
    //   247: invokespecial z : ()V
    //   250: aload_0
    //   251: getfield a : LKD/ae;
    //   254: getfield e : LKD/b;
    //   257: aload_0
    //   258: getfield a : LKD/ae;
    //   261: getfield c : LKD/i;
    //   264: getfield e : [I
    //   267: goto -> 552
    //   270: aload_0
    //   271: getfield b : I
    //   274: bipush #7
    //   276: if_icmpne -> 330
    //   279: aload_0
    //   280: getfield R : Ljavax/microedition/lcdui/List;
    //   283: invokevirtual getSelectedIndex : ()I
    //   286: dup
    //   287: istore_3
    //   288: iflt -> 574
    //   291: aload_0
    //   292: aconst_null
    //   293: putfield d : Ljava/lang/String;
    //   296: aload_0
    //   297: aload_0
    //   298: getfield R : Ljavax/microedition/lcdui/List;
    //   301: iload_3
    //   302: invokevirtual getString : (I)Ljava/lang/String;
    //   305: putfield d : Ljava/lang/String;
    //   308: aload_0
    //   309: iload_3
    //   310: putfield c : I
    //   313: aload_0
    //   314: bipush #20
    //   316: putfield b : I
    //   319: aload_0
    //   320: invokespecial r : ()V
    //   323: aload_0
    //   324: invokevirtual a : ()V
    //   327: goto -> 3237
    //   330: aload_0
    //   331: getfield b : I
    //   334: bipush #20
    //   336: if_icmpne -> 411
    //   339: aload_0
    //   340: getfield R : Ljavax/microedition/lcdui/List;
    //   343: invokevirtual getSelectedIndex : ()I
    //   346: dup
    //   347: istore_3
    //   348: ifne -> 368
    //   351: aload_0
    //   352: bipush #21
    //   354: putfield b : I
    //   357: aload_0
    //   358: invokespecial z : ()V
    //   361: aload_0
    //   362: invokevirtual a : ()V
    //   365: goto -> 3237
    //   368: iload_3
    //   369: ifle -> 574
    //   372: aload_0
    //   373: aconst_null
    //   374: putfield f : Ljava/lang/String;
    //   377: aload_0
    //   378: aload_0
    //   379: getfield R : Ljavax/microedition/lcdui/List;
    //   382: iload_3
    //   383: invokevirtual getString : (I)Ljava/lang/String;
    //   386: putfield f : Ljava/lang/String;
    //   389: aload_0
    //   390: iload_3
    //   391: putfield e : I
    //   394: aload_0
    //   395: bipush #22
    //   397: putfield b : I
    //   400: aload_0
    //   401: invokespecial z : ()V
    //   404: aload_0
    //   405: invokevirtual a : ()V
    //   408: goto -> 3237
    //   411: aload_0
    //   412: getfield b : I
    //   415: bipush #8
    //   417: if_icmpne -> 471
    //   420: aload_0
    //   421: getfield R : Ljavax/microedition/lcdui/List;
    //   424: invokevirtual getSelectedIndex : ()I
    //   427: dup
    //   428: istore_3
    //   429: iflt -> 574
    //   432: aload_0
    //   433: aconst_null
    //   434: putfield f : Ljava/lang/String;
    //   437: aload_0
    //   438: aload_0
    //   439: getfield R : Ljavax/microedition/lcdui/List;
    //   442: iload_3
    //   443: invokevirtual getString : (I)Ljava/lang/String;
    //   446: putfield f : Ljava/lang/String;
    //   449: aload_0
    //   450: iload_3
    //   451: putfield e : I
    //   454: aload_0
    //   455: bipush #23
    //   457: putfield b : I
    //   460: aload_0
    //   461: invokespecial p : ()V
    //   464: aload_0
    //   465: invokevirtual a : ()V
    //   468: goto -> 3237
    //   471: aload_0
    //   472: getfield b : I
    //   475: bipush #23
    //   477: if_icmpne -> 484
    //   480: iconst_1
    //   481: goto -> 485
    //   484: iconst_0
    //   485: aload_0
    //   486: getfield b : I
    //   489: bipush #21
    //   491: if_icmpne -> 498
    //   494: iconst_1
    //   495: goto -> 499
    //   498: iconst_0
    //   499: ior
    //   500: aload_0
    //   501: getfield b : I
    //   504: bipush #22
    //   506: if_icmpne -> 513
    //   509: iconst_1
    //   510: goto -> 514
    //   513: iconst_0
    //   514: ior
    //   515: ifeq -> 574
    //   518: aload_0
    //   519: getfield R : Ljavax/microedition/lcdui/List;
    //   522: invokevirtual getSelectedIndex : ()I
    //   525: dup
    //   526: istore_3
    //   527: iflt -> 574
    //   530: aload_0
    //   531: getfield a : LKD/ae;
    //   534: invokevirtual e : ()V
    //   537: aload_0
    //   538: invokespecial z : ()V
    //   541: aload_0
    //   542: getfield a : LKD/ae;
    //   545: getfield e : LKD/b;
    //   548: aload_0
    //   549: getfield g : [I
    //   552: invokevirtual a : ([I)V
    //   555: aload_0
    //   556: getfield a : LKD/ae;
    //   559: getfield e : LKD/b;
    //   562: iload_3
    //   563: iconst_1
    //   564: invokevirtual a : (IZ)V
    //   567: aload_0
    //   568: getfield a : LKD/ae;
    //   571: invokevirtual g : ()V
    //   574: return
    //   575: aload_1
    //   576: aload_0
    //   577: getfield S : Ljavax/microedition/lcdui/Command;
    //   580: if_acmpne -> 1257
    //   583: aload_0
    //   584: getfield b : I
    //   587: iconst_1
    //   588: if_icmpne -> 614
    //   591: aload_0
    //   592: iconst_0
    //   593: putfield b : I
    //   596: aload_0
    //   597: invokevirtual a : ()V
    //   600: aload_0
    //   601: getfield h : LKD/ab;
    //   604: iconst_1
    //   605: iconst_1
    //   606: invokevirtual setSelectedIndex : (IZ)V
    //   609: aload_0
    //   610: invokespecial e : ()V
    //   613: return
    //   614: aload_0
    //   615: getfield b : I
    //   618: iconst_2
    //   619: if_icmpne -> 645
    //   622: aload_0
    //   623: iconst_0
    //   624: putfield b : I
    //   627: aload_0
    //   628: invokevirtual a : ()V
    //   631: aload_0
    //   632: getfield h : LKD/ab;
    //   635: iconst_2
    //   636: iconst_1
    //   637: invokevirtual setSelectedIndex : (IZ)V
    //   640: aload_0
    //   641: invokespecial z : ()V
    //   644: return
    //   645: aload_0
    //   646: getfield b : I
    //   649: iconst_3
    //   650: if_icmpne -> 676
    //   653: aload_0
    //   654: iconst_0
    //   655: putfield b : I
    //   658: aload_0
    //   659: invokevirtual a : ()V
    //   662: aload_0
    //   663: getfield h : LKD/ab;
    //   666: iconst_3
    //   667: iconst_1
    //   668: invokevirtual setSelectedIndex : (IZ)V
    //   671: aload_0
    //   672: invokespecial g : ()V
    //   675: return
    //   676: aload_0
    //   677: getfield b : I
    //   680: iconst_4
    //   681: if_icmpne -> 707
    //   684: aload_0
    //   685: iconst_0
    //   686: putfield b : I
    //   689: aload_0
    //   690: invokevirtual a : ()V
    //   693: aload_0
    //   694: getfield h : LKD/ab;
    //   697: iconst_4
    //   698: iconst_1
    //   699: invokevirtual setSelectedIndex : (IZ)V
    //   702: aload_0
    //   703: invokespecial B : ()V
    //   706: return
    //   707: aload_0
    //   708: getfield b : I
    //   711: iconst_5
    //   712: if_icmpne -> 738
    //   715: aload_0
    //   716: iconst_0
    //   717: putfield b : I
    //   720: aload_0
    //   721: invokevirtual a : ()V
    //   724: aload_0
    //   725: getfield h : LKD/ab;
    //   728: iconst_5
    //   729: iconst_1
    //   730: invokevirtual setSelectedIndex : (IZ)V
    //   733: aload_0
    //   734: invokespecial i : ()V
    //   737: return
    //   738: aload_0
    //   739: getfield b : I
    //   742: bipush #14
    //   744: if_icmpne -> 770
    //   747: aload_0
    //   748: iconst_3
    //   749: putfield b : I
    //   752: aload_0
    //   753: invokevirtual a : ()V
    //   756: aload_0
    //   757: getfield j : LKD/x;
    //   760: iconst_0
    //   761: iconst_1
    //   762: invokevirtual setSelectedIndex : (IZ)V
    //   765: aload_0
    //   766: invokespecial S : ()V
    //   769: return
    //   770: aload_0
    //   771: getfield b : I
    //   774: bipush #15
    //   776: if_icmpne -> 802
    //   779: aload_0
    //   780: iconst_3
    //   781: putfield b : I
    //   784: aload_0
    //   785: invokevirtual a : ()V
    //   788: aload_0
    //   789: getfield j : LKD/x;
    //   792: iconst_1
    //   793: iconst_1
    //   794: invokevirtual setSelectedIndex : (IZ)V
    //   797: aload_0
    //   798: invokespecial U : ()V
    //   801: return
    //   802: aload_0
    //   803: getfield b : I
    //   806: bipush #16
    //   808: if_icmpne -> 834
    //   811: aload_0
    //   812: iconst_3
    //   813: putfield b : I
    //   816: aload_0
    //   817: invokevirtual a : ()V
    //   820: aload_0
    //   821: getfield j : LKD/x;
    //   824: iconst_2
    //   825: iconst_1
    //   826: invokevirtual setSelectedIndex : (IZ)V
    //   829: aload_0
    //   830: invokespecial k : ()V
    //   833: return
    //   834: aload_0
    //   835: getfield b : I
    //   838: bipush #17
    //   840: if_icmpne -> 866
    //   843: aload_0
    //   844: iconst_5
    //   845: putfield b : I
    //   848: aload_0
    //   849: invokevirtual a : ()V
    //   852: aload_0
    //   853: getfield J : LKD/q;
    //   856: iconst_0
    //   857: iconst_1
    //   858: invokevirtual setSelectedIndex : (IZ)V
    //   861: aload_0
    //   862: invokespecial Q : ()V
    //   865: return
    //   866: aload_0
    //   867: getfield b : I
    //   870: bipush #18
    //   872: if_icmpne -> 898
    //   875: aload_0
    //   876: iconst_5
    //   877: putfield b : I
    //   880: aload_0
    //   881: invokevirtual a : ()V
    //   884: aload_0
    //   885: getfield J : LKD/q;
    //   888: iconst_1
    //   889: iconst_1
    //   890: invokevirtual setSelectedIndex : (IZ)V
    //   893: aload_0
    //   894: invokespecial O : ()V
    //   897: return
    //   898: aload_0
    //   899: getfield b : I
    //   902: bipush #19
    //   904: if_icmpne -> 930
    //   907: aload_0
    //   908: iconst_5
    //   909: putfield b : I
    //   912: aload_0
    //   913: invokevirtual a : ()V
    //   916: aload_0
    //   917: getfield J : LKD/q;
    //   920: iconst_2
    //   921: iconst_1
    //   922: invokevirtual setSelectedIndex : (IZ)V
    //   925: aload_0
    //   926: invokespecial m : ()V
    //   929: return
    //   930: aload_0
    //   931: getfield b : I
    //   934: bipush #6
    //   936: if_icmpne -> 962
    //   939: aload_0
    //   940: iconst_1
    //   941: putfield b : I
    //   944: aload_0
    //   945: invokevirtual a : ()V
    //   948: aload_0
    //   949: getfield i : LKD/a;
    //   952: iconst_0
    //   953: iconst_1
    //   954: invokevirtual setSelectedIndex : (IZ)V
    //   957: aload_0
    //   958: invokespecial z : ()V
    //   961: return
    //   962: aload_0
    //   963: getfield b : I
    //   966: bipush #7
    //   968: if_icmpne -> 994
    //   971: aload_0
    //   972: iconst_1
    //   973: putfield b : I
    //   976: aload_0
    //   977: invokevirtual a : ()V
    //   980: aload_0
    //   981: getfield i : LKD/a;
    //   984: iconst_1
    //   985: iconst_1
    //   986: invokevirtual setSelectedIndex : (IZ)V
    //   989: aload_0
    //   990: invokespecial p : ()V
    //   993: return
    //   994: aload_0
    //   995: getfield b : I
    //   998: bipush #8
    //   1000: if_icmpne -> 1026
    //   1003: aload_0
    //   1004: iconst_1
    //   1005: putfield b : I
    //   1008: aload_0
    //   1009: invokevirtual a : ()V
    //   1012: aload_0
    //   1013: getfield i : LKD/a;
    //   1016: iconst_2
    //   1017: iconst_1
    //   1018: invokevirtual setSelectedIndex : (IZ)V
    //   1021: aload_0
    //   1022: invokespecial r : ()V
    //   1025: return
    //   1026: aload_0
    //   1027: getfield b : I
    //   1030: bipush #20
    //   1032: if_icmpne -> 1067
    //   1035: aload_0
    //   1036: aconst_null
    //   1037: putfield d : Ljava/lang/String;
    //   1040: aload_0
    //   1041: bipush #7
    //   1043: putfield b : I
    //   1046: aload_0
    //   1047: invokespecial u : ()V
    //   1050: aload_0
    //   1051: invokevirtual a : ()V
    //   1054: aload_0
    //   1055: getfield R : Ljavax/microedition/lcdui/List;
    //   1058: aload_0
    //   1059: getfield c : I
    //   1062: iconst_1
    //   1063: invokevirtual setSelectedIndex : (IZ)V
    //   1066: return
    //   1067: aload_0
    //   1068: getfield b : I
    //   1071: bipush #21
    //   1073: if_icmpne -> 1091
    //   1076: aload_0
    //   1077: bipush #20
    //   1079: putfield b : I
    //   1082: aload_0
    //   1083: invokespecial z : ()V
    //   1086: aload_0
    //   1087: invokevirtual a : ()V
    //   1090: return
    //   1091: aload_0
    //   1092: getfield b : I
    //   1095: bipush #22
    //   1097: if_icmpne -> 1132
    //   1100: aload_0
    //   1101: aconst_null
    //   1102: putfield f : Ljava/lang/String;
    //   1105: aload_0
    //   1106: bipush #20
    //   1108: putfield b : I
    //   1111: aload_0
    //   1112: invokespecial z : ()V
    //   1115: aload_0
    //   1116: invokevirtual a : ()V
    //   1119: aload_0
    //   1120: getfield R : Ljavax/microedition/lcdui/List;
    //   1123: aload_0
    //   1124: getfield e : I
    //   1127: iconst_1
    //   1128: invokevirtual setSelectedIndex : (IZ)V
    //   1131: return
    //   1132: aload_0
    //   1133: getfield b : I
    //   1136: bipush #23
    //   1138: if_icmpne -> 1173
    //   1141: aload_0
    //   1142: aconst_null
    //   1143: putfield f : Ljava/lang/String;
    //   1146: aload_0
    //   1147: bipush #8
    //   1149: putfield b : I
    //   1152: aload_0
    //   1153: invokespecial w : ()V
    //   1156: aload_0
    //   1157: invokevirtual a : ()V
    //   1160: aload_0
    //   1161: getfield R : Ljavax/microedition/lcdui/List;
    //   1164: aload_0
    //   1165: getfield e : I
    //   1168: iconst_1
    //   1169: invokevirtual setSelectedIndex : (IZ)V
    //   1172: return
    //   1173: aload_0
    //   1174: getfield b : I
    //   1177: bipush #25
    //   1179: if_icmpne -> 1215
    //   1182: aload_0
    //   1183: iconst_4
    //   1184: putfield b : I
    //   1187: aload_0
    //   1188: invokevirtual a : ()V
    //   1191: aload_0
    //   1192: invokespecial G : ()V
    //   1195: aload_0
    //   1196: getfield k : I
    //   1199: ifle -> 3237
    //   1202: aload_0
    //   1203: getfield m : LKD/z;
    //   1206: aload_0
    //   1207: getfield k : I
    //   1210: iconst_1
    //   1211: invokevirtual setSelectedIndex : (IZ)V
    //   1214: return
    //   1215: aload_0
    //   1216: getfield b : I
    //   1219: bipush #27
    //   1221: if_icmpne -> 3237
    //   1224: aload_0
    //   1225: iconst_4
    //   1226: putfield b : I
    //   1229: aload_0
    //   1230: invokevirtual a : ()V
    //   1233: aload_0
    //   1234: invokespecial I : ()V
    //   1237: aload_0
    //   1238: getfield k : I
    //   1241: ifle -> 3237
    //   1244: aload_0
    //   1245: getfield m : LKD/z;
    //   1248: aload_0
    //   1249: getfield k : I
    //   1252: iconst_1
    //   1253: invokevirtual setSelectedIndex : (IZ)V
    //   1256: return
    //   1257: aload_1
    //   1258: aload_0
    //   1259: getfield U : Ljavax/microedition/lcdui/Command;
    //   1262: if_acmpne -> 1525
    //   1265: iconst_0
    //   1266: istore_3
    //   1267: aload_0
    //   1268: getfield b : I
    //   1271: iconst_2
    //   1272: if_icmpne -> 1279
    //   1275: iconst_1
    //   1276: goto -> 1280
    //   1279: iconst_0
    //   1280: aload_0
    //   1281: getfield b : I
    //   1284: bipush #6
    //   1286: if_icmpne -> 1293
    //   1289: iconst_1
    //   1290: goto -> 1294
    //   1293: iconst_0
    //   1294: ior
    //   1295: ifeq -> 1332
    //   1298: aload_0
    //   1299: getfield R : Ljavax/microedition/lcdui/List;
    //   1302: invokevirtual getSelectedIndex : ()I
    //   1305: dup
    //   1306: istore_3
    //   1307: iflt -> 1524
    //   1310: aload_0
    //   1311: aload_0
    //   1312: getfield a : LKD/ae;
    //   1315: getfield c : LKD/i;
    //   1318: getfield e : [I
    //   1321: putfield g : [I
    //   1324: aload_0
    //   1325: iload_3
    //   1326: invokespecial a : (I)V
    //   1329: goto -> 3237
    //   1332: aload_0
    //   1333: getfield b : I
    //   1336: bipush #23
    //   1338: if_icmpne -> 1345
    //   1341: iconst_1
    //   1342: goto -> 1346
    //   1345: iconst_0
    //   1346: aload_0
    //   1347: getfield b : I
    //   1350: bipush #22
    //   1352: if_icmpne -> 1359
    //   1355: iconst_1
    //   1356: goto -> 1360
    //   1359: iconst_0
    //   1360: ior
    //   1361: aload_0
    //   1362: getfield b : I
    //   1365: bipush #21
    //   1367: if_icmpne -> 1374
    //   1370: iconst_1
    //   1371: goto -> 1375
    //   1374: iconst_0
    //   1375: ior
    //   1376: ifeq -> 1399
    //   1379: aload_0
    //   1380: getfield R : Ljavax/microedition/lcdui/List;
    //   1383: invokevirtual getSelectedIndex : ()I
    //   1386: dup
    //   1387: istore_3
    //   1388: iflt -> 1524
    //   1391: aload_0
    //   1392: iload_3
    //   1393: invokespecial a : (I)V
    //   1396: goto -> 3237
    //   1399: aload_0
    //   1400: getfield b : I
    //   1403: bipush #7
    //   1405: if_icmpne -> 1439
    //   1408: aload_0
    //   1409: getfield R : Ljavax/microedition/lcdui/List;
    //   1412: invokevirtual getSelectedIndex : ()I
    //   1415: dup
    //   1416: istore_3
    //   1417: iflt -> 1524
    //   1420: aload_0
    //   1421: aload_0
    //   1422: getfield R : Ljavax/microedition/lcdui/List;
    //   1425: iload_3
    //   1426: invokevirtual getString : (I)Ljava/lang/String;
    //   1429: putfield d : Ljava/lang/String;
    //   1432: aload_0
    //   1433: invokespecial K : ()V
    //   1436: goto -> 3237
    //   1439: aload_0
    //   1440: getfield b : I
    //   1443: bipush #8
    //   1445: if_icmpne -> 1477
    //   1448: aload_0
    //   1449: getfield R : Ljavax/microedition/lcdui/List;
    //   1452: invokevirtual getSelectedIndex : ()I
    //   1455: dup
    //   1456: istore_3
    //   1457: iflt -> 1524
    //   1460: aload_0
    //   1461: aload_0
    //   1462: getfield R : Ljavax/microedition/lcdui/List;
    //   1465: iload_3
    //   1466: invokevirtual getString : (I)Ljava/lang/String;
    //   1469: putfield f : Ljava/lang/String;
    //   1472: aload_0
    //   1473: iconst_1
    //   1474: goto -> 1520
    //   1477: aload_0
    //   1478: getfield b : I
    //   1481: bipush #20
    //   1483: if_icmpne -> 1524
    //   1486: aload_0
    //   1487: getfield R : Ljavax/microedition/lcdui/List;
    //   1490: invokevirtual getSelectedIndex : ()I
    //   1493: dup
    //   1494: istore_3
    //   1495: iflt -> 1524
    //   1498: aload_0
    //   1499: aload_0
    //   1500: getfield R : Ljavax/microedition/lcdui/List;
    //   1503: iload_3
    //   1504: invokevirtual getString : (I)Ljava/lang/String;
    //   1507: putfield f : Ljava/lang/String;
    //   1510: aload_0
    //   1511: iconst_2
    //   1512: iload_3
    //   1513: ifne -> 1520
    //   1516: iconst_1
    //   1517: goto -> 1521
    //   1520: iconst_0
    //   1521: invokespecial a : (IZ)V
    //   1524: return
    //   1525: aload_1
    //   1526: aload_0
    //   1527: getfield V : Ljavax/microedition/lcdui/Command;
    //   1530: if_acmpne -> 1955
    //   1533: aload_0
    //   1534: getfield b : I
    //   1537: iconst_1
    //   1538: if_icmpne -> 1612
    //   1541: aload_0
    //   1542: getfield a : LKD/ae;
    //   1545: getfield c : LKD/i;
    //   1548: invokevirtual c : ()[Ljava/lang/String;
    //   1551: dup
    //   1552: astore_3
    //   1553: ifnull -> 1611
    //   1556: aload_3
    //   1557: arraylength
    //   1558: ifle -> 1611
    //   1561: aload_0
    //   1562: getfield a : LKD/ae;
    //   1565: invokevirtual e : ()V
    //   1568: aload_0
    //   1569: invokespecial e : ()V
    //   1572: aload_0
    //   1573: getfield a : LKD/ae;
    //   1576: getfield e : LKD/b;
    //   1579: aload_0
    //   1580: getfield a : LKD/ae;
    //   1583: getfield c : LKD/i;
    //   1586: getfield e : [I
    //   1589: invokevirtual a : ([I)V
    //   1592: aload_0
    //   1593: getfield a : LKD/ae;
    //   1596: getfield e : LKD/b;
    //   1599: iconst_0
    //   1600: iconst_1
    //   1601: invokevirtual a : (IZ)V
    //   1604: aload_0
    //   1605: getfield a : LKD/ae;
    //   1608: invokevirtual g : ()V
    //   1611: return
    //   1612: aload_0
    //   1613: getfield b : I
    //   1616: bipush #7
    //   1618: if_icmpne -> 1717
    //   1621: aload_0
    //   1622: getfield R : Ljavax/microedition/lcdui/List;
    //   1625: invokevirtual getSelectedIndex : ()I
    //   1628: dup
    //   1629: istore_3
    //   1630: iflt -> 1716
    //   1633: aload_0
    //   1634: aload_0
    //   1635: getfield R : Ljavax/microedition/lcdui/List;
    //   1638: iload_3
    //   1639: invokevirtual getString : (I)Ljava/lang/String;
    //   1642: putfield d : Ljava/lang/String;
    //   1645: aload_0
    //   1646: getfield a : LKD/ae;
    //   1649: getfield c : LKD/i;
    //   1652: getfield d : LKD/af;
    //   1655: aload_0
    //   1656: getfield d : Ljava/lang/String;
    //   1659: invokevirtual c : (Ljava/lang/String;)[I
    //   1662: dup
    //   1663: astore #4
    //   1665: ifnull -> 1716
    //   1668: aload #4
    //   1670: arraylength
    //   1671: ifle -> 1716
    //   1674: aload_0
    //   1675: getfield a : LKD/ae;
    //   1678: invokevirtual e : ()V
    //   1681: aload_0
    //   1682: invokespecial z : ()V
    //   1685: aload_0
    //   1686: getfield a : LKD/ae;
    //   1689: getfield e : LKD/b;
    //   1692: aload #4
    //   1694: invokevirtual a : ([I)V
    //   1697: aload_0
    //   1698: getfield a : LKD/ae;
    //   1701: getfield e : LKD/b;
    //   1704: iconst_0
    //   1705: iconst_1
    //   1706: invokevirtual a : (IZ)V
    //   1709: aload_0
    //   1710: getfield a : LKD/ae;
    //   1713: invokevirtual g : ()V
    //   1716: return
    //   1717: aload_0
    //   1718: getfield b : I
    //   1721: bipush #8
    //   1723: if_icmpne -> 1822
    //   1726: aload_0
    //   1727: getfield R : Ljavax/microedition/lcdui/List;
    //   1730: invokevirtual getSelectedIndex : ()I
    //   1733: dup
    //   1734: istore_3
    //   1735: iflt -> 1821
    //   1738: aload_0
    //   1739: aload_0
    //   1740: getfield R : Ljavax/microedition/lcdui/List;
    //   1743: iload_3
    //   1744: invokevirtual getString : (I)Ljava/lang/String;
    //   1747: putfield f : Ljava/lang/String;
    //   1750: aload_0
    //   1751: getfield a : LKD/ae;
    //   1754: getfield c : LKD/i;
    //   1757: getfield d : LKD/af;
    //   1760: aload_0
    //   1761: getfield f : Ljava/lang/String;
    //   1764: invokevirtual d : (Ljava/lang/String;)[I
    //   1767: dup
    //   1768: astore #4
    //   1770: ifnull -> 1821
    //   1773: aload #4
    //   1775: arraylength
    //   1776: ifle -> 1821
    //   1779: aload_0
    //   1780: getfield a : LKD/ae;
    //   1783: invokevirtual e : ()V
    //   1786: aload_0
    //   1787: invokespecial z : ()V
    //   1790: aload_0
    //   1791: getfield a : LKD/ae;
    //   1794: getfield e : LKD/b;
    //   1797: aload #4
    //   1799: invokevirtual a : ([I)V
    //   1802: aload_0
    //   1803: getfield a : LKD/ae;
    //   1806: getfield e : LKD/b;
    //   1809: iconst_0
    //   1810: iconst_1
    //   1811: invokevirtual a : (IZ)V
    //   1814: aload_0
    //   1815: getfield a : LKD/ae;
    //   1818: invokevirtual g : ()V
    //   1821: return
    //   1822: aload_0
    //   1823: getfield b : I
    //   1826: bipush #20
    //   1828: if_icmpne -> 3237
    //   1831: aload_0
    //   1832: getfield R : Ljavax/microedition/lcdui/List;
    //   1835: invokevirtual getSelectedIndex : ()I
    //   1838: dup
    //   1839: istore_3
    //   1840: iflt -> 1954
    //   1843: aload_0
    //   1844: aload_0
    //   1845: getfield R : Ljavax/microedition/lcdui/List;
    //   1848: iload_3
    //   1849: invokevirtual getString : (I)Ljava/lang/String;
    //   1852: putfield f : Ljava/lang/String;
    //   1855: iload_3
    //   1856: ifne -> 1879
    //   1859: aload_0
    //   1860: getfield a : LKD/ae;
    //   1863: getfield c : LKD/i;
    //   1866: getfield d : LKD/af;
    //   1869: aload_0
    //   1870: getfield d : Ljava/lang/String;
    //   1873: invokevirtual c : (Ljava/lang/String;)[I
    //   1876: goto -> 1900
    //   1879: aload_0
    //   1880: getfield a : LKD/ae;
    //   1883: getfield c : LKD/i;
    //   1886: getfield d : LKD/af;
    //   1889: aload_0
    //   1890: getfield d : Ljava/lang/String;
    //   1893: aload_0
    //   1894: getfield f : Ljava/lang/String;
    //   1897: invokevirtual a : (Ljava/lang/String;Ljava/lang/String;)[I
    //   1900: dup
    //   1901: astore #4
    //   1903: ifnull -> 1954
    //   1906: aload #4
    //   1908: arraylength
    //   1909: ifle -> 1954
    //   1912: aload_0
    //   1913: getfield a : LKD/ae;
    //   1916: invokevirtual e : ()V
    //   1919: aload_0
    //   1920: invokespecial z : ()V
    //   1923: aload_0
    //   1924: getfield a : LKD/ae;
    //   1927: getfield e : LKD/b;
    //   1930: aload #4
    //   1932: invokevirtual a : ([I)V
    //   1935: aload_0
    //   1936: getfield a : LKD/ae;
    //   1939: getfield e : LKD/b;
    //   1942: iconst_0
    //   1943: iconst_1
    //   1944: invokevirtual a : (IZ)V
    //   1947: aload_0
    //   1948: getfield a : LKD/ae;
    //   1951: invokevirtual g : ()V
    //   1954: return
    //   1955: aload_1
    //   1956: aload_0
    //   1957: getfield O : Ljavax/microedition/lcdui/Command;
    //   1960: if_acmpne -> 1999
    //   1963: aload_0
    //   1964: getfield L : LKD/ak;
    //   1967: invokevirtual getSelectedIndex : ()I
    //   1970: dup
    //   1971: istore_3
    //   1972: iflt -> 1998
    //   1975: aload_0
    //   1976: getfield a : LKD/ae;
    //   1979: getfield j : LKD/s;
    //   1982: aload_0
    //   1983: getfield N : Ljavax/microedition/lcdui/Command;
    //   1986: aload_0
    //   1987: aload_0
    //   1988: getfield L : LKD/ak;
    //   1991: iload_3
    //   1992: invokevirtual getString : (I)Ljava/lang/String;
    //   1995: invokevirtual a : (Ljavax/microedition/lcdui/Command;Ljavax/microedition/lcdui/CommandListener;Ljava/lang/String;)V
    //   1998: return
    //   1999: aload_1
    //   2000: aload_0
    //   2001: getfield P : Ljavax/microedition/lcdui/Command;
    //   2004: if_acmpne -> 2024
    //   2007: aload_0
    //   2008: getfield a : LKD/ae;
    //   2011: getfield j : LKD/s;
    //   2014: aload_0
    //   2015: getfield M : Ljavax/microedition/lcdui/Command;
    //   2018: aload_0
    //   2019: aconst_null
    //   2020: invokevirtual a : (Ljavax/microedition/lcdui/Command;Ljavax/microedition/lcdui/CommandListener;Ljava/lang/String;)V
    //   2023: return
    //   2024: aload_1
    //   2025: aload_0
    //   2026: getfield Q : Ljavax/microedition/lcdui/Command;
    //   2029: if_acmpne -> 2067
    //   2032: aload_0
    //   2033: getfield L : LKD/ak;
    //   2036: invokevirtual getSelectedIndex : ()I
    //   2039: dup
    //   2040: istore_3
    //   2041: iflt -> 2066
    //   2044: aload_0
    //   2045: getfield a : LKD/ae;
    //   2048: getfield c : LKD/i;
    //   2051: iload_3
    //   2052: invokevirtual a : (I)Z
    //   2055: ifeq -> 2066
    //   2058: aload_0
    //   2059: getfield L : LKD/ak;
    //   2062: iload_3
    //   2063: invokevirtual delete : (I)V
    //   2066: return
    //   2067: aload_1
    //   2068: aload_0
    //   2069: getfield M : Ljavax/microedition/lcdui/Command;
    //   2072: if_acmpne -> 2147
    //   2075: aload_0
    //   2076: getfield a : LKD/ae;
    //   2079: getfield j : LKD/s;
    //   2082: getfield n : [Ljava/lang/String;
    //   2085: ifnull -> 2132
    //   2088: aload_0
    //   2089: getfield a : LKD/ae;
    //   2092: getfield c : LKD/i;
    //   2095: aload_0
    //   2096: getfield a : LKD/ae;
    //   2099: getfield j : LKD/s;
    //   2102: getfield n : [Ljava/lang/String;
    //   2105: iconst_0
    //   2106: aaload
    //   2107: invokevirtual a : (Ljava/lang/String;)Z
    //   2110: ifeq -> 2132
    //   2113: aload_0
    //   2114: getfield L : LKD/ak;
    //   2117: aload_0
    //   2118: getfield a : LKD/ae;
    //   2121: getfield j : LKD/s;
    //   2124: getfield n : [Ljava/lang/String;
    //   2127: iconst_0
    //   2128: aaload
    //   2129: invokevirtual a : (Ljava/lang/String;)V
    //   2132: aload_0
    //   2133: getfield a : LKD/ae;
    //   2136: getfield a : Lfavax/microedition/lcdui/Display;
    //   2139: aload_0
    //   2140: getfield L : LKD/ak;
    //   2143: invokevirtual setCurrent : (Ljavax/microedition/lcdui/Displayable;)V
    //   2146: return
    //   2147: aload_1
    //   2148: aload_0
    //   2149: getfield N : Ljavax/microedition/lcdui/Command;
    //   2152: if_acmpne -> 2237
    //   2155: aload_0
    //   2156: getfield a : LKD/ae;
    //   2159: getfield j : LKD/s;
    //   2162: getfield n : [Ljava/lang/String;
    //   2165: ifnull -> 2222
    //   2168: aload_0
    //   2169: getfield L : LKD/ak;
    //   2172: invokevirtual getSelectedIndex : ()I
    //   2175: istore_3
    //   2176: aload_0
    //   2177: getfield a : LKD/ae;
    //   2180: getfield c : LKD/i;
    //   2183: iload_3
    //   2184: aload_0
    //   2185: getfield a : LKD/ae;
    //   2188: getfield j : LKD/s;
    //   2191: getfield n : [Ljava/lang/String;
    //   2194: iconst_0
    //   2195: aaload
    //   2196: invokevirtual a : (ILjava/lang/String;)Z
    //   2199: ifeq -> 2222
    //   2202: aload_0
    //   2203: getfield L : LKD/ak;
    //   2206: iload_3
    //   2207: aload_0
    //   2208: getfield a : LKD/ae;
    //   2211: getfield j : LKD/s;
    //   2214: getfield n : [Ljava/lang/String;
    //   2217: iconst_0
    //   2218: aaload
    //   2219: invokevirtual a : (ILjava/lang/String;)V
    //   2222: aload_0
    //   2223: getfield a : LKD/ae;
    //   2226: getfield a : Lfavax/microedition/lcdui/Display;
    //   2229: aload_0
    //   2230: getfield L : LKD/ak;
    //   2233: invokevirtual setCurrent : (Ljavax/microedition/lcdui/Displayable;)V
    //   2236: return
    //   2237: aload_1
    //   2238: aload_0
    //   2239: getfield n : Ljavax/microedition/lcdui/Command;
    //   2242: if_acmpne -> 2287
    //   2245: aload_0
    //   2246: getfield m : LKD/z;
    //   2249: invokevirtual getSelectedIndex : ()I
    //   2252: dup
    //   2253: istore_3
    //   2254: ifne -> 2263
    //   2257: aload_0
    //   2258: bipush #24
    //   2260: goto -> 2275
    //   2263: iload_3
    //   2264: ifle -> 2286
    //   2267: aload_0
    //   2268: iload_3
    //   2269: putfield k : I
    //   2272: aload_0
    //   2273: bipush #25
    //   2275: putfield b : I
    //   2278: aload_0
    //   2279: invokevirtual a : ()V
    //   2282: aload_0
    //   2283: invokespecial B : ()V
    //   2286: return
    //   2287: aload_1
    //   2288: aload_0
    //   2289: getfield o : Ljavax/microedition/lcdui/Command;
    //   2292: if_acmpne -> 2382
    //   2295: aload_0
    //   2296: getfield m : LKD/z;
    //   2299: invokevirtual getSelectedIndex : ()I
    //   2302: dup
    //   2303: istore_3
    //   2304: ifle -> 2381
    //   2307: aload_0
    //   2308: aload_0
    //   2309: getfield a : LKD/ae;
    //   2312: getfield d : LKD/y;
    //   2315: iload_3
    //   2316: invokevirtual b : (I)[I
    //   2319: putfield g : [I
    //   2322: aload_0
    //   2323: getfield g : [I
    //   2326: ifnull -> 2381
    //   2329: aload_0
    //   2330: getfield g : [I
    //   2333: arraylength
    //   2334: ifle -> 2381
    //   2337: aload_0
    //   2338: getfield a : LKD/ae;
    //   2341: invokevirtual e : ()V
    //   2344: aload_0
    //   2345: invokespecial B : ()V
    //   2348: aload_0
    //   2349: getfield a : LKD/ae;
    //   2352: getfield e : LKD/b;
    //   2355: aload_0
    //   2356: getfield g : [I
    //   2359: invokevirtual a : ([I)V
    //   2362: aload_0
    //   2363: getfield a : LKD/ae;
    //   2366: getfield e : LKD/b;
    //   2369: iconst_0
    //   2370: iconst_1
    //   2371: invokevirtual a : (IZ)V
    //   2374: aload_0
    //   2375: getfield a : LKD/ae;
    //   2378: invokevirtual g : ()V
    //   2381: return
    //   2382: aload_1
    //   2383: aload_0
    //   2384: getfield p : Ljavax/microedition/lcdui/Command;
    //   2387: if_acmpne -> 2422
    //   2390: aload_0
    //   2391: getfield m : LKD/z;
    //   2394: invokevirtual getSelectedIndex : ()I
    //   2397: dup
    //   2398: istore_3
    //   2399: ifle -> 2421
    //   2402: aload_0
    //   2403: iload_3
    //   2404: putfield k : I
    //   2407: aload_0
    //   2408: bipush #27
    //   2410: putfield b : I
    //   2413: aload_0
    //   2414: invokevirtual a : ()V
    //   2417: aload_0
    //   2418: invokespecial B : ()V
    //   2421: return
    //   2422: aload_1
    //   2423: aload_0
    //   2424: getfield q : Ljavax/microedition/lcdui/Command;
    //   2427: if_acmpne -> 2445
    //   2430: aload_0
    //   2431: bipush #24
    //   2433: putfield b : I
    //   2436: aload_0
    //   2437: invokevirtual a : ()V
    //   2440: aload_0
    //   2441: invokespecial B : ()V
    //   2444: return
    //   2445: aload_1
    //   2446: aload_0
    //   2447: getfield s : Ljavax/microedition/lcdui/Command;
    //   2450: if_acmpne -> 2493
    //   2453: aload_0
    //   2454: getfield m : LKD/z;
    //   2457: invokevirtual getSelectedIndex : ()I
    //   2460: dup
    //   2461: istore_3
    //   2462: ifle -> 2492
    //   2465: aload_0
    //   2466: getfield a : LKD/ae;
    //   2469: invokevirtual e : ()V
    //   2472: aload_0
    //   2473: invokespecial B : ()V
    //   2476: aload_0
    //   2477: getfield a : LKD/ae;
    //   2480: getfield d : LKD/y;
    //   2483: iload_3
    //   2484: invokevirtual a : (I)B
    //   2487: pop
    //   2488: aload_0
    //   2489: invokespecial A : ()V
    //   2492: return
    //   2493: aload_1
    //   2494: aload_0
    //   2495: getfield r : Ljavax/microedition/lcdui/Command;
    //   2498: if_acmpne -> 2533
    //   2501: aload_0
    //   2502: getfield m : LKD/z;
    //   2505: invokevirtual getSelectedIndex : ()I
    //   2508: dup
    //   2509: istore_3
    //   2510: ifle -> 2532
    //   2513: aload_0
    //   2514: iload_3
    //   2515: putfield k : I
    //   2518: aload_0
    //   2519: bipush #26
    //   2521: putfield b : I
    //   2524: aload_0
    //   2525: invokevirtual a : ()V
    //   2528: aload_0
    //   2529: invokespecial B : ()V
    //   2532: return
    //   2533: aload_1
    //   2534: aload_0
    //   2535: getfield v : Ljavax/microedition/lcdui/Command;
    //   2538: if_acmpne -> 2611
    //   2541: aload_0
    //   2542: getfield u : LKD/aj;
    //   2545: invokevirtual getString : ()Ljava/lang/String;
    //   2548: astore_3
    //   2549: aload_0
    //   2550: getfield a : LKD/ae;
    //   2553: getfield d : LKD/y;
    //   2556: aload_3
    //   2557: invokevirtual a : (Ljava/lang/String;)B
    //   2560: dup
    //   2561: istore #4
    //   2563: ifne -> 2587
    //   2566: aload_0
    //   2567: aload_0
    //   2568: getfield a : LKD/ae;
    //   2571: getfield d : LKD/y;
    //   2574: invokevirtual b : ()I
    //   2577: putfield k : I
    //   2580: aload_0
    //   2581: invokespecial V : ()V
    //   2584: goto -> 3237
    //   2587: iload #4
    //   2589: iconst_3
    //   2590: if_icmpne -> 2610
    //   2593: aload_0
    //   2594: getfield a : LKD/ae;
    //   2597: ldc_w 'Новый плейлист'
    //   2600: ldc 'Данное имя плейлиста уже используется!'
    //   2602: aconst_null
    //   2603: aconst_null
    //   2604: sipush #2000
    //   2607: invokevirtual a : (Ljava/lang/String;Ljava/lang/String;Ljavax/microedition/lcdui/Image;Ljavax/microedition/lcdui/AlertType;I)V
    //   2610: return
    //   2611: aload_1
    //   2612: aload_0
    //   2613: getfield w : Ljavax/microedition/lcdui/Command;
    //   2616: if_acmpne -> 2633
    //   2619: aload_0
    //   2620: iconst_4
    //   2621: putfield b : I
    //   2624: aload_0
    //   2625: invokespecial D : ()V
    //   2628: aload_0
    //   2629: invokevirtual a : ()V
    //   2632: return
    //   2633: aload_1
    //   2634: aload_0
    //   2635: getfield x : Ljavax/microedition/lcdui/Command;
    //   2638: if_acmpne -> 2722
    //   2641: aload_0
    //   2642: getfield u : LKD/aj;
    //   2645: invokevirtual getString : ()Ljava/lang/String;
    //   2648: astore_3
    //   2649: aload_0
    //   2650: getfield a : LKD/ae;
    //   2653: getfield d : LKD/y;
    //   2656: aload_0
    //   2657: getfield k : I
    //   2660: aload_3
    //   2661: invokevirtual a : (ILjava/lang/String;)B
    //   2664: dup
    //   2665: istore #4
    //   2667: ifne -> 2698
    //   2670: aload_0
    //   2671: iconst_4
    //   2672: putfield b : I
    //   2675: aload_0
    //   2676: invokevirtual a : ()V
    //   2679: aload_0
    //   2680: getfield m : LKD/z;
    //   2683: aload_0
    //   2684: getfield k : I
    //   2687: iconst_1
    //   2688: invokevirtual setSelectedIndex : (IZ)V
    //   2691: aload_0
    //   2692: invokespecial D : ()V
    //   2695: goto -> 3237
    //   2698: iload #4
    //   2700: iconst_3
    //   2701: if_icmpne -> 2721
    //   2704: aload_0
    //   2705: getfield a : LKD/ae;
    //   2708: ldc_w 'Изменение...'
    //   2711: ldc 'Данное имя плейлиста уже используется!'
    //   2713: aconst_null
    //   2714: aconst_null
    //   2715: sipush #2000
    //   2718: invokevirtual a : (Ljava/lang/String;Ljava/lang/String;Ljavax/microedition/lcdui/Image;Ljavax/microedition/lcdui/AlertType;I)V
    //   2721: return
    //   2722: aload_1
    //   2723: aload_0
    //   2724: getfield B : Ljavax/microedition/lcdui/Command;
    //   2727: if_acmpne -> 2787
    //   2730: aload_0
    //   2731: getfield R : Ljavax/microedition/lcdui/List;
    //   2734: invokevirtual getSelectedIndex : ()I
    //   2737: dup
    //   2738: istore_3
    //   2739: iflt -> 2786
    //   2742: aload_0
    //   2743: getfield a : LKD/ae;
    //   2746: invokevirtual e : ()V
    //   2749: aload_0
    //   2750: invokespecial G : ()V
    //   2753: aload_0
    //   2754: getfield a : LKD/ae;
    //   2757: getfield e : LKD/b;
    //   2760: aload_0
    //   2761: getfield g : [I
    //   2764: invokevirtual a : ([I)V
    //   2767: aload_0
    //   2768: getfield a : LKD/ae;
    //   2771: getfield e : LKD/b;
    //   2774: iload_3
    //   2775: iconst_1
    //   2776: invokevirtual a : (IZ)V
    //   2779: aload_0
    //   2780: getfield a : LKD/ae;
    //   2783: invokevirtual g : ()V
    //   2786: return
    //   2787: aload_1
    //   2788: aload_0
    //   2789: getfield C : Ljavax/microedition/lcdui/Command;
    //   2792: if_acmpne -> 2813
    //   2795: aload_0
    //   2796: getfield R : Ljavax/microedition/lcdui/List;
    //   2799: invokevirtual getSelectedIndex : ()I
    //   2802: dup
    //   2803: istore_3
    //   2804: iflt -> 2812
    //   2807: aload_0
    //   2808: iload_3
    //   2809: invokespecial a : (I)V
    //   2812: return
    //   2813: aload_1
    //   2814: aload_0
    //   2815: getfield A : Ljavax/microedition/lcdui/Command;
    //   2818: if_acmpne -> 2840
    //   2821: aload_0
    //   2822: getfield a : LKD/ae;
    //   2825: getfield a : Lfavax/microedition/lcdui/Display;
    //   2828: aload_0
    //   2829: getfield R : Ljavax/microedition/lcdui/List;
    //   2832: invokevirtual setCurrent : (Ljavax/microedition/lcdui/Displayable;)V
    //   2835: aload_0
    //   2836: invokespecial J : ()V
    //   2839: return
    //   2840: aload_1
    //   2841: aload_0
    //   2842: getfield D : Ljavax/microedition/lcdui/Command;
    //   2845: if_acmpne -> 2868
    //   2848: aload_0
    //   2849: invokespecial V : ()V
    //   2852: aload_0
    //   2853: aload_0
    //   2854: getfield R : Ljavax/microedition/lcdui/List;
    //   2857: invokevirtual getSelectedIndex : ()I
    //   2860: putfield y : I
    //   2863: aload_0
    //   2864: invokespecial G : ()V
    //   2867: return
    //   2868: aload_1
    //   2869: aload_0
    //   2870: getfield E : Ljavax/microedition/lcdui/Command;
    //   2873: if_acmpne -> 2934
    //   2876: aload_0
    //   2877: getfield R : Ljavax/microedition/lcdui/List;
    //   2880: invokevirtual getSelectedIndex : ()I
    //   2883: dup
    //   2884: istore_3
    //   2885: iflt -> 2933
    //   2888: aload_0
    //   2889: getfield a : LKD/ae;
    //   2892: getfield d : LKD/y;
    //   2895: aload_0
    //   2896: getfield k : I
    //   2899: iload_3
    //   2900: invokevirtual a : (II)V
    //   2903: aload_0
    //   2904: aload_0
    //   2905: getfield a : LKD/ae;
    //   2908: getfield c : LKD/i;
    //   2911: getfield d : LKD/af;
    //   2914: aload_0
    //   2915: getfield g : [I
    //   2918: iload_3
    //   2919: invokevirtual b : ([II)[I
    //   2922: putfield g : [I
    //   2925: aload_0
    //   2926: getfield R : Ljavax/microedition/lcdui/List;
    //   2929: iload_3
    //   2930: invokevirtual delete : (I)V
    //   2933: return
    //   2934: aload_1
    //   2935: aload_0
    //   2936: getfield F : Ljavax/microedition/lcdui/Command;
    //   2939: if_acmpne -> 2978
    //   2942: aload_0
    //   2943: getfield a : LKD/ae;
    //   2946: getfield d : LKD/y;
    //   2949: getfield c : [I
    //   2952: aload_0
    //   2953: getfield k : I
    //   2956: iaload
    //   2957: dup
    //   2958: istore_3
    //   2959: iconst_1
    //   2960: if_icmple -> 2977
    //   2963: aload_0
    //   2964: bipush #28
    //   2966: putfield b : I
    //   2969: aload_0
    //   2970: invokevirtual a : ()V
    //   2973: aload_0
    //   2974: invokespecial G : ()V
    //   2977: return
    //   2978: aload_1
    //   2979: aload_0
    //   2980: getfield I : Ljavax/microedition/lcdui/Command;
    //   2983: if_acmpne -> 3001
    //   2986: aload_0
    //   2987: bipush #25
    //   2989: putfield b : I
    //   2992: aload_0
    //   2993: invokevirtual a : ()V
    //   2996: aload_0
    //   2997: invokespecial M : ()V
    //   3000: return
    //   3001: aload_1
    //   3002: aload_0
    //   3003: getfield H : Ljavax/microedition/lcdui/Command;
    //   3006: if_acmpne -> 3063
    //   3009: aload_0
    //   3010: getfield G : LKD/r;
    //   3013: invokevirtual getSelectedIndex : ()I
    //   3016: dup
    //   3017: istore_3
    //   3018: iflt -> 3062
    //   3021: aload_0
    //   3022: getfield a : LKD/ae;
    //   3025: invokevirtual e : ()V
    //   3028: iinc #3, 1
    //   3031: aload_0
    //   3032: getfield a : LKD/ae;
    //   3035: getfield d : LKD/y;
    //   3038: aload_0
    //   3039: getfield k : I
    //   3042: iload_3
    //   3043: iconst_0
    //   3044: invokevirtual a : (III)I
    //   3047: pop
    //   3048: aload_0
    //   3049: bipush #25
    //   3051: putfield b : I
    //   3054: aload_0
    //   3055: invokevirtual a : ()V
    //   3058: aload_0
    //   3059: invokespecial M : ()V
    //   3062: return
    //   3063: aload_1
    //   3064: aload_0
    //   3065: getfield ae : Ljavax/microedition/lcdui/Command;
    //   3068: if_acmpne -> 3158
    //   3071: aload_0
    //   3072: getfield ad : LKD/o;
    //   3075: invokevirtual a : ()[Ljava/lang/String;
    //   3078: dup
    //   3079: astore_3
    //   3080: ifnull -> 3139
    //   3083: aload_3
    //   3084: arraylength
    //   3085: ifle -> 3135
    //   3088: aload_0
    //   3089: getfield a : LKD/ae;
    //   3092: getfield c : LKD/i;
    //   3095: aconst_null
    //   3096: putfield c : [Ljava/lang/String;
    //   3099: aload_0
    //   3100: getfield a : LKD/ae;
    //   3103: getfield c : LKD/i;
    //   3106: aload_3
    //   3107: putfield c : [Ljava/lang/String;
    //   3110: aload_0
    //   3111: iconst_5
    //   3112: putfield b : I
    //   3115: aload_0
    //   3116: invokevirtual a : ()V
    //   3119: aload_0
    //   3120: invokespecial O : ()V
    //   3123: aload_0
    //   3124: getfield J : LKD/q;
    //   3127: iconst_1
    //   3128: iconst_1
    //   3129: invokevirtual setSelectedIndex : (IZ)V
    //   3132: goto -> 3237
    //   3135: aload_0
    //   3136: goto -> 3140
    //   3139: aload_0
    //   3140: getfield a : LKD/ae;
    //   3143: ldc_w 'Информация'
    //   3146: ldc_w 'Необходимо выделить хотя бы один тип файлов!'
    //   3149: aconst_null
    //   3150: aconst_null
    //   3151: sipush #2000
    //   3154: invokevirtual a : (Ljava/lang/String;Ljava/lang/String;Ljavax/microedition/lcdui/Image;Ljavax/microedition/lcdui/AlertType;I)V
    //   3157: return
    //   3158: aload_1
    //   3159: aload_0
    //   3160: getfield ac : Ljavax/microedition/lcdui/Command;
    //   3163: if_acmpne -> 3225
    //   3166: aload_0
    //   3167: getfield a : LKD/ae;
    //   3170: aload_0
    //   3171: getfield ab : LKD/j;
    //   3174: getfield a : Ljavax/microedition/lcdui/ChoiceGroup;
    //   3177: iconst_0
    //   3178: invokevirtual isSelected : (I)Z
    //   3181: putfield k : Z
    //   3184: aload_0
    //   3185: getfield a : LKD/ae;
    //   3188: aload_0
    //   3189: getfield ab : LKD/j;
    //   3192: getfield a : Ljavax/microedition/lcdui/ChoiceGroup;
    //   3195: iconst_1
    //   3196: invokevirtual isSelected : (I)Z
    //   3199: putfield l : Z
    //   3202: aload_0
    //   3203: iconst_5
    //   3204: putfield b : I
    //   3207: aload_0
    //   3208: invokevirtual a : ()V
    //   3211: aload_0
    //   3212: getfield J : LKD/q;
    //   3215: iconst_0
    //   3216: iconst_1
    //   3217: invokevirtual setSelectedIndex : (IZ)V
    //   3220: aload_0
    //   3221: invokespecial Q : ()V
    //   3224: return
    //   3225: aload_1
    //   3226: aload_0
    //   3227: getfield l : Ljavax/microedition/lcdui/Command;
    //   3230: if_acmpne -> 3237
    //   3233: aload_0
    //   3234: invokespecial W : ()V
    //   3237: return
  }
  
  private void b() {
    this.h = new ab();
    this.h.setSelectCommand(this.T);
    this.h.addCommand(this.W);
    this.h.setCommandListener(this);
    this.a.a.setCurrent((Displayable)this.h);
  }
  
  private void c() {
    this.h.deleteAll();
    this.h = null;
  }
  
  private void d() {
    this.i = new a();
    this.i.setSelectCommand(this.T);
    this.i.addCommand(this.V);
    this.i.addCommand(this.S);
    this.i.setCommandListener(this);
    this.a.a.setCurrent((Displayable)this.i);
  }
  
  private void e() {
    this.i.deleteAll();
    this.i = null;
  }
  
  private void f() {
    this.j = new x();
    this.j.setSelectCommand(this.T);
    this.j.addCommand(this.S);
    this.j.setCommandListener(this);
    this.a.a.setCurrent((Displayable)this.j);
  }
  
  private void g() {
    this.j.deleteAll();
    this.j = null;
  }
  
  private void h() {
    this.J = new q();
    this.J.setSelectCommand(this.T);
    this.J.addCommand(this.S);
    this.J.setCommandListener(this);
    this.a.a.setCurrent((Displayable)this.J);
  }
  
  private void i() {
    this.J.deleteAll();
    this.J = null;
  }
  
  private void j() {
    this.K = new ai();
    this.K.addCommand(this.S);
    this.K.setCommandListener(this);
    this.a.a.setCurrent((Displayable)this.K);
  }
  
  private void k() {
    this.K.deleteAll();
    this.K = null;
  }
  
  private void l() {
    this.L = new ak(this.a.c.b);
    this.M = new Command("", 4, 4);
    this.N = new Command("", 4, 5);
    this.O = new Command("Изменить", 4, 0);
    this.P = new Command("Добавить", 4, 1);
    this.Q = new Command("Удалить", 4, 2);
    this.L.addCommand(this.S);
    this.L.addCommand(this.O);
    this.L.addCommand(this.P);
    this.L.addCommand(this.Q);
    this.L.setCommandListener(this);
    this.a.a.setCurrent((Displayable)this.L);
  }
  
  private void m() {
    this.L.deleteAll();
    this.L = null;
    this.Q = null;
    this.P = null;
    this.O = null;
    this.M = null;
  }
  
  private void n() {
    Image image = u.a("/images/lib/lib_music.png");
    Image[] arrayOfImage = new Image[arrayOfString.length];
    for (byte b = 0; b < arrayOfString.length; b++)
      arrayOfImage[b] = image; 
    String[] arrayOfString;
    this.R = ((arrayOfString = this.a.c.c()) != null) ? new List("Вся музыка", 3, arrayOfString, arrayOfImage) : new List("Вся музыка", 3);
    this.R.setSelectCommand(this.T);
    this.R.addCommand(this.U);
    this.R.addCommand(this.S);
    this.R.setCommandListener(this);
    this.a.a.setCurrent((Displayable)this.R);
  }
  
  private void o() {
    if (this.a.c == null)
      return; 
    Image image = u.a("/images/lib/lib_artist.png");
    Image[] arrayOfImage = new Image[arrayOfString.length];
    for (byte b = 0; b < arrayOfString.length; b++)
      arrayOfImage[b] = image; 
    String[] arrayOfString;
    this.R = ((arrayOfString = this.a.c.e()) != null) ? new List("Исполнители", 3, arrayOfString, arrayOfImage) : new List("Исполнители", 3);
    this.R.setSelectCommand(this.T);
    this.R.addCommand(this.U);
    this.R.addCommand(this.V);
    this.R.addCommand(this.S);
    this.R.setCommandListener(this);
    this.a.a.setCurrent((Displayable)this.R);
  }
  
  private void p() {
    this.R.deleteAll();
    this.R = null;
  }
  
  private void q() {
    if (this.a.c == null)
      return; 
    Image image = u.a("/images/lib/lib_album.png");
    Image[] arrayOfImage = new Image[arrayOfString.length];
    for (byte b = 0; b < arrayOfString.length; b++)
      arrayOfImage[b] = image; 
    String[] arrayOfString;
    this.R = ((arrayOfString = this.a.c.f()) != null) ? new List("Альбомы", 3, arrayOfString, arrayOfImage) : new List("Альбомы", 3);
    this.R.setSelectCommand(this.T);
    this.R.addCommand(this.U);
    this.R.addCommand(this.V);
    this.R.addCommand(this.S);
    this.R.setCommandListener(this);
    this.a.a.setCurrent((Displayable)this.R);
  }
  
  private void r() {
    this.R.deleteAll();
    this.R = null;
  }
  
  private void s() {
    if (this.a.c == null)
      return; 
    Image image = u.a("/images/lib/lib_allvideo.png");
    Image[] arrayOfImage = new Image[arrayOfString.length];
    for (byte b = 0; b < arrayOfString.length; b++)
      arrayOfImage[b] = image; 
    String[] arrayOfString;
    this.R = ((arrayOfString = this.a.c.d()) != null) ? new List("Все видео", 3, arrayOfString, arrayOfImage) : new List("Все видео", 3);
    this.R.setSelectCommand(this.T);
    this.R.addCommand(this.U);
    this.R.addCommand(this.S);
    this.R.setCommandListener(this);
    this.a.a.setCurrent((Displayable)this.R);
  }
  
  private void t() {
    if (this.a.c == null)
      return; 
    if (this.d == null)
      return; 
    Image image = u.a("/images/lib/lib_album.png");
    Image[] arrayOfImage = new Image[arrayOfString.length];
    for (byte b = 0; b < arrayOfString.length; b++)
      arrayOfImage[b] = image; 
    String[] arrayOfString;
    this.R = ((arrayOfString = this.a.c.d.b(this.d)) != null) ? new List(this.d, 3, arrayOfString, arrayOfImage) : new List(this.d, 3);
    this.R.setSelectCommand(this.T);
    this.R.addCommand(this.U);
    this.R.addCommand(this.V);
    this.R.addCommand(this.S);
    this.R.setCommandListener(this);
    this.a.a.setCurrent((Displayable)this.R);
  }
  
  private void u() {
    this.R.deleteAll();
    this.R = null;
  }
  
  private void v() {
    if (this.f == null)
      return; 
    this.g = null;
    this.g = this.a.c.d.d(this.f);
    String[] arrayOfString;
    if ((arrayOfString = this.a.c.d.a(this.g)) != null) {
      Image image = u.a("/images/lib/lib_music.png");
      Image[] arrayOfImage = new Image[arrayOfString.length];
      for (byte b = 0; b < arrayOfString.length; b++)
        arrayOfImage[b] = image; 
      this.R = new List(this.f, 3, arrayOfString, arrayOfImage);
    } 
    this.R.setSelectCommand(this.T);
    this.R.addCommand(this.U);
    this.R.addCommand(this.S);
    this.R.setCommandListener(this);
    this.a.a.setCurrent((Displayable)this.R);
  }
  
  private void w() {
    this.R.deleteAll();
    this.R = null;
  }
  
  private void x() {
    if (this.d == null)
      return; 
    this.g = null;
    this.g = this.a.c.d.c(this.d);
    String[] arrayOfString;
    if ((arrayOfString = this.a.c.d.a(this.g)) != null) {
      Image image = u.a("/images/lib/lib_music.png");
      Image[] arrayOfImage = new Image[arrayOfString.length];
      for (byte b = 0; b < arrayOfString.length; b++)
        arrayOfImage[b] = image; 
      this.R = new List("Дорожки", 3, arrayOfString, arrayOfImage);
    } 
    this.R.setSelectCommand(this.T);
    this.R.addCommand(this.U);
    this.R.addCommand(this.S);
    this.R.setCommandListener(this);
    this.a.a.setCurrent((Displayable)this.R);
  }
  
  private void y() {
    if (this.d == null)
      return; 
    if (this.f == null)
      return; 
    this.g = null;
    this.g = this.a.c.d.a(this.d, this.f);
    String[] arrayOfString;
    if ((arrayOfString = this.a.c.d.a(this.g)) != null) {
      Image image = u.a("/images/lib/lib_music.png");
      Image[] arrayOfImage = new Image[arrayOfString.length];
      for (byte b = 0; b < arrayOfString.length; b++)
        arrayOfImage[b] = image; 
      this.R = new List(this.f, 3, arrayOfString, arrayOfImage);
    } 
    this.R.setSelectCommand(this.T);
    this.R.addCommand(this.U);
    this.R.addCommand(this.S);
    this.R.setCommandListener(this);
    this.a.a.setCurrent((Displayable)this.R);
  }
  
  private void z() {
    this.R.deleteAll();
    this.R = null;
  }
  
  private void A() {
    this.n = new Command("Открыть", 4, 0);
    this.o = new Command("Воспроизвести", 4, 1);
    this.p = new Command("Информация", 4, 2);
    this.q = new Command("Создать", 4, 3);
    this.r = new Command("Изменить имя", 4, 4);
    this.s = new Command("Удалить", 4, 5);
    this.m = new z();
    String[] arrayOfString;
    if ((arrayOfString = this.a.d.a()) != null)
      for (byte b = 0; b < arrayOfString.length; b++)
        this.m.a(arrayOfString[b]);  
    this.m.setSelectCommand(this.n);
    this.m.addCommand(this.S);
    this.m.addCommand(this.o);
    this.m.addCommand(this.p);
    this.m.addCommand(this.q);
    this.m.addCommand(this.r);
    this.m.addCommand(this.s);
    this.m.addCommand(this.S);
    this.m.setCommandListener(this);
    this.a.a.setCurrent((Displayable)this.m);
  }
  
  private void B() {
    this.m.deleteAll();
    this.m = null;
    this.n = null;
    this.o = null;
    this.p = null;
    this.q = null;
    this.s = null;
    this.r = null;
  }
  
  private void C() {
    this.v = new Command("Ok", 4, 0);
    this.w = new Command("Отмена", 2, 1);
    this.u = new aj();
    this.u.addCommand(this.v);
    this.u.addCommand(this.w);
    this.u.setCommandListener(this);
    this.a.a.setCurrent((Displayable)this.u);
  }
  
  private void D() {
    this.u = null;
    this.v = null;
    this.w = null;
    this.x = null;
  }
  
  private void E() {
    this.x = new Command("Ok", 4, 0);
    this.w = new Command("Отмена", 2, 1);
    this.u = new aj();
    this.u.setString(this.a.d.a[this.k]);
    this.u.addCommand(this.x);
    this.u.addCommand(this.w);
    this.u.setCommandListener(this);
    this.a.a.setCurrent((Displayable)this.u);
  }
  
  private void F() {
    this.g = null;
    this.g = this.a.d.b(this.k);
    Image image = u.a("/images/lib/lib_music.png");
    Image[] arrayOfImage = new Image[arrayOfString.length];
    for (byte b = 0; b < arrayOfString.length; b++)
      arrayOfImage[b] = image; 
    String[] arrayOfString;
    this.R = ((arrayOfString = this.a.c.d.a(this.g)) != null) ? new List(this.a.d.a[this.k], 3, arrayOfString, arrayOfImage) : new List(this.a.d.a[this.k], 3);
    this.B = new Command("Воспр.", 4, 0);
    this.C = new Command("Информация", 4, 1);
    this.D = new Command("Добавить файлы", 4, 2);
    this.E = new Command("Удалить", 4, 3);
    this.F = new Command("Сортировать", 4, 4);
    this.R.setSelectCommand(this.B);
    this.R.addCommand(this.C);
    this.R.addCommand(this.D);
    this.R.addCommand(this.E);
    this.R.addCommand(this.F);
    this.R.addCommand(this.S);
    this.R.setCommandListener(this);
    this.a.a.setCurrent((Displayable)this.R);
  }
  
  private void G() {
    z();
    this.B = null;
    this.C = null;
    this.D = null;
    this.E = null;
    this.F = null;
  }
  
  private void H() {
    if ((((this.k > 0) ? 1 : 0) & ((this.k <= this.a.d.b()) ? 1 : 0)) != 0) {
      this.t = new w(this.a.d.a[this.k], this.a.d.b[this.k], this.a.d.c[this.k]);
      this.t.addCommand(this.S);
      this.t.setCommandListener(this);
      this.a.a.setCurrent((Displayable)this.t);
    } 
  }
  
  private void I() {
    this.t = null;
  }
  
  private void a(int paramInt) {
    if (this.g != null)
      if ((((paramInt >= 0) ? 1 : 0) & ((paramInt < this.g.length) ? 1 : 0)) != 0) {
        int i = this.g[paramInt];
        this.z = null;
        this.a.e();
        this.z = new p(this.a.c.d.c[i], this.a.a);
        this.A = new Command("Назад", 2, 0);
        this.z.addCommand(this.A);
        this.z.setCommandListener(this);
      }  
  }
  
  private void J() {
    this.z = null;
    this.X = null;
    this.Y = null;
    this.A = null;
  }
  
  private void K() {
    if (this.d != null) {
      this.X = null;
      this.a.e();
      int i = 0;
      String[] arrayOfString;
      if ((arrayOfString = this.a.c.d.b(this.d)).length > 1)
        arrayOfString = this.a.c.d.b(arrayOfString, 0); 
      try {
        i = (this.a.c.d.c(this.d)).length;
      } catch (Exception exception) {}
      this.X = new h(this.d, arrayOfString, i);
      this.A = new Command("Назад", 2, 0);
      this.X.addCommand(this.A);
      this.X.setCommandListener(this);
      this.a.a.setCurrent((Displayable)this.X);
    } 
  }
  
  private void a(int paramInt, boolean paramBoolean) {
    if (this.f != null) {
      this.Y = null;
      this.a.e();
      int i = 0;
      if (paramInt == 1) {
        try {
          i = (this.a.c.d.d(this.f)).length;
        } catch (Exception exception) {}
      } else if (paramInt == 2) {
        if (paramBoolean) {
          try {
            i = (this.a.c.d.c(this.d)).length;
          } catch (Exception exception) {}
        } else {
          try {
            i = (this.a.c.d.a(this.d, this.f)).length;
          } catch (Exception exception) {}
        } 
      } 
      this.Y = new ah(this.f, i);
      this.f = null;
      this.A = new Command("Назад", 2, 0);
      this.Y.addCommand(this.A);
      this.Y.setCommandListener(this);
      this.a.a.setCurrent((Displayable)this.Y);
    } 
  }
  
  private void L() {
    this.G = new r();
    this.H = new Command("Ok", 4, 0);
    this.I = new Command("Отмена", 2, 1);
    this.G.setSelectCommand(this.H);
    this.G.addCommand(this.I);
    this.G.setCommandListener(this);
    this.a.a.setCurrent((Displayable)this.G);
  }
  
  private void M() {
    this.G.deleteAll();
    this.G = null;
    this.H = null;
    this.I = null;
  }
  
  private void N() {
    this.ad = new o(ag.a, ag.b, this.a.k());
    this.ae = new Command("Сохранить", 4, 0);
    this.ad.addCommand(this.S);
    this.ad.addCommand(this.ae);
    this.ad.setCommandListener(this);
    this.a.a.setCurrent((Displayable)this.ad);
  }
  
  private void O() {
    this.ad = null;
    this.ae = null;
  }
  
  private void P() {
    this.ab = new j();
    this.ab.a.setSelectedIndex(0, this.a.k);
    this.ab.a.setSelectedIndex(1, this.a.l);
    this.ac = new Command("Сохранить", 4, 0);
    this.ab.addCommand(this.S);
    this.ab.addCommand(this.ac);
    this.ab.setCommandListener(this);
    this.a.a.setCurrent((Displayable)this.ab);
  }
  
  private void Q() {
    this.ab = null;
    this.ac = null;
  }
  
  private void R() {
    this.Z = new g();
    this.Z.addCommand(this.S);
    this.Z.setCommandListener(this);
    this.a.a.setCurrent((Displayable)this.Z);
  }
  
  private void S() {
    this.Z = null;
  }
  
  private void T() {
    this.aa = new am();
    this.aa.addCommand(this.S);
    this.aa.setCommandListener(this);
    this.a.a.setCurrent((Displayable)this.aa);
  }
  
  private void U() {
    this.aa = null;
  }
  
  private void V() {
    if ((((this.k > 0) ? 1 : 0) | ((this.k < this.a.d.b()) ? 1 : 0)) != 0)
      this.a.j.a(this.l, this, this.a.k()); 
  }
  
  private void W() {
    this.a.e();
    int i;
    if (this.a.j.n != null && (i = this.a.j.n.length) > 0)
      this.a.d.a(this.k, this.a.j.n); 
    this.b = 25;
    a();
    D();
    if ((((this.y > 0) ? 1 : 0) & ((this.y < this.a.d.c[this.k]) ? 1 : 0)) != 0)
      this.R.setSelectedIndex(this.y, true); 
  }
}


/* Location:              D:\Desktop\kemulator\LocID_BitByByte.jar!\KD\d.class
 * Java compiler version: 1 (45.3)
 * JD-Core Version:       1.1.3
 */